Workbook

Sheet KPI
R1: Акмолинская
R2: Актюбинская
R3: Алматинская
R4: Атырауская
B5: ДГД | D5: Позиция | F5: Итоговый KPI | R5: ВКО
B6: г.Шымкент | D6: =VLOOKUP(B6,'KPI-20 ДГД'!A:I,9,0) -> 1 | F6: =VLOOKUP(B6,'KPI-20 ДГД'!A:H,8,0) -> 100 | R6: ЗКО
R7: Карагандинская
E8: млн.тг. | R8: Кызылординская
A9: № | B9: Показатель | C9: =MONTH(TODAY())-1&" месяцев "&YEAR(TODAY())&" года" -> 3 месяцев 2026 года | E9: Разница | F9: Исполнение, % | G9: Доля влияния | H9: Баллы | I9: Достигнут да/ нет | R9: Костанайская
C10: KPI | D10: Факт | R10: Мангистауская
A11: 1 | B11: Сумма доначислений | C11: =VLOOKUP(B6,Доначисление!C:H,6,0) -> 533.01022 | D11: =VLOOKUP(B6,Доначисление!C:I,7,0) -> 4102.124 | E11: =D11-C11 -> 3569.1138 | F11: =D11/C11 -> 7.6961452 | G11: 10 | H11: =VLOOKUP(B6,'KPI-20 ДГД'!A:B,2,0) -> 10 | I11: =IF(F11>=100%,"ДА","НЕТ") -> ДА | R11: Павлодарская
A12: 2 | B12: Сумма взысканий | C12: =VLOOKUP(B6,Взыскание!C:H,6,0) -> 206.62806 | D12: =VLOOKUP(B6,Взыскание!C:I,7,0) -> 255.38722 | E12: =D12-C12 -> 48.759161 | F12: =D12/C12 -> 1.2359755 | G12: 40 | H12: =VLOOKUP(B6,'KPI-20 ДГД'!A:C,3,0) -> 40 | I12: =IF(F12>=100%,"ДА","НЕТ") -> ДА | R12: СКО
A13: 3 | B13: Среднее доначисление | C13: =38.32 -> 38.32 | D13: =VLOOKUP(B6,'Среднее доначисление'!C:I,7,0) -> 205.1062 | E13: =D13-C13 -> 166.7862 | F13: =D13/C13 -> 5.3524583 | G13: 10 | H13: =VLOOKUP(B6,'KPI-20 ДГД'!A:D,4,0) -> 10 | I13: =IF(F13>=100%,"ДА","НЕТ") -> ДА | R13: Туркестанская
A14: 4 | B14: Коэффициент занятости | C14: 0.5 | D14: =VLOOKUP(B6,Занятость!C:F,4,0) -> 0.51282051 | E14: =D14-C14 -> 0.012820513 | F14: =D14/C14 -> 1.025641 | G14: 15 | H14: =VLOOKUP(B6,'KPI-20 ДГД'!A:E,5,0) -> 15 | I14: =IF(F14>=100%,"ДА","НЕТ") -> ДА | R14: г.Шымкент
R15: г.Алматы
A16: 5 | B16: Доля проверок > 6 мес, % | C16: =MONTH(TODAY())-1&" месяцев "&YEAR(TODAY())&" года" -> 3 месяцев 2026 года | E16: Разница | F16: Удельный вес, % | G16: Доля влияния | H16: Баллы | I16: Достигнут да/ нет | R16: г.Астана
C17: Всего проверок | D17: > 6 мес. | R17: Область Жетісу
C18: =VLOOKUP(B6,Проводимые!C:D,2,0) -> 22 | D18: =VLOOKUP(B6,Проводимые!C:E,3,0) -> 2 | E18: =C18-D18 -> 20 | F18: =D18/C18 -> 0.090909091 | G18: 10 | H18: =VLOOKUP(B6,'KPI-20 ДГД'!A:F,6,0) -> 10 | I18: =IF(F18<20%,"ДА","НЕТ") -> ДА | R18: Область Абай
E19: млн.тг. | R19: Область Ұлытау
A20: 6 | B20: Удельный вес отмененных сумм доначислений | C20: =MONTH(TODAY())-1&" месяцев "&YEAR(TODAY())&" года" -> 3 месяцев 2026 года | E20: Разница | F20: Удельный вес, % | G20: Доля влияния | H20: Баллы | I20: Достигнут да/ нет | R20: Жамбылская
C21: Всего доначислено | D21: Отмененная сумма | R21: КГД
C22: =VLOOKUP(B6,Отмененные!C:D,2,0) -> 4102.124 | D22: =VLOOKUP(B6,Отмененные!C:G,5,0) -> 0 | E22: =D22-C22 -> -4102.124 | F22: =IFERROR(D22/C22,IF(KPI!D22>=1,KPI!D22,0)) -> 0 | G22: 15 | H22: =VLOOKUP(B6,'KPI-20 ДГД'!A:G,7,0) -> 15 | I22: =IF(F22<=1%,"ДА","НЕТ") -> ДА

Sheet Для УСР
B1: KPI по УНА за 3 месяца 2026 года
B3: ДГД | C3: Наименование KPI | E3: KPI | F3: Факт | G3: Достигнут | H3: Балл | I3: KPI | J3: Факт, %
B5: Акмолинская | C5: 1 | D5: Сумма доначислений | E5: =VLOOKUP(B5,Доначисление!C:H,6,0) -> 361.20109 | F5: =VLOOKUP(B5,Доначисление!C:I,7,0) -> 4.635403 | G5: =IF(H5>9,"да","нет") -> нет | H5: =VLOOKUP(B5,Доначисление!C:O,13,0) -> 0 | I5: 1 | J5: =F5*100/E5 -> 1.2833303
B6: Акмолинская | C6: 2 | D6: Сумма взысканий | E6: =VLOOKUP(B6,Взыскание!C:H,6,0) -> 140.02411 | F6: =VLOOKUP(B6,Взыскание!C:I,7,0) -> 961.45756 | G6: =IF(H6>=40,"да","нет") -> да | H6: =VLOOKUP(B6,Взыскание!C:L,10,0) -> 40 | I6: 1 | J6: =F6*100/E6 -> 686.63716
B7: Акмолинская | C7: 3 | D7: Среднее доначисление | E7: =VLOOKUP(B7,'Среднее доначисление'!C:J,8,0) -> 38.32 | F7: =VLOOKUP(B7,'Среднее доначисление'!C:I,7,0) -> 0.38628358 | G7: =IF(H7>=10,"да","нет") -> нет | H7: =VLOOKUP(B7,'Среднее доначисление'!C:M,11,0) -> 0 | I7: 1 | J7: =F7*100/E7 -> 1.0080469
B8: Акмолинская | C8: 4 | D8: Коэффициент занятости | E8: 0.5 | F8: =VLOOKUP(B8,Занятость!C:F,4,0) -> 0.36363636 | G8: =IF(H8>=10,"да","нет") -> нет | H8: =VLOOKUP(B8,Занятость!C:G,5,0) -> 0 | I8: =E8 -> 0.5 | J8: =F8 -> 0.36363636
B9: Акмолинская | C9: 5 | D9: Доля проверок > 6 мес, % | E9: 0.2 | F9: =VLOOKUP(B9,Проводимые!C:F,4,0)*100 -> 0 | G9: =IF(H9>=10,"да","нет") -> да | H9: =VLOOKUP(B9,Проводимые!C:G,5,0) -> 10 | I9: 0.2 | J9: =F9 -> 0
B10: Акмолинская | C10: 6 | D10: Удельный вес отмененных сумм доначислений | E10: 0.01 | F10: =VLOOKUP(B10,Отмененные!C:I,7,0) -> 344.64317 | G10: =IF(H10>=10,"да","нет") -> нет | H10: =VLOOKUP(B10,Отмененные!C:J,8,0) -> 0 | I10: 0.01 | J10: =F10 -> 344.64317
B11: Актюбинская | C11: 1 | D11: Сумма доначислений | E11: =VLOOKUP(B11,Доначисление!C:H,6,0) -> 524.72171 | F11: =VLOOKUP(B11,Доначисление!C:I,7,0) -> 2608.9058 | G11: =IF(H11>9,"да","нет") -> да | H11: =VLOOKUP(B11,Доначисление!C:O,13,0) -> 10 | I11: 1 | J11: =F11*100/E11 -> 497.19799
B12: Актюбинская | C12: 2 | D12: Сумма взысканий | E12: =VLOOKUP(B12,Взыскание!C:H,6,0) -> 203.41491 | F12: =VLOOKUP(B12,Взыскание!C:I,7,0) -> 1301.693 | G12: =IF(H12>=40,"да","нет") -> да | H12: =VLOOKUP(B12,Взыскание!C:L,10,0) -> 40 | I12: 1 | J12: =F12*100/E12 -> 639.92016
B13: Актюбинская | C13: 3 | D13: Среднее доначисление | E13: =VLOOKUP(B13,'Среднее доначисление'!C:J,8,0) -> 38.32 | F13: =VLOOKUP(B13,'Среднее доначисление'!C:I,7,0) -> 118.58663 | G13: =IF(H13>=10,"да","нет") -> да | H13: =VLOOKUP(B13,'Среднее доначисление'!C:M,11,0) -> 10 | I13: 1 | J13: =F13*100/E13 -> 309.46406
B14: Актюбинская | C14: 4 | D14: Коэффициент занятости | E14: 0.5 | F14: =VLOOKUP(B14,Занятость!C:F,4,0) -> 0.40740741 | G14: =IF(H14>=10,"да","нет") -> нет | H14: =VLOOKUP(B14,Занятость!C:G,5,0) -> 5 | I14: =E14 -> 0.5 | J14: =F14 -> 0.40740741
B15: Актюбинская | C15: 5 | D15: Доля проверок > 6 мес, % | E15: 0.2 | F15: =VLOOKUP(B15,Проводимые!C:F,4,0)*100 -> 10.526316 | G15: =IF(H15>=10,"да","нет") -> да | H15: =VLOOKUP(B15,Проводимые!C:G,5,0) -> 10 | I15: 0.2 | J15: =F15 -> 10.526316
B16: Актюбинская | C16: 6 | D16: Удельный вес отмененных сумм доначислений | E16: 0.01 | F16: =VLOOKUP(B16,Отмененные!C:I,7,0) -> 0 | G16: =IF(H16>=10,"да","нет") -> да | H16: =VLOOKUP(B16,Отмененные!C:J,8,0) -> 15 | I16: 0.01 | J16: =F16 -> 0
B17: Алматинская | C17: 1 | D17: Сумма доначислений | E17: =VLOOKUP(B17,Доначисление!C:H,6,0) -> 686.48855 | F17: =VLOOKUP(B17,Доначисление!C:I,7,0) -> 1511.0814 | G17: =IF(H17>9,"да","нет") -> да | H17: =VLOOKUP(B17,Доначисление!C:O,13,0) -> 10 | I17: 1 | J17: =F17*100/E17 -> 220.11749
B18: Алматинская | C18: 2 | D18: Сумма взысканий | E18: =VLOOKUP(B18,Взыскание!C:H,6,0) -> 266.12585 | F18: =VLOOKUP(B18,Взыскание!C:I,7,0) -> 333.55386 | G18: =IF(H18>=40,"да","нет") -> да | H18: =VLOOKUP(B18,Взыскание!C:L,10,0) -> 40 | I18: 1 | J18: =F18*100/E18 -> 125.33689
B19: Алматинская | C19: 3 | D19: Среднее доначисление | E19: =VLOOKUP(B19,'Среднее доначисление'!C:J,8,0) -> 38.32 | F19: =VLOOKUP(B19,'Среднее доначисление'!C:I,7,0) -> 215.86877 | G19: =IF(H19>=10,"да","нет") -> да | H19: =VLOOKUP(B19,'Среднее доначисление'!C:M,11,0) -> 10 | I19: 1 | J19: =F19*100/E19 -> 563.33186
B20: Алматинская | C20: 4 | D20: Коэффициент занятости | E20: 0.5 | F20: =VLOOKUP(B20,Занятость!C:F,4,0) -> 0.15555556 | G20: =IF(H20>=10,"да","нет") -> нет | H20: =VLOOKUP(B20,Занятость!C:G,5,0) -> 0 | I20: =E20 -> 0.5 | J20: =F20 -> 0.15555556
B21: Алматинская | C21: 5 | D21: Доля проверок > 6 мес, % | E21: 0.2 | F21: =VLOOKUP(B21,Проводимые!C:F,4,0)*100 -> 0 | G21: =IF(H21>=10,"да","нет") -> да | H21: =VLOOKUP(B21,Проводимые!C:G,5,0) -> 10 | I21: 0.2 | J21: =F21 -> 0
B22: Алматинская | C22: 6 | D22: Удельный вес отмененных сумм доначислений | E22: 0.01 | F22: =VLOOKUP(B22,Отмененные!C:I,7,0) -> 0.093416544 | G22: =IF(H22>=10,"да","нет") -> да | H22: =VLOOKUP(B22,Отмененные!C:J,8,0) -> 15 | I22: 0.01 | J22: =F22 -> 0.093416544
B23: Атырауская | C23: 1 | D23: Сумма доначислений | E23: =VLOOKUP(B23,Доначисление!C:H,6,0) -> 1012.4767 | F23: =VLOOKUP(B23,Доначисление!C:I,7,0) -> 83.797924 | G23: =IF(H23>9,"да","нет") -> нет | H23: =VLOOKUP(B23,Доначисление!C:O,13,0) -> 0 | I23: 1 | J23: =F23*100/E23 -> 8.2765289
B24: Атырауская | C24: 2 | D24: Сумма взысканий | E24: =VLOOKUP(B24,Взыскание!C:H,6,0) -> 392.49921 | F24: =VLOOKUP(B24,Взыскание!C:I,7,0) -> 1174.8994 | G24: =IF(H24>=40,"да","нет") -> да | H24: =VLOOKUP(B24,Взыскание!C:L,10,0) -> 40 | I24: 1 | J24: =F24*100/E24 -> 299.33804
B25: Атырауская | C25: 3 | D25: Среднее доначисление | E25: =VLOOKUP(B25,'Среднее доначисление'!C:J,8,0) -> 38.32 | F25: =VLOOKUP(B25,'Среднее доначисление'!C:I,7,0) -> 4.6554402 | G25: =IF(H25>=10,"да","нет") -> нет | H25: =VLOOKUP(B25,'Среднее доначисление'!C:M,11,0) -> 0 | I25: 1 | J25: =F25*100/E25 -> 12.148852
B26: Атырауская | C26: 4 | D26: Коэффициент занятости | E26: 0.5 | F26: =VLOOKUP(B26,Занятость!C:F,4,0) -> 0.75 | G26: =IF(H26>=10,"да","нет") -> да | H26: =VLOOKUP(B26,Занятость!C:G,5,0) -> 15 | I26: =E26 -> 0.5 | J26: =F26 -> 0.75
B27: Атырауская | C27: 5 | D27: Доля проверок > 6 мес, % | E27: 0.2 | F27: =VLOOKUP(B27,Проводимые!C:F,4,0)*100 -> 4.7619048 | G27: =IF(H27>=10,"да","нет") -> да | H27: =VLOOKUP(B27,Проводимые!C:G,5,0) -> 10 | I27: 0.2 | J27: =F27 -> 4.7619048
B28: Атырауская | C28: 6 | D28: Удельный вес отмененных сумм доначислений | E28: 0.01 | F28: =VLOOKUP(B28,Отмененные!C:I,7,0) -> 5.7993084 | G28: =IF(H28>=10,"да","нет") -> нет | H28: =VLOOKUP(B28,Отмененные!C:J,8,0) -> 0 | I28: 0.01 | J28: =F28 -> 5.7993084
B29: ВКО | C29: 1 | D29: Сумма доначислений | E29: =VLOOKUP(B29,Доначисление!C:H,6,0) -> 496.36951 | F29: =VLOOKUP(B29,Доначисление!C:I,7,0) -> 704.02056 | G29: =IF(H29>9,"да","нет") -> да | H29: =VLOOKUP(B29,Доначисление!C:O,13,0) -> 10 | I29: 1 | J29: =F29*100/E29 -> 141.83397
B30: ВКО | C30: 2 | D30: Сумма взысканий | E30: =VLOOKUP(B30,Взыскание!C:H,6,0) -> 192.42383 | F30: =VLOOKUP(B30,Взыскание!C:I,7,0) -> 592.34982 | G30: =IF(H30>=40,"да","нет") -> да | H30: =VLOOKUP(B30,Взыскание!C:L,10,0) -> 40 | I30: 1 | J30: =F30*100/E30 -> 307.836
B31: ВКО | C31: 3 | D31: Среднее доначисление | E31: =VLOOKUP(B31,'Среднее доначисление'!C:J,8,0) -> 38.32 | F31: =VLOOKUP(B31,'Среднее доначисление'!C:I,7,0) -> 176.00514 | G31: =IF(H31>=10,"да","нет") -> да | H31: =VLOOKUP(B31,'Среднее доначисление'!C:M,11,0) -> 10 | I31: 1 | J31: =F31*100/E31 -> 459.3036
B32: ВКО | C32: 4 | D32: Коэффициент занятости | E32: 0.5 | F32: =VLOOKUP(B32,Занятость!C:F,4,0) -> 0.066666667 | G32: =IF(H32>=10,"да","нет") -> нет | H32: =VLOOKUP(B32,Занятость!C:G,5,0) -> 0 | I32: =E32 -> 0.5 | J32: =F32 -> 0.066666667
B33: ВКО | C33: 5 | D33: Доля проверок > 6 мес, % | E33: 0.2 | F33: =VLOOKUP(B33,Проводимые!C:F,4,0)*100 -> 12.5 | G33: =IF(H33>=10,"да","нет") -> да | H33: =VLOOKUP(B33,Проводимые!C:G,5,0) -> 10 | I33: 0.2 | J33: =F33 -> 12.5
B34: ВКО | C34: 6 | D34: Удельный вес отмененных сумм доначислений | E34: 0.01 | F34: =VLOOKUP(B34,Отмененные!C:I,7,0) -> 0.67415645 | G34: =IF(H34>=10,"да","нет") -> да | H34: =VLOOKUP(B34,Отмененные!C:J,8,0) -> 15 | I34: 0.01 | J34: =F34 -> 0.67415645
B35: Жамбылская | C35: 1 | D35: Сумма доначислений | E35: =VLOOKUP(B35,Доначисление!C:H,6,0) -> 240.2935 | F35: =VLOOKUP(B35,Доначисление!C:I,7,0) -> 39.948959 | G35: =IF(H35>9,"да","нет") -> нет | H35: =VLOOKUP(B35,Доначисление!C:O,13,0) -> 0 | I35: 1 | J35: =F35*100/E35 -> 16.625068
B36: Жамбылская | C36: 2 | D36: Сумма взысканий | E36: =VLOOKUP(B36,Взыскание!C:H,6,0) -> 93.152772 | F36: =VLOOKUP(B36,Взыскание!C:I,7,0) -> 854.66994 | G36: =IF(H36>=40,"да","нет") -> да | H36: =VLOOKUP(B36,Взыскание!C:L,10,0) -> 40 | I36: 1 | J36: =F36*100/E36 -> 917.49276
B37: Жамбылская | C37: 3 | D37: Среднее доначисление | E37: =VLOOKUP(B37,'Среднее доначисление'!C:J,8,0) -> 38.32 | F37: =VLOOKUP(B37,'Среднее доначисление'!C:I,7,0) -> 9.9872397 | G37: =IF(H37>=10,"да","нет") -> нет | H37: =VLOOKUP(B37,'Среднее доначисление'!C:M,11,0) -> 0 | I37: 1 | J37: =F37*100/E37 -> 26.062734
B38: Жамбылская | C38: 4 | D38: Коэффициент занятости | E38: 0.5 | F38: =VLOOKUP(B38,Занятость!C:F,4,0) -> 0.088888889 | G38: =IF(H38>=10,"да","нет") -> нет | H38: =VLOOKUP(B38,Занятость!C:G,5,0) -> 0 | I38: =E38 -> 0.5 | J38: =F38 -> 0.088888889
B39: Жамбылская | C39: 5 | D39: Доля проверок > 6 мес, % | E39: 0.2 | F39: =VLOOKUP(B39,Проводимые!C:F,4,0)*100 -> 0 | G39: =IF(H39>=10,"да","нет") -> да | H39: =VLOOKUP(B39,Проводимые!C:G,5,0) -> 10 | I39: 0.2 | J39: =F39 -> 0
B40: Жамбылская | C40: 6 | D40: Удельный вес отмененных сумм доначислений | E40: 0.01 | F40: =VLOOKUP(B40,Отмененные!C:I,7,0) -> 0 | G40: =IF(H40>=10,"да","нет") -> да | H40: =VLOOKUP(B40,Отмененные!C:J,8,0) -> 15 | I40: 0.01 | J40: =F40 -> 0
B41: ЗКО | C41: 1 | D41: Сумма доначислений | E41: =VLOOKUP(B41,Доначисление!C:H,6,0) -> 335.93498 | F41: =VLOOKUP(B41,Доначисление!C:I,7,0) -> 12.336714 | G41: =IF(H41>9,"да","нет") -> нет | H41: =VLOOKUP(B41,Доначисление!C:O,13,0) -> 0 | I41: 1 | J41: =F41*100/E41 -> 3.6723515
B42: ЗКО | C42: 2 | D42: Сумма взысканий | E42: =VLOOKUP(B42,Взыскание!C:H,6,0) -> 130.22939 | F42: =VLOOKUP(B42,Взыскание!C:I,7,0) -> 402.34887 | G42: =IF(H42>=40,"да","нет") -> да | H42: =VLOOKUP(B42,Взыскание!C:L,10,0) -> 40 | I42: 1 | J42: =F42*100/E42 -> 308.95398
B43: ЗКО | C43: 3 | D43: Среднее доначисление | E43: =VLOOKUP(B43,'Среднее доначисление'!C:J,8,0) -> 38.32 | F43: =VLOOKUP(B43,'Среднее доначисление'!C:I,7,0) -> 0.72568903 | G43: =IF(H43>=10,"да","нет") -> нет | H43: =VLOOKUP(B43,'Среднее доначисление'!C:M,11,0) -> 0 | I43: 1 | J43: =F43*100/E43 -> 1.8937605
B44: ЗКО | C44: 4 | D44: Коэффициент занятости | E44: 0.5 | F44: =VLOOKUP(B44,Занятость!C:F,4,0) -> 0.51515152 | G44: =IF(H44>=10,"да","нет") -> да | H44: =VLOOKUP(B44,Занятость!C:G,5,0) -> 15 | I44: =E44 -> 0.5 | J44: =F44 -> 0.51515152
B45: ЗКО | C45: 5 | D45: Доля проверок > 6 мес, % | E45: 0.2 | F45: =VLOOKUP(B45,Проводимые!C:F,4,0)*100 -> 10 | G45: =IF(H45>=10,"да","нет") -> да | H45: =VLOOKUP(B45,Проводимые!C:G,5,0) -> 10 | I45: 0.2 | J45: =F45 -> 10
B46: ЗКО | C46: 6 | D46: Удельный вес отмененных сумм доначислений | E46: 0.01 | F46: =VLOOKUP(B46,Отмененные!C:I,7,0) -> 257.40486 | G46: =IF(H46>=10,"да","нет") -> нет | H46: =VLOOKUP(B46,Отмененные!C:J,8,0) -> 0 | I46: 0.01 | J46: =F46 -> 257.40486
B47: Карагандинская | C47: 1 | D47: Сумма доначислений | E47: =VLOOKUP(B47,Доначисление!C:H,6,0) -> 746.51205 | F47: =VLOOKUP(B47,Доначисление!C:I,7,0) -> 3604.2166 | G47: =IF(H47>9,"да","нет") -> да | H47: =VLOOKUP(B47,Доначисление!C:O,13,0) -> 10 | I47: 1 | J47: =F47*100/E47 -> 482.80755
B48: Карагандинская | C48: 2 | D48: Сумма взысканий | E48: =VLOOKUP(B48,Взыскание!C:H,6,0) -> 289.3947 | F48: =VLOOKUP(B48,Взыскание!C:I,7,0) -> 551.82157 | G48: =IF(H48>=40,"да","нет") -> да | H48: =VLOOKUP(B48,Взыскание!C:L,10,0) -> 40 | I48: 1 | J48: =F48*100/E48 -> 190.68129
B49: Карагандинская | C49: 3 | D49: Среднее доначисление | E49: =VLOOKUP(B49,'Среднее доначисление'!C:J,8,0) -> 38.32 | F49: =VLOOKUP(B49,'Среднее доначисление'!C:I,7,0) -> 106.00637 | G49: =IF(H49>=10,"да","нет") -> да | H49: =VLOOKUP(B49,'Среднее доначисление'!C:M,11,0) -> 10 | I49: 1 | J49: =F49*100/E49 -> 276.63458
B50: Карагандинская | C50: 4 | D50: Коэффициент занятости | E50: 0.5 | F50: =VLOOKUP(B50,Занятость!C:F,4,0) -> 0.51515152 | G50: =IF(H50>=10,"да","нет") -> да | H50: =VLOOKUP(B50,Занятость!C:G,5,0) -> 15 | I50: =E50 -> 0.5 | J50: =F50 -> 0.51515152
B51: Карагандинская | C51: 5 | D51: Доля проверок > 6 мес, % | E51: 0.2 | F51: =VLOOKUP(B51,Проводимые!C:F,4,0)*100 -> 19.230769 | G51: =IF(H51>=10,"да","нет") -> да | H51: =VLOOKUP(B51,Проводимые!C:G,5,0) -> 10 | I51: 0.2 | J51: =F51 -> 19.230769
B52: Карагандинская | C52: 6 | D52: Удельный вес отмененных сумм доначислений | E52: 0.01 | F52: =VLOOKUP(B52,Отмененные!C:I,7,0) -> 2.4133566 | G52: =IF(H52>=10,"да","нет") -> нет | H52: =VLOOKUP(B52,Отмененные!C:J,8,0) -> 0 | I52: 0.01 | J52: =F52 -> 2.4133566
B53: Кызылординская | C53: 1 | D53: Сумма доначислений | E53: =VLOOKUP(B53,Доначисление!C:H,6,0) -> 356.60865 | F53: =VLOOKUP(B53,Доначисление!C:I,7,0) -> 407.49043 | G53: =IF(H53>9,"да","нет") -> да | H53: =VLOOKUP(B53,Доначисление!C:O,13,0) -> 10 | I53: 1 | J53: =F53*100/E53 -> 114.26824
B54: Кызылординская | C54: 2 | D54: Сумма взысканий | E54: =VLOOKUP(B54,Взыскание!C:H,6,0) -> 138.24379 | F54: =VLOOKUP(B54,Взыскание!C:I,7,0) -> 165.0742 | G54: =IF(H54>=40,"да","нет") -> да | H54: =VLOOKUP(B54,Взыскание!C:L,10,0) -> 40 | I54: 1 | J54: =F54*100/E54 -> 119.40804
B55: Кызылординская | C55: 3 | D55: Среднее доначисление | E55: =VLOOKUP(B55,'Среднее доначисление'!C:J,8,0) -> 38.32 | F55: =VLOOKUP(B55,'Среднее доначисление'!C:I,7,0) -> 27.166029 | G55: =IF(H55>=10,"да","нет") -> нет | H55: =VLOOKUP(B55,'Среднее доначисление'!C:M,11,0) -> 0 | I55: 1 | J55: =F55*100/E55 -> 70.892559
B56: Кызылординская | C56: 4 | D56: Коэффициент занятости | E56: 0.5 | F56: =VLOOKUP(B56,Занятость!C:F,4,0) -> 0.3125 | G56: =IF(H56>=10,"да","нет") -> нет | H56: =VLOOKUP(B56,Занятость!C:G,5,0) -> 0 | I56: =E56 -> 0.5 | J56: =F56 -> 0.3125
B57: Кызылординская | C57: 5 | D57: Доля проверок > 6 мес, % | E57: 0.2 | F57: =VLOOKUP(B57,Проводимые!C:F,4,0)*100 -> 0 | G57: =IF(H57>=10,"да","нет") -> да | H57: =VLOOKUP(B57,Проводимые!C:G,5,0) -> 10 | I57: 0.2 | J57: =F57 -> 0
B58: Кызылординская | C58: 6 | D58: Удельный вес отмененных сумм доначислений | E58: 0.01 | F58: =VLOOKUP(B58,Отмененные!C:I,7,0) -> 0 | G58: =IF(H58>=10,"да","нет") -> да | H58: =VLOOKUP(B58,Отмененные!C:J,8,0) -> 15 | I58: 0.01 | J58: =F58 -> 0
B59: Костанайская | C59: 1 | D59: Сумма доначислений | E59: =VLOOKUP(B59,Доначисление!C:H,6,0) -> 364.94461 | F59: =VLOOKUP(B59,Доначисление!C:I,7,0) -> 440.40228 | G59: =IF(H59>9,"да","нет") -> да | H59: =VLOOKUP(B59,Доначисление!C:O,13,0) -> 10 | I59: 1 | J59: =F59*100/E59 -> 120.67647
B60: Костанайская | C60: 2 | D60: Сумма взысканий | E60: =VLOOKUP(B60,Взыскание!C:H,6,0) -> 141.47533 | F60: =VLOOKUP(B60,Взыскание!C:I,7,0) -> 141.16053 | G60: =IF(H60>=40,"да","нет") -> нет | H60: =VLOOKUP(B60,Взыскание!C:L,10,0) -> 20 | I60: 1 | J60: =F60*100/E60 -> 99.77749
B61: Костанайская | C61: 3 | D61: Среднее доначисление | E61: =VLOOKUP(B61,'Среднее доначисление'!C:J,8,0) -> 38.32 | F61: =VLOOKUP(B61,'Среднее доначисление'!C:I,7,0) -> 44.040228 | G61: =IF(H61>=10,"да","нет") -> да | H61: =VLOOKUP(B61,'Среднее доначисление'!C:M,11,0) -> 10 | I61: 1 | J61: =F61*100/E61 -> 114.92753
B62: Костанайская | C62: 4 | D62: Коэффициент занятости | E62: 0.5 | F62: =VLOOKUP(B62,Занятость!C:F,4,0) -> 0.27777778 | G62: =IF(H62>=10,"да","нет") -> нет | H62: =VLOOKUP(B62,Занятость!C:G,5,0) -> 0 | I62: =E62 -> 0.5 | J62: =F62 -> 0.27777778
B63: Костанайская | C63: 5 | D63: Доля проверок > 6 мес, % | E63: 0.2 | F63: =VLOOKUP(B63,Проводимые!C:F,4,0)*100 -> 0 | G63: =IF(H63>=10,"да","нет") -> да | H63: =VLOOKUP(B63,Проводимые!C:G,5,0) -> 10 | I63: 0.2 | J63: =F63 -> 0
B64: Костанайская | C64: 6 | D64: Удельный вес отмененных сумм доначислений | E64: 0.01 | F64: =VLOOKUP(B64,Отмененные!C:I,7,0) -> 0 | G64: =IF(H64>=10,"да","нет") -> да | H64: =VLOOKUP(B64,Отмененные!C:J,8,0) -> 15 | I64: 0.01 | J64: =F64 -> 0
B65: Мангистауская | C65: 1 | D65: Сумма доначислений | E65: =VLOOKUP(B65,Доначисление!C:H,6,0) -> 497.94622 | F65: =VLOOKUP(B65,Доначисление!C:I,7,0) -> 2808.6616 | G65: =IF(H65>9,"да","нет") -> да | H65: =VLOOKUP(B65,Доначисление!C:O,13,0) -> 10 | I65: 1 | J65: =F65*100/E65 -> 564.04918
B66: Мангистауская | C66: 2 | D66: Сумма взысканий | E66: =VLOOKUP(B66,Взыскание!C:H,6,0) -> 193.03506 | F66: =VLOOKUP(B66,Взыскание!C:I,7,0) -> 166.45599 | G66: =IF(H66>=40,"да","нет") -> нет | H66: =VLOOKUP(B66,Взыскание!C:L,10,0) -> 10 | I66: 1 | J66: =F66*100/E66 -> 86.230964
B67: Мангистауская | C67: 3 | D67: Среднее доначисление | E67: =VLOOKUP(B67,'Среднее доначисление'!C:J,8,0) -> 38.32 | F67: =VLOOKUP(B67,'Среднее доначисление'!C:I,7,0) -> 147.82429 | G67: =IF(H67>=10,"да","нет") -> да | H67: =VLOOKUP(B67,'Среднее доначисление'!C:M,11,0) -> 10 | I67: 1 | J67: =F67*100/E67 -> 385.76277
B68: Мангистауская | C68: 4 | D68: Коэффициент занятости | E68: 0.5 | F68: =VLOOKUP(B68,Занятость!C:F,4,0) -> 0.48717949 | G68: =IF(H68>=10,"да","нет") -> нет | H68: =VLOOKUP(B68,Занятость!C:G,5,0) -> 5 | I68: =E68 -> 0.5 | J68: =F68 -> 0.48717949
B69: Мангистауская | C69: 5 | D69: Доля проверок > 6 мес, % | E69: 0.2 | F69: =VLOOKUP(B69,Проводимые!C:F,4,0)*100 -> 36.363636 | G69: =IF(H69>=10,"да","нет") -> нет | H69: =VLOOKUP(B69,Проводимые!C:G,5,0) -> 0 | I69: 0.2 | J69: =F69 -> 36.363636
B70: Мангистауская | C70: 6 | D70: Удельный вес отмененных сумм доначислений | E70: 0.01 | F70: =VLOOKUP(B70,Отмененные!C:I,7,0) -> 0 | G70: =IF(H70>=10,"да","нет") -> да | H70: =VLOOKUP(B70,Отмененные!C:J,8,0) -> 15 | I70: 0.01 | J70: =F70 -> 0
B71: Павлодарская | C71: 1 | D71: Сумма доначислений | E71: =VLOOKUP(B71,Доначисление!C:H,6,0) -> 514.7939 | F71: =VLOOKUP(B71,Доначисление!C:I,7,0) -> 1070.5822 | G71: =IF(H71>9,"да","нет") -> да | H71: =VLOOKUP(B71,Доначисление!C:O,13,0) -> 10 | I71: 1 | J71: =F71*100/E71 -> 207.96327
B72: Павлодарская | C72: 2 | D72: Сумма взысканий | E72: =VLOOKUP(B72,Взыскание!C:H,6,0) -> 199.56627 | F72: =VLOOKUP(B72,Взыскание!C:I,7,0) -> 208.333 | G72: =IF(H72>=40,"да","нет") -> да | H72: =VLOOKUP(B72,Взыскание!C:L,10,0) -> 40 | I72: 1 | J72: =F72*100/E72 -> 104.39289
B73: Павлодарская | C73: 3 | D73: Среднее доначисление | E73: =VLOOKUP(B73,'Среднее доначисление'!C:J,8,0) -> 38.32 | F73: =VLOOKUP(B73,'Среднее доначисление'!C:I,7,0) -> 71.37215 | G73: =IF(H73>=10,"да","нет") -> да | H73: =VLOOKUP(B73,'Среднее доначисление'!C:M,11,0) -> 10 | I73: 1 | J73: =F73*100/E73 -> 186.253
B74: Павлодарская | C74: 4 | D74: Коэффициент занятости | E74: 0.5 | F74: =VLOOKUP(B74,Занятость!C:F,4,0) -> 0.5 | G74: =IF(H74>=10,"да","нет") -> да | H74: =VLOOKUP(B74,Занятость!C:G,5,0) -> 15 | I74: =E74 -> 0.5 | J74: =F74 -> 0.5
B75: Павлодарская | C75: 5 | D75: Доля проверок > 6 мес, % | E75: 0.2 | F75: =VLOOKUP(B75,Проводимые!C:F,4,0)*100 -> 14.285714 | G75: =IF(H75>=10,"да","нет") -> да | H75: =VLOOKUP(B75,Проводимые!C:G,5,0) -> 10 | I75: 0.2 | J75: =F75 -> 14.285714
B76: Павлодарская | C76: 6 | D76: Удельный вес отмененных сумм доначислений | E76: 0.01 | F76: =VLOOKUP(B76,Отмененные!C:I,7,0) -> 0 | G76: =IF(H76>=10,"да","нет") -> да | H76: =VLOOKUP(B76,Отмененные!C:J,8,0) -> 15 | I76: 0.01 | J76: =F76 -> 0
B77: СКО | C77: 1 | D77: Сумма доначислений | E77: =VLOOKUP(B77,Доначисление!C:H,6,0) -> 204.71346 | F77: =VLOOKUP(B77,Доначисление!C:I,7,0) -> 718.23921 | G77: =IF(H77>9,"да","нет") -> да | H77: =VLOOKUP(B77,Доначисление!C:O,13,0) -> 10 | I77: 1 | J77: =F77*100/E77 -> 350.851
B78: СКО | C78: 2 | D78: Сумма взысканий | E78: =VLOOKUP(B78,Взыскание!C:H,6,0) -> 79.359724 | F78: =VLOOKUP(B78,Взыскание!C:I,7,0) -> 139.63351 | G78: =IF(H78>=40,"да","нет") -> да | H78: =VLOOKUP(B78,Взыскание!C:L,10,0) -> 40 | I78: 1 | J78: =F78*100/E78 -> 175.9501
B79: СКО | C79: 3 | D79: Среднее доначисление | E79: =VLOOKUP(B79,'Среднее доначисление'!C:J,8,0) -> 38.32 | F79: =VLOOKUP(B79,'Среднее доначисление'!C:I,7,0) -> 143.64784 | G79: =IF(H79>=10,"да","нет") -> да | H79: =VLOOKUP(B79,'Среднее доначисление'!C:M,11,0) -> 10 | I79: 1 | J79: =F79*100/E79 -> 374.86389
B80: СКО | C80: 4 | D80: Коэффициент занятости | E80: 0.5 | F80: =VLOOKUP(B80,Занятость!C:F,4,0) -> 0.13888889 | G80: =IF(H80>=10,"да","нет") -> нет | H80: =VLOOKUP(B80,Занятость!C:G,5,0) -> 0 | I80: =E80 -> 0.5 | J80: =F80 -> 0.13888889
B81: СКО | C81: 5 | D81: Доля проверок > 6 мес, % | E81: 0.2 | F81: =VLOOKUP(B81,Проводимые!C:F,4,0)*100 -> 0 | G81: =IF(H81>=10,"да","нет") -> да | H81: =VLOOKUP(B81,Проводимые!C:G,5,0) -> 10 | I81: 0.2 | J81: =F81 -> 0
B82: СКО | C82: 6 | D82: Удельный вес отмененных сумм доначислений | E82: 0.01 | F82: =VLOOKUP(B82,Отмененные!C:I,7,0) -> 0 | G82: =IF(H82>=10,"да","нет") -> да | H82: =VLOOKUP(B82,Отмененные!C:J,8,0) -> 15 | I82: 0.01 | J82: =F82 -> 0
B83: Туркестанская | C83: 1 | D83: Сумма доначислений | E83: =VLOOKUP(B83,Доначисление!C:H,6,0) -> 459.59261 | F83: =VLOOKUP(B83,Доначисление!C:I,7,0) -> 492.47053 | G83: =IF(H83>9,"да","нет") -> да | H83: =VLOOKUP(B83,Доначисление!C:O,13,0) -> 10 | I83: 1 | J83: =F83*100/E83 -> 107.15371
B84: Туркестанская | C84: 2 | D84: Сумма взысканий | E84: =VLOOKUP(B84,Взыскание!C:H,6,0) -> 178.16681 | F84: =VLOOKUP(B84,Взыскание!C:I,7,0) -> 197.50011 | G84: =IF(H84>=40,"да","нет") -> да | H84: =VLOOKUP(B84,Взыскание!C:L,10,0) -> 40 | I84: 1 | J84: =F84*100/E84 -> 110.85124
B85: Туркестанская | C85: 3 | D85: Среднее доначисление | E85: =VLOOKUP(B85,'Среднее доначисление'!C:J,8,0) -> 38.32 | F85: =VLOOKUP(B85,'Среднее доначисление'!C:I,7,0) -> 32.831369 | G85: =IF(H85>=10,"да","нет") -> нет | H85: =VLOOKUP(B85,'Среднее доначисление'!C:M,11,0) -> 0 | I85: 1 | J85: =F85*100/E85 -> 85.67685
B86: Туркестанская | C86: 4 | D86: Коэффициент занятости | E86: 0.5 | F86: =VLOOKUP(B86,Занятость!C:F,4,0) -> 0.38461538 | G86: =IF(H86>=10,"да","нет") -> нет | H86: =VLOOKUP(B86,Занятость!C:G,5,0) -> 0 | I86: =E86 -> 0.5 | J86: =F86 -> 0.38461538
B87: Туркестанская | C87: 5 | D87: Доля проверок > 6 мес, % | E87: 0.2 | F87: =VLOOKUP(B87,Проводимые!C:F,4,0)*100 -> 7.1428571 | G87: =IF(H87>=10,"да","нет") -> да | H87: =VLOOKUP(B87,Проводимые!C:G,5,0) -> 10 | I87: 0.2 | J87: =F87 -> 7.1428571
B88: Туркестанская | C88: 6 | D88: Удельный вес отмененных сумм доначислений | E88: 0.01 | F88: =VLOOKUP(B88,Отмененные!C:I,7,0) -> 21.657052 | G88: =IF(H88>=10,"да","нет") -> нет | H88: =VLOOKUP(B88,Отмененные!C:J,8,0) -> 0 | I88: 0.01 | J88: =F88 -> 21.657052
B89: г.Шымкент | C89: 1 | D89: Сумма доначислений | E89: =VLOOKUP(B89,Доначисление!C:H,6,0) -> 533.01022 | F89: =VLOOKUP(B89,Доначисление!C:I,7,0) -> 4102.124 | G89: =IF(H89>9,"да","нет") -> да | H89: =VLOOKUP(B89,Доначисление!C:O,13,0) -> 10 | I89: 1 | J89: =F89*100/E89 -> 769.61452
B90: г.Шымкент | C90: 2 | D90: Сумма взысканий | E90: =VLOOKUP(B90,Взыскание!C:H,6,0) -> 206.62806 | F90: =VLOOKUP(B90,Взыскание!C:I,7,0) -> 255.38722 | G90: =IF(H90>=40,"да","нет") -> да | H90: =VLOOKUP(B90,Взыскание!C:L,10,0) -> 40 | I90: 1 | J90: =F90*100/E90 -> 123.59755
B91: г.Шымкент | C91: 3 | D91: Среднее доначисление | E91: =VLOOKUP(B91,'Среднее доначисление'!C:J,8,0) -> 38.32 | F91: =VLOOKUP(B91,'Среднее доначисление'!C:I,7,0) -> 205.1062 | G91: =IF(H91>=10,"да","нет") -> да | H91: =VLOOKUP(B91,'Среднее доначисление'!C:M,11,0) -> 10 | I91: 1 | J91: =F91*100/E91 -> 535.24583
B92: г.Шымкент | C92: 4 | D92: Коэффициент занятости | E92: 0.5 | F92: =VLOOKUP(B92,Занятость!C:F,4,0) -> 0.51282051 | G92: =IF(H92>=10,"да","нет") -> да | H92: =VLOOKUP(B92,Занятость!C:G,5,0) -> 15 | I92: =E92 -> 0.5 | J92: =F92 -> 0.51282051
B93: г.Шымкент | C93: 5 | D93: Доля проверок > 6 мес, % | E93: 0.2 | F93: =VLOOKUP(B93,Проводимые!C:F,4,0)*100 -> 9.0909091 | G93: =IF(H93>=10,"да","нет") -> да | H93: =VLOOKUP(B93,Проводимые!C:G,5,0) -> 10 | I93: 0.2 | J93: =F93 -> 9.0909091
B94: г.Шымкент | C94: 6 | D94: Удельный вес отмененных сумм доначислений | E94: 0.01 | F94: =VLOOKUP(B94,Отмененные!C:I,7,0) -> 0 | G94: =IF(H94>=10,"да","нет") -> да | H94: =VLOOKUP(B94,Отмененные!C:J,8,0) -> 15 | I94: 0.01 | J94: =F94 -> 0
B95: г.Алматы | C95: 1 | D95: Сумма доначислений | E95: =VLOOKUP(B95,Доначисление!C:H,6,0) -> 6003.1118 | F95: =VLOOKUP(B95,Доначисление!C:I,7,0) -> 18998.209 | G95: =IF(H95>9,"да","нет") -> да | H95: =VLOOKUP(B95,Доначисление!C:O,13,0) -> 10 | I95: 1 | J95: =F95*100/E95 -> 316.47269
B96: г.Алматы | C96: 2 | D96: Сумма взысканий | E96: =VLOOKUP(B96,Взыскание!C:H,6,0) -> 2327.1811 | F96: =VLOOKUP(B96,Взыскание!C:I,7,0) -> 6208.7656 | G96: =IF(H96>=40,"да","нет") -> да | H96: =VLOOKUP(B96,Взыскание!C:L,10,0) -> 40 | I96: 1 | J96: =F96*100/E96 -> 266.7934
B97: г.Алматы | C97: 3 | D97: Среднее доначисление | E97: =VLOOKUP(B97,'Среднее доначисление'!C:J,8,0) -> 38.32 | F97: =VLOOKUP(B97,'Среднее доначисление'!C:I,7,0) -> 218.37022 | G97: =IF(H97>=10,"да","нет") -> да | H97: =VLOOKUP(B97,'Среднее доначисление'!C:M,11,0) -> 10 | I97: 1 | J97: =F97*100/E97 -> 569.85965
B98: г.Алматы | C98: 4 | D98: Коэффициент занятости | E98: 0.5 | F98: =VLOOKUP(B98,Занятость!C:F,4,0) -> 0.49152542 | G98: =IF(H98>=10,"да","нет") -> нет | H98: =VLOOKUP(B98,Занятость!C:G,5,0) -> 5 | I98: =E98 -> 0.5 | J98: =F98 -> 0.49152542
B99: г.Алматы | C99: 5 | D99: Доля проверок > 6 мес, % | E99: 0.2 | F99: =VLOOKUP(B99,Проводимые!C:F,4,0)*100 -> 9.4972067 | G99: =IF(H99>=10,"да","нет") -> да | H99: =VLOOKUP(B99,Проводимые!C:G,5,0) -> 10 | I99: 0.2 | J99: =F99 -> 9.4972067
B100: г.Алматы | C100: 6 | D100: Удельный вес отмененных сумм доначислений | E100: 0.01 | F100: =VLOOKUP(B100,Отмененные!C:I,7,0) -> 0.082226172 | G100: =IF(H100>=10,"да","нет") -> да | H100: =VLOOKUP(B100,Отмененные!C:J,8,0) -> 15 | I100: 0.01 | J100: =F100 -> 0.082226172
B101: г.Астана | C101: 1 | D101: Сумма доначислений | E101: =VLOOKUP(B101,Доначисление!C:H,6,0) -> 3710.0991 | F101: =VLOOKUP(B101,Доначисление!C:I,7,0) -> 2199.6467 | G101: =IF(H101>9,"да","нет") -> нет | H101: =VLOOKUP(B101,Доначисление!C:O,13,0) -> 0 | I101: 1 | J101: =F101*100/E101 -> 59.288084
B102: г.Астана | C102: 2 | D102: Сумма взысканий | E102: =VLOOKUP(B102,Взыскание!C:H,6,0) -> 1438.2662 | F102: =VLOOKUP(B102,Взыскание!C:I,7,0) -> 1316.3046 | G102: =IF(H102>=40,"да","нет") -> нет | H102: =VLOOKUP(B102,Взыскание!C:L,10,0) -> 20 | I102: 1 | J102: =F102*100/E102 -> 91.520234
...

Sheet KPI-20 ДГД
A1: Баллы на 01.04.2026
A3: ДГД | B3: Доначисление | C3: Взыскание | D3: Доначисление на 1 проверку | E3: Коэффициент занятости | F3: Доля проверок > 6 мес, % | G3: Удельный вес отмененных сумм доначислений | H3: Баллы | I3: Позиция
A4: Акмолинская | B4: =SUMIF(Доначисление!C:C,'KPI-20 ДГД'!A4,Доначисление!O:O) -> 0 | C4: =SUMIF(Взыскание!C:C,'KPI-20 ДГД'!A4,Взыскание!L:L) -> 40 | D4: =SUMIF('Среднее доначисление'!C:C,'KPI-20 ДГД'!A4,'Среднее доначисление'!M:M) -> 0 | E4: =SUMIF(Занятость!C:C,'KPI-20 ДГД'!A4,Занятость!G:G) -> 0 | F4: =SUMIF(Проводимые!C:C,'KPI-20 ДГД'!A4,Проводимые!G:G) -> 10 | G4: =SUMIF(Отмененные!C:C,'KPI-20 ДГД'!A4,Отмененные!J:J) -> 0 | H4: =SUM(B4:G4) -> 50 | I4: =RANK(H4,$H$4:$H$23,0) -> 19
A5: Актюбинская | B5: =SUMIF(Доначисление!C:C,'KPI-20 ДГД'!A5,Доначисление!O:O) -> 10 | C5: =SUMIF(Взыскание!C:C,'KPI-20 ДГД'!A5,Взыскание!L:L) -> 40 | D5: =SUMIF('Среднее доначисление'!C:C,'KPI-20 ДГД'!A5,'Среднее доначисление'!M:M) -> 10 | E5: =SUMIF(Занятость!C:C,'KPI-20 ДГД'!A5,Занятость!G:G) -> 5 | F5: =SUMIF(Проводимые!C:C,'KPI-20 ДГД'!A5,Проводимые!G:G) -> 10 | G5: =SUMIF(Отмененные!C:C,'KPI-20 ДГД'!A5,Отмененные!J:J) -> 15 | H5: =SUM(B5:G5) -> 90 | I5: =RANK(H5,$H$4:$H$23,0) -> 4
A6: Алматинская | B6: =SUMIF(Доначисление!C:C,'KPI-20 ДГД'!A6,Доначисление!O:O) -> 10 | C6: =SUMIF(Взыскание!C:C,'KPI-20 ДГД'!A6,Взыскание!L:L) -> 40 | D6: =SUMIF('Среднее доначисление'!C:C,'KPI-20 ДГД'!A6,'Среднее доначисление'!M:M) -> 10 | E6: =SUMIF(Занятость!C:C,'KPI-20 ДГД'!A6,Занятость!G:G) -> 0 | F6: =SUMIF(Проводимые!C:C,'KPI-20 ДГД'!A6,Проводимые!G:G) -> 10 | G6: =SUMIF(Отмененные!C:C,'KPI-20 ДГД'!A6,Отмененные!J:J) -> 15 | H6: =SUM(B6:G6) -> 85 | I6: =RANK(H6,$H$4:$H$23,0) -> 7
A7: Атырауская | B7: =SUMIF(Доначисление!C:C,'KPI-20 ДГД'!A7,Доначисление!O:O) -> 0 | C7: =SUMIF(Взыскание!C:C,'KPI-20 ДГД'!A7,Взыскание!L:L) -> 40 | D7: =SUMIF('Среднее доначисление'!C:C,'KPI-20 ДГД'!A7,'Среднее доначисление'!M:M) -> 0 | E7: =SUMIF(Занятость!C:C,'KPI-20 ДГД'!A7,Занятость!G:G) -> 15 | F7: =SUMIF(Проводимые!C:C,'KPI-20 ДГД'!A7,Проводимые!G:G) -> 10 | G7: =SUMIF(Отмененные!C:C,'KPI-20 ДГД'!A7,Отмененные!J:J) -> 0 | H7: =SUM(B7:G7) -> 65 | I7: =RANK(H7,$H$4:$H$23,0) -> 14
A8: ВКО | B8: =SUMIF(Доначисление!C:C,'KPI-20 ДГД'!A8,Доначисление!O:O) -> 10 | C8: =SUMIF(Взыскание!C:C,'KPI-20 ДГД'!A8,Взыскание!L:L) -> 40 | D8: =SUMIF('Среднее доначисление'!C:C,'KPI-20 ДГД'!A8,'Среднее доначисление'!M:M) -> 10 | E8: =SUMIF(Занятость!C:C,'KPI-20 ДГД'!A8,Занятость!G:G) -> 0 | F8: =SUMIF(Проводимые!C:C,'KPI-20 ДГД'!A8,Проводимые!G:G) -> 10 | G8: =SUMIF(Отмененные!C:C,'KPI-20 ДГД'!A8,Отмененные!J:J) -> 15 | H8: =SUM(B8:G8) -> 85 | I8: =RANK(H8,$H$4:$H$23,0) -> 7
A9: Жамбылская | B9: =SUMIF(Доначисление!C:C,'KPI-20 ДГД'!A9,Доначисление!O:O) -> 0 | C9: =SUMIF(Взыскание!C:C,'KPI-20 ДГД'!A9,Взыскание!L:L) -> 40 | D9: =SUMIF('Среднее доначисление'!C:C,'KPI-20 ДГД'!A9,'Среднее доначисление'!M:M) -> 0 | E9: =SUMIF(Занятость!C:C,'KPI-20 ДГД'!A9,Занятость!G:G) -> 0 | F9: =SUMIF(Проводимые!C:C,'KPI-20 ДГД'!A9,Проводимые!G:G) -> 10 | G9: =SUMIF(Отмененные!C:C,'KPI-20 ДГД'!A9,Отмененные!J:J) -> 15 | H9: =SUM(B9:G9) -> 65 | I9: =RANK(H9,$H$4:$H$23,0) -> 14
A10: ЗКО | B10: =SUMIF(Доначисление!C:C,'KPI-20 ДГД'!A10,Доначисление!O:O) -> 0 | C10: =SUMIF(Взыскание!C:C,'KPI-20 ДГД'!A10,Взыскание!L:L) -> 40 | D10: =SUMIF('Среднее доначисление'!C:C,'KPI-20 ДГД'!A10,'Среднее доначисление'!M:M) -> 0 | E10: =SUMIF(Занятость!C:C,'KPI-20 ДГД'!A10,Занятость!G:G) -> 15 | F10: =SUMIF(Проводимые!C:C,'KPI-20 ДГД'!A10,Проводимые!G:G) -> 10 | G10: =SUMIF(Отмененные!C:C,'KPI-20 ДГД'!A10,Отмененные!J:J) -> 0 | H10: =SUM(B10:G10) -> 65 | I10: =RANK(H10,$H$4:$H$23,0) -> 14
A11: Карагандинская | B11: =SUMIF(Доначисление!C:C,'KPI-20 ДГД'!A11,Доначисление!O:O) -> 10 | C11: =SUMIF(Взыскание!C:C,'KPI-20 ДГД'!A11,Взыскание!L:L) -> 40 | D11: =SUMIF('Среднее доначисление'!C:C,'KPI-20 ДГД'!A11,'Среднее доначисление'!M:M) -> 10 | E11: =SUMIF(Занятость!C:C,'KPI-20 ДГД'!A11,Занятость!G:G) -> 15 | F11: =SUMIF(Проводимые!C:C,'KPI-20 ДГД'!A11,Проводимые!G:G) -> 10 | G11: =SUMIF(Отмененные!C:C,'KPI-20 ДГД'!A11,Отмененные!J:J) -> 0 | H11: =SUM(B11:G11) -> 85 | I11: =RANK(H11,$H$4:$H$23,0) -> 7
A12: Кызылординская | B12: =SUMIF(Доначисление!C:C,'KPI-20 ДГД'!A12,Доначисление!O:O) -> 10 | C12: =SUMIF(Взыскание!C:C,'KPI-20 ДГД'!A12,Взыскание!L:L) -> 40 | D12: =SUMIF('Среднее доначисление'!C:C,'KPI-20 ДГД'!A12,'Среднее доначисление'!M:M) -> 0 | E12: =SUMIF(Занятость!C:C,'KPI-20 ДГД'!A12,Занятость!G:G) -> 0 | F12: =SUMIF(Проводимые!C:C,'KPI-20 ДГД'!A12,Проводимые!G:G) -> 10 | G12: =SUMIF(Отмененные!C:C,'KPI-20 ДГД'!A12,Отмененные!J:J) -> 15 | H12: =SUM(B12:G12) -> 75 | I12: =RANK(H12,$H$4:$H$23,0) -> 11
A13: Костанайская | B13: =SUMIF(Доначисление!C:C,'KPI-20 ДГД'!A13,Доначисление!O:O) -> 10 | C13: =SUMIF(Взыскание!C:C,'KPI-20 ДГД'!A13,Взыскание!L:L) -> 20 | D13: =SUMIF('Среднее доначисление'!C:C,'KPI-20 ДГД'!A13,'Среднее доначисление'!M:M) -> 10 | E13: =SUMIF(Занятость!C:C,'KPI-20 ДГД'!A13,Занятость!G:G) -> 0 | F13: =SUMIF(Проводимые!C:C,'KPI-20 ДГД'!A13,Проводимые!G:G) -> 10 | G13: =SUMIF(Отмененные!C:C,'KPI-20 ДГД'!A13,Отмененные!J:J) -> 15 | H13: =SUM(B13:G13) -> 65 | I13: =RANK(H13,$H$4:$H$23,0) -> 14
A14: Мангистауская | B14: =SUMIF(Доначисление!C:C,'KPI-20 ДГД'!A14,Доначисление!O:O) -> 10 | C14: =SUMIF(Взыскание!C:C,'KPI-20 ДГД'!A14,Взыскание!L:L) -> 10 | D14: =SUMIF('Среднее доначисление'!C:C,'KPI-20 ДГД'!A14,'Среднее доначисление'!M:M) -> 10 | E14: =SUMIF(Занятость!C:C,'KPI-20 ДГД'!A14,Занятость!G:G) -> 5 | F14: =SUMIF(Проводимые!C:C,'KPI-20 ДГД'!A14,Проводимые!G:G) -> 0 | G14: =SUMIF(Отмененные!C:C,'KPI-20 ДГД'!A14,Отмененные!J:J) -> 15 | H14: =SUM(B14:G14) -> 50 | I14: =RANK(H14,$H$4:$H$23,0) -> 19
A15: Павлодарская | B15: =SUMIF(Доначисление!C:C,'KPI-20 ДГД'!A15,Доначисление!O:O) -> 10 | C15: =SUMIF(Взыскание!C:C,'KPI-20 ДГД'!A15,Взыскание!L:L) -> 40 | D15: =SUMIF('Среднее доначисление'!C:C,'KPI-20 ДГД'!A15,'Среднее доначисление'!M:M) -> 10 | E15: =SUMIF(Занятость!C:C,'KPI-20 ДГД'!A15,Занятость!G:G) -> 15 | F15: =SUMIF(Проводимые!C:C,'KPI-20 ДГД'!A15,Проводимые!G:G) -> 10 | G15: =SUMIF(Отмененные!C:C,'KPI-20 ДГД'!A15,Отмененные!J:J) -> 15 | H15: =SUM(B15:G15) -> 100 | I15: =RANK(H15,$H$4:$H$23,0) -> 1
... A23: Область Ұлытау | B23: =SUMIF(Доначисление!C:C,'KPI-20 ДГД'!A23,Доначисление!O:O) -> 10 | C23: =SUMIF(Взыскание!C:C,'KPI-20 ДГД'!A23,Взыскание!L:L) -> 40 | D23: =SUMIF('Среднее доначисление'!C:C,'KPI-20 ДГД'!A23,'Среднее доначисление'!M:M) -> 10 | E23: =SUMIF(Занятость!C:C,'KPI-20 ДГД'!A23,Занятость!G:G) -> 0 | F23: =SUMIF(Проводимые!C:C,'KPI-20 ДГД'!A23,Проводимые!G:G) -> 10 | G23: =SUMIF(Отмененные!C:C,'KPI-20 ДГД'!A23,Отмененные!J:J) -> 0 | H23: =SUM(B23:G23) -> 70 | I23: =RANK(H23,$H$4:$H$23,0) -> 12
A24: КГД | B24: =SUMIF(Доначисление!C:C,'KPI-20 ДГД'!A24,Доначисление!O:O) -> 10 | C24: =SUMIF(Взыскание!C:C,'KPI-20 ДГД'!A24,Взыскание!L:L) -> 40 | D24: =SUMIF('Среднее доначисление'!C:C,'KPI-20 ДГД'!A24,'Среднее доначисление'!M:M) -> 10 | E24: =SUMIF(Занятость!C:C,'KPI-20 ДГД'!A24,Занятость!G:G) -> 0 | F24: =SUMIF(Проводимые!C:C,'KPI-20 ДГД'!A24,Проводимые!G:G) -> 10 | G24: =SUMIF(Отмененные!C:C,'KPI-20 ДГД'!A24,Отмененные!J:J) -> 15 | H24: =SUM(B24:G24) -> 85 | I24: -

Sheet KPI-печать
A1: Баллы на 01.04.2026
A3: ДГД | B3: Доначисление | C3: Взыскание | D3: Доначисление на 1 проверку | E3: Коэффициент занятости | F3: Доля проверок > 6 мес, % | G3: Удельный вес отмененных сумм доначислений | H3: Баллы | I3: Позиция
A4: Павлодарская | B4: 10 | C4: 40 | D4: 10 | E4: 15 | F4: 10 | G4: 15 | H4: 100 | I4: 1
A5: г.Шымкент | B5: 10 | C5: 40 | D5: 10 | E5: 15 | F5: 10 | G5: 15 | H5: 100 | I5: 1
A6: Область Жетісу | B6: 10 | C6: 40 | D6: 10 | E6: 15 | F6: 10 | G6: 15 | H6: 100 | I6: 1
A7: Актюбинская | B7: 10 | C7: 40 | D7: 10 | E7: 5 | F7: 10 | G7: 15 | H7: 90 | I7: 4
A8: г.Алматы | B8: 10 | C8: 40 | D8: 10 | E8: 5 | F8: 10 | G8: 15 | H8: 90 | I8: 4
A9: Область Абай | B9: 10 | C9: 40 | D9: 0 | E9: 15 | F9: 10 | G9: 15 | H9: 90 | I9: 4
A10: Алматинская | B10: 10 | C10: 40 | D10: 10 | E10: 0 | F10: 10 | G10: 15 | H10: 85 | I10: 7
A11: ВКО | B11: 10 | C11: 40 | D11: 10 | E11: 0 | F11: 10 | G11: 15 | H11: 85 | I11: 7
A12: Карагандинская | B12: 10 | C12: 40 | D12: 10 | E12: 15 | F12: 10 | G12: 0 | H12: 85 | I12: 7
A13: СКО | B13: 10 | C13: 40 | D13: 10 | E13: 0 | F13: 10 | G13: 15 | H13: 85 | I13: 7
A14: Кызылординская | B14: 10 | C14: 40 | D14: 0 | E14: 0 | F14: 10 | G14: 15 | H14: 75 | I14: 11
A15: г.Астана | B15: 0 | C15: 20 | D15: 10 | E15: 15 | F15: 10 | G15: 15 | H15: 70 | I15: 12
... A23: Мангистауская | B23: 10 | C23: 10 | D23: 10 | E23: 5 | F23: 0 | G23: 15 | H23: 50 | I23: 19
A24: КГД | B24: 10 | C24: 40 | D24: 10 | E24: 0 | F24: 10 | G24: 15 | H24: 85 | I24: -

Sheet Доначисление
B2: Динамика доначисленных сумм на 01.04.2026
I3: млн.тг.
B4: № | C4: ДГД | D4: Доля в % по 4 КБК | E4: Доначислено на 01.01.2026 | F4: Темп роста +120% | G4: KPI на 01.01.2027 | H4: KPI на 01.04.2026 | I4: Факт на 01.04.2026 | J4: Данные КГД на 01.04.2026 | K4: Данные ДГД на 01.04.2026 | L4: Отклонение | M4: Исполнение KPI | O4: Баллы | P4: Доначислено на 01.03.2026 | Q4: Темп роста | R4: Откл | S4: Доначислено на 01.04.2025 | T4: Темп роста
M5: в сумме | N5: в %
A6: 58xx | B6: =RANK(N6,$N$6:$N$25,0) -> 14 | C6: Туркестанская | D6: 2.614949 | E6: 7752.9492 | F6: =E6*120% -> 9303.5391 | G6: =D6%*$F$26 -> 4595.9261 | H6: 459.59261 | I6: =MIN(J6:K6) -> 492.47053 | J6: =SUMIFS('Завершенные ИНИС и ИСНА'!U:U,'Завершенные ИНИС и ИСНА'!T:T,"УНА",'Завершенные ИНИС и ИСНА'!C:C,Доначисление!A6)/1000000 -> 492.47053 | K6: =SUMIFS('Завершенные данные ДГД'!AH:AH,'Завершенные данные ДГД'!AS:AS,"УНА",'Завершенные данные ДГД'!L:L,">01.01.2026",'Завершенные данные ДГД'!C:C,Доначисление!A6)/1000000 -> 492.47053 | L6: =K6-J6 -> -4.6999997e-07 | M6: =I6-H6 -> 32.877921 | N6: =I6/H6 -> 1.0715371 | O6: =IF(N6<90%,0,IF(N6<=99.999999%,5,IF(N6>=100%,10,""))) -> 10 | P6: 78.333259 | Q6: =I6/P6*100 -> 628.68638 | R6: =I6-P6 -> 414.13727 | S6: 1786.2055 | T6: =I6/S6*100 -> 27.570766
A7: 70xx | B7: =RANK(N7,$N$6:$N$25,0) -> 1 | C7: область Жетісу | D7: 0.95788406 | E7: 3866.5806 | F7: =E7*120% -> 4639.8967 | G7: =D7%*$F$26 -> 1683.5374 | H7: 168.35374 | I7: =MIN(J7:K7) -> 1859.4109 | J7: =SUMIFS('Завершенные ИНИС и ИСНА'!U:U,'Завершенные ИНИС и ИСНА'!T:T,"УНА",'Завершенные ИНИС и ИСНА'!C:C,Доначисление!A7)/1000000 -> 1859.6706 | K7: =SUMIFS('Завершенные данные ДГД'!AH:AH,'Завершенные данные ДГД'!AS:AS,"УНА",'Завершенные данные ДГД'!L:L,">01.01.2026",'Завершенные данные ДГД'!C:C,Доначисление!A7)/1000000 -> 1859.4109 | L7: =K7-J7 -> -0.25967877 | M7: =I7-H7 -> 1691.0571 | N7: =I7/H7 -> 11.044666 | O7: =IF(N7<90%,0,IF(N7<=99.999999%,5,IF(N7>=100%,10,""))) -> 10 | P7: 1709.3888 | Q7: =I7/P7*100 -> 108.77636 | R7: =I7-P7 -> 150.02211 | S7: 1002.7767 | T7: =I7/S7*100 -> 185.42621
A8: 06xx | B8: =RANK(N8,$N$6:$N$25,0) -> 4 | C8: Актюбинская | D8: 2.9855147 | E8: 11448.066 | F8: =E8*120% -> 13737.68 | G8: =D8%*$F$26 -> 5247.2171 | H8: 524.72171 | I8: =MIN(J8:K8) -> 2608.9058 | J8: =SUMIFS('Завершенные ИНИС и ИСНА'!U:U,'Завершенные ИНИС и ИСНА'!T:T,"УНА",'Завершенные ИНИС и ИСНА'!C:C,Доначисление!A8)/1000000 -> 2608.9058 | K8: =SUMIFS('Завершенные данные ДГД'!AH:AH,'Завершенные данные ДГД'!AS:AS,"УНА",'Завершенные данные ДГД'!L:L,">01.01.2026",'Завершенные данные ДГД'!C:C,Доначисление!A8)/1000000 -> 2609.2027 | L8: =K8-J8 -> 0.2968797 | M8: =I8-H8 -> 2084.1841 | N8: =I8/H8 -> 4.9719799 | O8: =IF(N8<90%,0,IF(N8<=99.999999%,5,IF(N8>=100%,10,""))) -> 10 | P8: 2454.0845 | Q8: =I8/P8*100 -> 106.30872 | R8: =I8-P8 -> 154.8213 | S8: 2940.4076 | T8: =I8/S8*100 -> 88.725991
A9: 71xx | B9: =RANK(N9,$N$6:$N$25,0) -> 15 | C9: область Абай | D9: 1.3477265 | E9: 2720.6351 | F9: =E9*120% -> 3264.7622 | G9: =D9%*$F$26 -> 2368.7083 | H9: 236.87083 | I9: =MIN(J9:K9) -> 241.51539 | J9: =SUMIFS('Завершенные ИНИС и ИСНА'!U:U,'Завершенные ИНИС и ИСНА'!T:T,"УНА",'Завершенные ИНИС и ИСНА'!C:C,Доначисление!A9)/1000000 -> 241.51539 | K9: =SUMIFS('Завершенные данные ДГД'!AH:AH,'Завершенные данные ДГД'!AS:AS,"УНА",'Завершенные данные ДГД'!L:L,">01.01.2026",'Завершенные данные ДГД'!C:C,Доначисление!A9)/1000000 -> 241.5434 | L9: =K9-J9 -> 0.02801262 | M9: =I9-H9 -> 4.6445619 | N9: =I9/H9 -> 1.019608 | O9: =IF(N9<90%,0,IF(N9<=99.999999%,5,IF(N9>=100%,10,""))) -> 10 | P9: 1.206162 | Q9: =I9/P9*100 -> 20023.462 | R9: =I9-P9 -> 240.30923 | S9: 749.06747 | T9: =I9/S9*100 -> 32.242141
A10: 21xx | B10: =RANK(N10,$N$6:$N$25,0) -> 17 | C10: Жамбылская | D10: 1.3672005 | E10: 2764.1785 | F10: =E10*120% -> 3317.0141 | G10: =D10%*$F$26 -> 2402.935 | H10: 240.2935 | I10: =MIN(J10:K10) -> 39.948959 | J10: =SUMIFS('Завершенные ИНИС и ИСНА'!U:U,'Завершенные ИНИС и ИСНА'!T:T,"УНА",'Завершенные ИНИС и ИСНА'!C:C,Доначисление!A10)/1000000 -> 40.145475 | K10: =SUMIFS('Завершенные данные ДГД'!AH:AH,'Завершенные данные ДГД'!AS:AS,"УНА",'Завершенные данные ДГД'!L:L,">01.01.2026",'Завершенные данные ДГД'!C:C,Доначисление!A10)/1000000 -> 39.948959 | L10: =K10-J10 -> -0.19651583 | M10: =I10-H10 -> -200.34454 | N10: =I10/H10 -> 0.16625068 | O10: =IF(N10<90%,0,IF(N10<=99.999999%,5,IF(N10>=100%,10,""))) -> 0 | P10: 5.202512 | Q10: =I10/P10*100 -> 767.87826 | R10: =I10-P10 -> 34.746447 | S10: 1517.7456 | T10: =I10/S10*100 -> 2.6321248
A11: 59xx | B11: =RANK(N11,$N$6:$N$25,0) -> 2 | C11: г.Шымкент | D11: 3.0326739 | E11: 7812.3703 | F11: =E11*120% -> 9374.8444 | G11: =D11%*$F$26 -> 5330.1022 | H11: 533.01022 | I11: =MIN(J11:K11) -> 4102.124 | J11: =SUMIFS('Завершенные ИНИС и ИСНА'!U:U,'Завершенные ИНИС и ИСНА'!T:T,"УНА",'Завершенные ИНИС и ИСНА'!C:C,Доначисление!A11)/1000000 -> 4102.3672 | K11: =SUMIFS('Завершенные данные ДГД'!AH:AH,'Завершенные данные ДГД'!AS:AS,"УНА",'Завершенные данные ДГД'!L:L,">01.01.2026",'Завершенные данные ДГД'!C:C,Доначисление!A11)/1000000 -> 4102.124 | L11: =K11-J11 -> -0.2431344 | M11: =I11-H11 -> 3569.1138 | N11: =I11/H11 -> 7.6961452 | O11: =IF(N11<90%,0,IF(N11<=99.999999%,5,IF(N11>=100%,10,""))) -> 10 | P11: 3590.2077 | Q11: =I11/P11*100 -> 114.25868 | R11: =I11-P11 -> 511.91634 | S11: 3801.0442 | T11: =I11/S11*100 -> 107.92098
A12: 33xx | B12: =RANK(N12,$N$6:$N$25,0) -> 13 | C12: Кызылординская | D12: 2.029 | E12: 4541.9624 | F12: =E12*120% -> 5450.3549 | G12: =D12%*$F$26 -> 3566.0865 | H12: 356.60865 | I12: =MIN(J12:K12) -> 407.49043 | J12: =SUMIFS('Завершенные ИНИС и ИСНА'!U:U,'Завершенные ИНИС и ИСНА'!T:T,"УНА",'Завершенные ИНИС и ИСНА'!C:C,Доначисление!A12)/1000000 -> 407.65693 | K12: =SUMIFS('Завершенные данные ДГД'!AH:AH,'Завершенные данные ДГД'!AS:AS,"УНА",'Завершенные данные ДГД'!L:L,">01.01.2026",'Завершенные данные ДГД'!C:C,Доначисление!A12)/1000000 -> 407.49043 | L12: =K12-J12 -> -0.16649927 | M12: =I12-H12 -> 50.881779 | N12: =I12/H12 -> 1.1426824 | O12: =IF(N12<90%,0,IF(N12<=99.999999%,5,IF(N12>=100%,10,""))) -> 10 | P12: 33.364663 | Q12: =I12/P12*100 -> 1221.3234 | R12: =I12-P12 -> 374.12577 | S12: 454.12563 | T12: =I12/S12*100 -> 89.73077
A13: 48xx | B13: =RANK(N13,$N$6:$N$25,0) -> 6 | C13: СКО | D13: 1.1647603 | E13: 1116.0235 | F13: =E13*120% -> 1339.2282 | G13: =D13%*$F$26 -> 2047.1346 | H13: 204.71346 | I13: =MIN(J13:K13) -> 718.23921 | J13: =SUMIFS('Завершенные ИНИС и ИСНА'!U:U,'Завершенные ИНИС и ИСНА'!T:T,"УНА",'Завершенные ИНИС и ИСНА'!C:C,Доначисление!A13)/1000000 -> 718.23921 | K13: =SUMIFS('Завершенные данные ДГД'!AH:AH,'Завершенные данные ДГД'!AS:AS,"УНА",'Завершенные данные ДГД'!L:L,">01.01.2026",'Завершенные данные ДГД'!C:C,Доначисление!A13)/1000000 -> 718.23921 | L13: =K13-J13 -> 0 | M13: =I13-H13 -> 513.52576 | N13: =I13/H13 -> 3.50851 | O13: =IF(N13<90%,0,IF(N13<=99.999999%,5,IF(N13>=100%,10,""))) -> 10 | P13: 101.80685 | Q13: =I13/P13*100 -> 705.492 | R13: =I13-P13 -> 616.43236 | S13: 623.26405 | T13: =I13/S13*100 -> 115.23835
A14: 43xx | B14: =RANK(N14,$N$6:$N$25,0) -> 3 | C14: Мангистауская | D14: 2.8331699 | E14: 4907.9639 | F14: =E14*120% -> 5889.5567 | G14: =D14%*$F$26 -> 4979.4622 | H14: 497.94622 | I14: =MIN(J14:K14) -> 2808.6616 | J14: =SUMIFS('Завершенные ИНИС и ИСНА'!U:U,'Завершенные ИНИС и ИСНА'!T:T,"УНА",'Завершенные ИНИС и ИСНА'!C:C,Доначисление!A14)/1000000 -> 2985.8145 | K14: =SUMIFS('Завершенные данные ДГД'!AH:AH,'Завершенные данные ДГД'!AS:AS,"УНА",'Завершенные данные ДГД'!L:L,">01.01.2026",'Завершенные данные ДГД'!C:C,Доначисление!A14)/1000000 -> 2808.6616 | L14: =K14-J14 -> -177.15289 | M14: =I14-H14 -> 2310.7154 | N14: =I14/H14 -> 5.6404918 | O14: =IF(N14<90%,0,IF(N14<=99.999999%,5,IF(N14>=100%,10,""))) -> 10 | P14: 507.77715 | Q14: =I14/P14*100 -> 553.12879 | R14: =I14-P14 -> 2300.8844 | S14: 1257.9869 | T14: =I14/S14*100 -> 223.26637
A15: 39xx | B15: =RANK(N15,$N$6:$N$25,0) -> 12 | C15: Костанайская | D15: 2.0764292 | E15: 2093.6257 | F15: =E15*120% -> 2512.3509 | G15: =D15%*$F$26 -> 3649.4461 | H15: 364.94461 | I15: =MIN(J15:K15) -> 440.40228 | J15: =SUMIFS('Завершенные ИНИС и ИСНА'!U:U,'Завершенные ИНИС и ИСНА'!T:T,"УНА",'Завершенные ИНИС и ИСНА'!C:C,Доначисление!A15)/1000000 -> 440.40228 | K15: =SUMIFS('Завершенные данные ДГД'!AH:AH,'Завершенные данные ДГД'!AS:AS,"УНА",'Завершенные данные ДГД'!L:L,">01.01.2026",'Завершенные данные ДГД'!C:C,Доначисление!A15)/1000000 -> 440.43752 | L15: =K15-J15 -> 0.03523728 | M15: =I15-H15 -> 75.45767 | N15: =I15/H15 -> 1.2067647 | O15: =IF(N15<90%,0,IF(N15<=99.999999%,5,IF(N15>=100%,10,""))) -> 10 | P15: 380.43948 | Q15: =I15/P15*100 -> 115.76146 | R15: =I15-P15 -> 59.962801 | S15: 891.17098 | T15: =I15/S15*100 -> 49.418382
A16: 15xx | B16: =RANK(N16,$N$6:$N$25,0) -> 18 | C16: Атырауская | D16: 5.7606993 | E16: 6315.985 | F16: =E16*120% -> 7579.182 | G16: =D16%*$F$26 -> 10124.767 | H16: 1012.4767 | I16: =MIN(J16:K16) -> 83.797924 | J16: =SUMIFS('Завершенные ИНИС и ИСНА'!U:U,'Завершенные ИНИС и ИСНА'!T:T,"УНА",'Завершенные ИНИС и ИСНА'!C:C,Доначисление!A16)/1000000 -> 83.797924 | K16: =SUMIFS('Завершенные данные ДГД'!AH:AH,'Завершенные данные ДГД'!AS:AS,"УНА",'Завершенные данные ДГД'!L:L,">01.01.2026",'Завершенные данные ДГД'!C:C,Доначисление!A16)/1000000 -> 83.809821 | L16: =K16-J16 -> 0.01189732 | M16: =I16-H16 -> -928.67874 | N16: =I16/H16 -> 0.082765289 | O16: =IF(N16<90%,0,IF(N16<=99.999999%,5,IF(N16>=100%,10,""))) -> 0 | P16: 36.650885 | Q16: =I16/P16*100 -> 228.6382 | R16: =I16-P16 -> 47.147039 | S16: 914.12818 | T16: =I16/S16*100 -> 9.1669774
A17: 60xx | B17: =RANK(N17,$N$6:$N$25,0) -> 7 | C17: г.Алматы | D17: 34.155969 | E17: 39277.384 | F17: =E17*120% -> 47132.861 | G17: =D17%*$F$26 -> 60031.118 | H17: 6003.1118 | I17: =MIN(J17:K17) -> 18998.209 | J17: =SUMIFS('Завершенные ИНИС и ИСНА'!U:U,'Завершенные ИНИС и ИСНА'!T:T,"УНА",'Завершенные ИНИС и ИСНА'!C:C,Доначисление!A17)/1000000 -> 18998.209 | K17: =SUMIFS('Завершенные данные ДГД'!AH:AH,'Завершенные данные ДГД'!AS:AS,"УНА",'Завершенные данные ДГД'!L:L,">01.01.2026",'Завершенные данные ДГД'!C:C,Доначисление!A17)/1000000 -> 18998.567 | L17: =K17-J17 -> 0.35828207 | M17: =I17-H17 -> 12995.097 | N17: =I17/H17 -> 3.1647269 | O17: =IF(N17<90%,0,IF(N17<=99.999999%,5,IF(N17>=100%,10,""))) -> 10 | P17: 4984.1401 | Q17: =I17/P17*100 -> 381.17325 | R17: =I17-P17 -> 14014.069 | S17: 9285.3339 | T17: =I17/S17*100 -> 204.60448
... A25: 03xx | B25: =RANK(N25,$N$6:$N$25,0) -> 20 | C25: Акмолинская | D25: 2.0551297 | E25: 1659.8398 | F25: =E25*120% -> 1991.8077 | G25: =D25%*$F$26 -> 3612.0109 | H25: 361.20109 | I25: =MIN(J25:K25) -> 4.635403 | J25: =SUMIFS('Завершенные ИНИС и ИСНА'!U:U,'Завершенные ИНИС и ИСНА'!T:T,"УНА",'Завершенные ИНИС и ИСНА'!C:C,Доначисление!A25)/1000000 -> 4.6354078 | K25: =SUMIFS('Завершенные данные ДГД'!AH:AH,'Завершенные данные ДГД'!AS:AS,"УНА",'Завершенные данные ДГД'!L:L,">01.01.2026",'Завершенные данные ДГД'!C:C,Доначисление!A25)/1000000 -> 4.635403 | L25: =K25-J25 -> -4.77e-06 | M25: =I25-H25 -> -356.56569 | N25: =I25/H25 -> 0.012833303 | O25: =IF(N25<90%,0,IF(N25<=99.999999%,5,IF(N25>=100%,10,""))) -> 0 | P25: 4.635403 | Q25: =I25/P25*100 -> 100 | R25: =I25-P25 -> 0 | S25: 154.69126 | T25: =I25/S25*100 -> 2.9965512
B26: Итого | C26: КГД | D26: =SUM(D6:D25) -> 100 | E26: =SUM(E6:E25) -> 146463.22 | F26: =SUM(F6:F25) -> 175755.86 | G26: =SUM(G6:G25) -> 175755.86 | H26: =SUM(H6:H25) -> 17575.586 | I26: =SUM(I6:I25) -> 42066.551 | J26: =SUM(J6:J25) -> 42245.761 | K26: =SUM(K6:K25) -> 42068.52 | L26: =SUM(L6:L25) -> -177.24126 | M26: =I26-H26 -> 24490.965 | N26: =I26/H26 -> 2.3934651 | O26: =IF(N26<90%,0,IF(N26<=99.999999%,5,IF(N26>=100%,10,""))) -> 10 | P26: =SUM(P6:P25) -> 19791.79 | Q26: =I26/P26*100 -> 212.54547 | R26: =SUM(R6:R25) -> 22274.762 | S26: =SUM(S6:S25) -> 33013.641 | T26: =I26/S26*100 -> 127.42173

Sheet Лист1
B2: Динамика доначисленных сумм на 01.04.2026
I3: млн.тг.
B4: № | C4: ДГД | D4: Доля в % по 4 КБК | E4: Доначислено на 01.01.2026 | F4: Темп роста +120% | G4: KPI на 01.01.2027 | H4: KPI на 01.04.2026 | I4: Факт на 01.04.2026 | J4: Исполнение KPI | L4: Баллы | M4: Доначислено на 01.04.2025 | N4: Темп роста
J5: в сумме | K5: в %
A6: 70xx | B6: 1 | C6: область Жетісу | D6: 0.95788406 | E6: 3866.5806 | F6: 4639.8967 | G6: 1683.5374 | H6: 168.35374 | I6: 1859.4109 | J6: 1691.0571 | K6: 11.044666 | L6: 10 | M6: 1002.7767 | N6: 185.42621
A7: 59xx | B7: 2 | C7: г.Шымкент | D7: 3.0326739 | E7: 7812.3703 | F7: 9374.8444 | G7: 5330.1022 | H7: 533.01022 | I7: 4102.124 | J7: 3569.1138 | K7: 7.6961452 | L7: 10 | M7: 3801.0442 | N7: 107.92098
A8: 43xx | B8: 3 | C8: Мангистауская | D8: 2.8331699 | E8: 4907.9639 | F8: 5889.5567 | G8: 4979.4622 | H8: 497.94622 | I8: 2808.6616 | J8: 2310.7154 | K8: 5.6404918 | L8: 10 | M8: 1257.9869 | N8: 223.26637
A9: 06xx | B9: 4 | C9: Актюбинская | D9: 2.9855147 | E9: 11448.066 | F9: 13737.68 | G9: 5247.2171 | H9: 524.72171 | I9: 2608.9058 | J9: 2084.1841 | K9: 4.9719799 | L9: 10 | M9: 2940.4076 | N9: 88.725991
A10: 30xx | B10: 5 | C10: Карагандинская | D10: 4.2474376 | E10: 4695.1737 | F10: 5634.2085 | G10: 7465.1205 | H10: 746.51205 | I10: 3604.2166 | J10: 2857.7045 | K10: 4.8280755 | L10: 10 | M10: 1174.7914 | N10: 306.79629
A11: 48xx | B11: 6 | C11: СКО | D11: 1.1647603 | E11: 1116.0235 | F11: 1339.2282 | G11: 2047.1346 | H11: 204.71346 | I11: 718.23921 | J11: 513.52576 | K11: 3.50851 | L11: 10 | M11: 623.26405 | N11: 115.23835
A12: 09xx | B12: 7 | C12: Алматинская | D12: 3.9059212 | E12: 12006.997 | F12: 14408.397 | G12: 6864.8855 | H12: 686.48855 | I12: 1511.0814 | J12: 824.59283 | K12: 2.2011749 | L12: 10 | M12: 801.2529 | N12: 188.58982
A13: 45xx | B13: 8 | C13: Павлодарская | D13: 2.9290283 | E13: 4518.6039 | F13: 5422.3247 | G13: 5147.939 | H13: 514.7939 | I13: 1070.5822 | J13: 555.78834 | K13: 2.0796327 | L13: 10 | M13: 709.06418 | N13: 150.98524
A14: 18xx | B14: 9 | C14: ВКО | D14: 2.8241989 | E14: 2538.0597 | F14: 3045.6717 | G14: 4963.6951 | H14: 496.36951 | I14: 704.02056 | J14: 207.65106 | K14: 1.4183397 | L14: 10 | M14: 152.36159 | N14: 462.07221
A15: 72xx | B15: 10 | C15: Область Ұлытау | D15: 0.69154453 | E15: 830.55508 | F15: 996.6661 | G15: 1215.43 | H15: 121.543 | I15: 158.85571 | J15: 37.312709 | K15: 1.3069918 | L15: 10 | M15: 221.13674 | N15: 71.835965
A16: 39xx | B16: 11 | C16: Костанайская | D16: 2.0764292 | E16: 2093.6257 | F16: 2512.3509 | G16: 3649.4461 | H16: 364.94461 | I16: 440.40228 | J16: 75.45767 | K16: 1.2067647 | L16: 10 | M16: 891.17098 | N16: 49.418382
A17: 33xx | B17: 12 | C17: Кызылординская | D17: 2.029 | E17: 4541.9624 | F17: 5450.3549 | G17: 3566.0865 | H17: 356.60865 | I17: 407.49043 | J17: 50.881779 | K17: 1.1426824 | L17: 10 | M17: 454.12563 | N17: 89.73077
... A25: 03xx | B25: 20 | C25: Акмолинская | D25: 2.0551297 | E25: 1659.8398 | F25: 1991.8077 | G25: 3612.0109 | H25: 361.20109 | I25: 4.635403 | J25: -356.56569 | K25: 0.012833303 | L25: 0 | M25: 154.69126 | N25: 2.9965512
B26: Итого | D26: 100 | E26: 146463.22 | F26: 175755.86 | G26: 175755.86 | H26: 17575.586 | I26: 29135.957 | J26: 11560.371 | K26: 1.6577517 | L26: 10 | M26: 33013.641 | N26: 127

Sheet Взыскание
B2: Структура взысканных сумм на 01.04.2026
I3: млн.тг.
B4: № | C4: ДГД | D4: Доля в % по 4 КБК | E4: Взыскано на 01.01.2026 | F4: Темп роста +120% | G4: KPI на 01.01.2027 | H4: KPI на 01.04.2026 | I4: Факт на 01.04.2026 | J4: Исполнение KPI | L4: Баллы | M4: Взыскано на 01.03.2026 | N4: Темп роста | O4: Откл | P4: Взыскано на 01.04.2025 | Q4: Темп роста
J5: в сумме | K5: в %
A6: 21xx | B6: =RANK(K6,$K$6:$K$25,0) -> 1 | C6: Жамбылская | D6: 1.3672005 | E6: 2619.5385 | F6: =E6*120% -> 3143.4462 | G6: =D6%*$F$26 -> 931.52772 | H6: 93.152772 | I6: =SUMIFS('Завершенные данные ДГД'!AM:AM,'Завершенные данные ДГД'!AT:AT,"да",'Завершенные данные ДГД'!C:C,Взыскание!A6)/1000000 -> 854.66994 | J6: =I6-H6 -> 761.51716 | K6: =I6/H6 -> 9.1749276 | L6: =IF(K6<80%,0,IF(K6<90%,10,IF(K6<=99.9%,20,IF(K6>=100%,40,"")))) -> 40 | M6: 812.30452 | N6: =I6/M6*100 -> 105.21546 | O6: =I6-M6 -> 42.36542 | P6: 383.64331 | Q6: =I6/P6*100 -> 222.77723
A7: 59xx | B7: =RANK(K7,$K$6:$K$25,0) -> 12 | C7: г.Шымкент | D7: 3.0326739 | E7: 2050.2551 | F7: =E7*120% -> 2460.3061 | G7: =D7%*$F$26 -> 2066.2806 | H7: 206.62806 | I7: =SUMIFS('Завершенные данные ДГД'!AM:AM,'Завершенные данные ДГД'!AT:AT,"да",'Завершенные данные ДГД'!C:C,Взыскание!A7)/1000000 -> 255.38722 | J7: =I7-H7 -> 48.759161 | K7: =I7/H7 -> 1.2359755 | L7: =IF(K7<80%,0,IF(K7<90%,10,IF(K7<=99.9%,20,IF(K7>=100%,40,"")))) -> 40 | M7: 159.15669 | N7: =I7/M7*100 -> 160.46277 | O7: =I7-M7 -> 96.230533 | P7: 1767.5859 | Q7: =I7/P7*100 -> 14.448363
A8: 33xx | B8: =RANK(K8,$K$6:$K$25,0) -> 13 | C8: Кызылординская | D8: 2.029 | E8: 2471.0836 | F8: =E8*120% -> 2965.3004 | G8: =D8%*$F$26 -> 1382.4379 | H8: 138.24379 | I8: =SUMIFS('Завершенные данные ДГД'!AM:AM,'Завершенные данные ДГД'!AT:AT,"да",'Завершенные данные ДГД'!C:C,Взыскание!A8)/1000000 -> 165.0742 | J8: =I8-H8 -> 26.830409 | K8: =I8/H8 -> 1.1940804 | L8: =IF(K8<80%,0,IF(K8<90%,10,IF(K8<=99.9%,20,IF(K8>=100%,40,"")))) -> 40 | M8: 76.36711 | N8: =I8/M8*100 -> 216.15876 | O8: =I8-M8 -> 88.707088 | P8: 161.87218 | Q8: =I8/P8*100 -> 101.97812
A9: 43xx | B9: =RANK(K9,$K$6:$K$25,0) -> 20 | C9: Мангистауская | D9: 2.8331699 | E9: 2262.2558 | F9: =E9*120% -> 2714.707 | G9: =D9%*$F$26 -> 1930.3506 | H9: 193.03506 | I9: =SUMIFS('Завершенные данные ДГД'!AM:AM,'Завершенные данные ДГД'!AT:AT,"да",'Завершенные данные ДГД'!C:C,Взыскание!A9)/1000000 -> 166.45599 | J9: =I9-H9 -> -26.579068 | K9: =I9/H9 -> 0.86230964 | L9: =IF(K9<80%,0,IF(K9<90%,10,IF(K9<=99.9%,20,IF(K9>=100%,40,"")))) -> 10 | M9: 66.867593 | N9: =I9/M9*100 -> 248.93373 | O9: =I9-M9 -> 99.588401 | P9: 408.06508 | Q9: =I9/P9*100 -> 40.791531
A10: 06xx | B10: =RANK(K10,$K$6:$K$25,0) -> 3 | C10: Актюбинская | D10: 2.9855147 | E10: 1837.3025 | F10: =E10*120% -> 2204.763 | G10: =D10%*$F$26 -> 2034.1491 | H10: 203.41491 | I10: =SUMIFS('Завершенные данные ДГД'!AM:AM,'Завершенные данные ДГД'!AT:AT,"да",'Завершенные данные ДГД'!C:C,Взыскание!A10)/1000000 -> 1301.693 | J10: =I10-H10 -> 1098.2781 | K10: =I10/H10 -> 6.3992016 | L10: =IF(K10<80%,0,IF(K10<90%,10,IF(K10<=99.9%,20,IF(K10>=100%,40,"")))) -> 40 | M10: 1261.4166 | N10: =I10/M10*100 -> 103.19295 | O10: =I10-M10 -> 40.276386 | P10: 887.47805 | Q10: =I10/P10*100 -> 146.67327
A11: 39xx | B11: =RANK(K11,$K$6:$K$25,0) -> 18 | C11: Костанайская | D11: 2.0764292 | E11: 1106.1252 | F11: =E11*120% -> 1327.3502 | G11: =D11%*$F$26 -> 1414.7533 | H11: 141.47533 | I11: =SUMIFS('Завершенные данные ДГД'!AM:AM,'Завершенные данные ДГД'!AT:AT,"да",'Завершенные данные ДГД'!C:C,Взыскание!A11)/1000000 -> 141.16053 | J11: =I11-H11 -> -0.3147962 | K11: =I11/H11 -> 0.9977749 | L11: =IF(K11<80%,0,IF(K11<90%,10,IF(K11<=99.9%,20,IF(K11>=100%,40,"")))) -> 20 | M11: 114.05017 | N11: =I11/M11*100 -> 123.77055 | O11: =I11-M11 -> 27.110358 | P11: 444.85742 | Q11: =I11/P11*100 -> 31.731635
A12: 18xx | B12: =RANK(K12,$K$6:$K$25,0) -> 5 | C12: ВКО | D12: 2.8241989 | E12: 1737.9054 | F12: =E12*120% -> 2085.4865 | G12: =D12%*$F$26 -> 1924.2383 | H12: 192.42383 | I12: =SUMIFS('Завершенные данные ДГД'!AM:AM,'Завершенные данные ДГД'!AT:AT,"да",'Завершенные данные ДГД'!C:C,Взыскание!A12)/1000000 -> 592.34982 | J12: =I12-H12 -> 399.92599 | K12: =I12/H12 -> 3.07836 | L12: =IF(K12<80%,0,IF(K12<90%,10,IF(K12<=99.9%,20,IF(K12>=100%,40,"")))) -> 40 | M12: 477.41027 | N12: =I12/M12*100 -> 124.07563 | O12: =I12-M12 -> 114.93955 | P12: 411.74894 | Q12: =I12/P12*100 -> 143.86189
A13: 71xx | B13: =RANK(K13,$K$6:$K$25,0) -> 17 | C13: область Абай | D13: 1.3477265 | E13: 765.32661 | F13: =E13*120% -> 918.39193 | G13: =D13%*$F$26 -> 918.2593 | H13: 91.82593 | I13: =SUMIFS('Завершенные данные ДГД'!AM:AM,'Завершенные данные ДГД'!AT:AT,"да",'Завершенные данные ДГД'!C:C,Взыскание!A13)/1000000 -> 92.042939 | J13: =I13-H13 -> 0.21700945 | K13: =I13/H13 -> 1.0023633 | L13: =IF(K13<80%,0,IF(K13<90%,10,IF(K13<=99.9%,20,IF(K13>=100%,40,"")))) -> 40 | M13: 15.434638 | N13: =I13/M13*100 -> 596.34012 | O13: =I13-M13 -> 76.608301 | P13: 30.063802 | Q13: =I13/P13*100 -> 306.15868
A14: 58xx | B14: =RANK(K14,$K$6:$K$25,0) -> 14 | C14: Туркестанская | D14: 2.614949 | E14: 903.24458 | F14: =E14*120% -> 1083.8935 | G14: =D14%*$F$26 -> 1781.6681 | H14: 178.16681 | I14: =SUMIFS('Завершенные данные ДГД'!AM:AM,'Завершенные данные ДГД'!AT:AT,"да",'Завершенные данные ДГД'!C:C,Взыскание!A14)/1000000 -> 197.50011 | J14: =I14-H14 -> 19.333304 | K14: =I14/H14 -> 1.1085124 | L14: =IF(K14<80%,0,IF(K14<90%,10,IF(K14<=99.9%,20,IF(K14>=100%,40,"")))) -> 40 | M14: 59.805365 | N14: =I14/M14*100 -> 330.23812 | O14: =I14-M14 -> 137.69475 | P14: 248.91945 | Q14: =I14/P14*100 -> 79.342982
A15: 30xx | B15: =RANK(K15,$K$6:$K$25,0) -> 8 | C15: Карагандинская | D15: 4.2474376 | E15: 2804.0401 | F15: =E15*120% -> 3364.8482 | G15: =D15%*$F$26 -> 2893.947 | H15: 289.3947 | I15: =SUMIFS('Завершенные данные ДГД'!AM:AM,'Завершенные данные ДГД'!AT:AT,"да",'Завершенные данные ДГД'!C:C,Взыскание!A15)/1000000 -> 551.82157 | J15: =I15-H15 -> 262.42686 | K15: =I15/H15 -> 1.9068129 | L15: =IF(K15<80%,0,IF(K15<90%,10,IF(K15<=99.9%,20,IF(K15>=100%,40,"")))) -> 40 | M15: 223.98907 | N15: =I15/M15*100 -> 246.36094 | O15: =I15-M15 -> 327.8325 | P15: 945.74625 | Q15: =I15/P15*100 -> 58.347741
A16: 70xx | B16: =RANK(K16,$K$6:$K$25,0) -> 10 | C16: область Жетісу | D16: 0.95788406 | E16: 496.48554 | F16: =E16*120% -> 595.78264 | G16: =D16%*$F$26 -> 652.64426 | H16: 65.264426 | I16: =SUMIFS('Завершенные данные ДГД'!AM:AM,'Завершенные данные ДГД'!AT:AT,"да",'Завершенные данные ДГД'!C:C,Взыскание!A16)/1000000 -> 94.391891 | J16: =I16-H16 -> 29.127465 | K16: =I16/H16 -> 1.4462993 | L16: =IF(K16<80%,0,IF(K16<90%,10,IF(K16<=99.9%,20,IF(K16>=100%,40,"")))) -> 40 | M16: 40.051735 | N16: =I16/M16*100 -> 235.67491 | O16: =I16-M16 -> 54.340156 | P16: 32.506977 | Q16: =I16/P16*100 -> 290.37425
A17: 45xx | B17: =RANK(K17,$K$6:$K$25,0) -> 15 | C17: Павлодарская | D17: 2.9290283 | E17: 1354.14 | F17: =E17*120% -> 1624.968 | G17: =D17%*$F$26 -> 1995.6627 | H17: 199.56627 | I17: =SUMIFS('Завершенные данные ДГД'!AM:AM,'Завершенные данные ДГД'!AT:AT,"да",'Завершенные данные ДГД'!C:C,Взыскание!A17)/1000000 -> 208.333 | J17: =I17-H17 -> 8.7667204 | K17: =I17/H17 -> 1.0439289 | L17: =IF(K17<80%,0,IF(K17<90%,10,IF(K17<=99.9%,20,IF(K17>=100%,40,"")))) -> 40 | M17: 56.978891 | N17: =I17/M17*100 -> 365.63189 | O17: =I17-M17 -> 151.3541 | P17: 12.346654 | Q17: =I17/P17*100 -> 1687.364
... A25: 62xx | B25: =RANK(K25,$K$6:$K$25,0) -> 19 | C25: г.Астана | D25: 21.109391 | E25: 9013.7223 | F25: =E25*120% -> 10816.467 | G25: =D25%*$F$26 -> 14382.662 | H25: 1438.2662 | I25: =SUMIFS('Завершенные данные ДГД'!AM:AM,'Завершенные данные ДГД'!AT:AT,"да",'Завершенные данные ДГД'!C:C,Взыскание!A25)/1000000 -> 1316.3046 | J25: =I25-H25 -> -121.9616 | K25: =I25/H25 -> 0.91520234 | L25: =IF(K25<80%,0,IF(K25<90%,10,IF(K25<=99.9%,20,IF(K25>=100%,40,"")))) -> 20 | M25: 325.0477 | N25: =I25/M25*100 -> 404.95736 | O25: =I25-M25 -> 991.25689 | P25: 16.806 | Q25: =I25/P25*100 -> 7832.3491
B26: Итого | C26: КГД | D26: =SUM(D6:D25) -> 100 | E26: =SUM(E6:E25) -> 56778.293 | F26: =SUM(F6:F25) -> 68133.951 | G26: =SUM(G6:G25) -> 68133.951 | H26: =SUM(H6:H25) -> 6813.3951 | I26: =SUM(I6:I25) -> 15205.795 | J26: =I26-H26 -> 8392.4001 | K26: =I26/H26 -> 2.2317501 | L26: =IF(K26<80%,0,IF(K26<90%,10,IF(K26<=99.9%,20,IF(K26>=100%,40,"")))) -> 40 | M26: =SUM(M6:M25) -> 6143.3193 | N26: =I26/M26*100 -> 247.51758 | O26: =SUM(O6:O25) -> 9062.4759 | P26: =SUM(P6:P25) -> 14031.418 | Q26: =I26/P26*100 -> 108.36963

Sheet Лист2
B2: Структура взысканных сумм на 01.04.2026
H3: млн.тг.
B4: № | C4: ДГД | D4: Доля в % по 4 КБК | E4: Взыскано на 01.01.2026 | F4: Темп роста +120% | G4: KPI на 01.01.2027 | H4: KPI на 01.04.2026 | I4: Факт на 01.04.2026 | J4: Исполнение KPI | L4: Баллы | M4: Взыскано на 01.04.2025 | N4: Темп роста
J5: в сумме | K5: в %
A6: 21xx | B6: 1 | C6: Жамбылская | D6: 1.3672005 | E6: 2619.5385 | F6: 3143.4462 | G6: 931.52772 | H6: 93.152772 | I6: 854.66994 | J6: 761.51716 | K6: 9.1749276 | L6: 40 | M6: 383.64331 | N6: 222.77723
A7: 03xx | B7: 2 | C7: Акмолинская | D7: 2.0551297 | E7: 789.06613 | F7: 946.87936 | G7: 1400.2411 | H7: 140.02411 | I7: 961.45756 | J7: 821.43345 | K7: 6.8663716 | L7: 40 | M7: 277.6975 | N7: 346.22478
A8: 06xx | B8: 3 | C8: Актюбинская | D8: 2.9855147 | E8: 1837.3025 | F8: 2204.763 | G8: 2034.1491 | H8: 203.41491 | I8: 1301.693 | J8: 1098.2781 | K8: 6.3992016 | L8: 40 | M8: 887.47805 | N8: 146.67327
A9: 27xx | B9: 4 | C9: ЗКО | D9: 1.9113729 | E9: 1279.9542 | F9: 1535.9451 | G9: 1302.2939 | H9: 130.22939 | I9: 402.34887 | J9: 272.11948 | K9: 3.0895398 | L9: 40 | M9: 202.32816 | N9: 198.85955
A10: 18xx | B10: 5 | C10: ВКО | D10: 2.8241989 | E10: 1737.9054 | F10: 2085.4865 | G10: 1924.2383 | H10: 192.42383 | I10: 592.34982 | J10: 399.92599 | K10: 3.07836 | L10: 40 | M10: 411.74894 | N10: 143.86189
A11: 15xx | B11: 6 | C11: Атырауская | D11: 5.7606993 | E11: 3303.7358 | F11: 3964.483 | G11: 3924.9921 | H11: 392.49921 | I11: 1174.8994 | J11: 782.40024 | K11: 2.9933804 | L11: 40 | M11: 228.8861 | N11: 513.31183
A12: 60xx | B12: 7 | C12: г.Алматы | D12: 34.155969 | E12: 17830.632 | F12: 21396.759 | G12: 23271.811 | H12: 2327.1811 | I12: 6208.7656 | J12: 3881.5844 | K12: 2.667934 | L12: 40 | M12: 7265.4486 | N12: 85.456052
A13: 30xx | B13: 8 | C13: Карагандинская | D13: 4.2474376 | E13: 2804.0401 | F13: 3364.8482 | G13: 2893.947 | H13: 289.3947 | I13: 551.82157 | J13: 262.42686 | K13: 1.9068129 | L13: 40 | M13: 945.74625 | N13: 58.347741
A14: 48xx | B14: 9 | C14: СКО | D14: 1.1647603 | E14: 669.59727 | F14: 803.51672 | G14: 793.59724 | H14: 79.359724 | I14: 139.63351 | J14: 60.273789 | K14: 1.759501 | L14: 40 | M14: 220.76463 | N14: 63.249948
A15: 70xx | B15: 10 | C15: область Жетісу | D15: 0.95788406 | E15: 496.48554 | F15: 595.78264 | G15: 652.64426 | H15: 65.264426 | I15: 94.391891 | J15: 29.127465 | K15: 1.4462993 | L15: 40 | M15: 32.506977 | N15: 290.37425
A16: 09xx | B16: 11 | C16: Алматинская | D16: 3.9059212 | E16: 2999.96 | F16: 3599.9521 | G16: 2661.2585 | H16: 266.12585 | I16: 333.55386 | J16: 67.428019 | K16: 1.2533689 | L16: 40 | M16: 84.652784 | N16: 394.02586
A17: 59xx | B17: 12 | C17: г.Шымкент | D17: 3.0326739 | E17: 2050.2551 | F17: 2460.3061 | G17: 2066.2806 | H17: 206.62806 | I17: 255.38722 | J17: 48.759161 | K17: 1.2359755 | L17: 40 | M17: 1767.5859 | N17: 14.448363
... A20: 45xx | B20: 15 | C20: Павлодарская | D20: 2.9290283 | E20: 1354.14 | F20: 1624.968 | G20: 1995.6627 | H20: 199.56627 | I20: 208.333 | J20: 8.7667204 | K20: 1.0439289 | L20: 40 | M20: 12.346654 | N20: 1687.364
A21: 72xx | B21: 16 | C21: область Ұлытау | D21: 0.69154453 | E21: 483.92191 | F21: 580.70629 | G21: 471.17661 | H21: 47.117661 | I21: 47.951655 | J21: 0.83399344 | K21: 1.0177002 | L21: 40 | M21: 0 | N21: #DIV/0!
A22: 71xx | B22: 17 | C22: область Абай | D22: 1.3477265 | E22: 765.32661 | F22: 918.39193 | G22: 918.2593 | H22: 91.82593 | I22: 92.042939 | J22: 0.21700945 | K22: 1.0023633 | L22: 40 | M22: 30.063802 | N22: 306.15868
A23: 39xx | B23: 18 | C23: Костанайская | D23: 2.0764292 | E23: 1106.1252 | F23: 1327.3502 | G23: 1414.7533 | H23: 141.47533 | I23: 141.16053 | J23: -0.3147962 | K23: 0.9977749 | L23: 20 | M23: 444.85742 | N23: 31.731635
A24: 62xx | B24: 19 | C24: г.Астана | D24: 21.109391 | E24: 9013.7223 | F24: 10816.467 | G24: 14382.662 | H24: 1438.2662 | I24: 1316.3046 | J24: -121.9616 | K24: 0.91520234 | L24: 20 | M24: 16.806 | N24: 7832.3491
A25: 43xx | B25: 20 | C25: Мангистауская | D25: 2.8331699 | E25: 2262.2558 | F25: 2714.707 | G25: 1930.3506 | H25: 193.03506 | I25: 166.45599 | J25: -26.579068 | K25: 0.86230964 | L25: 10 | M25: 408.06508 | N25: 40.791531
B26: Итого | D26: 100 | E26: 56778.293 | F26: 68133.951 | G26: 68133.951 | H26: 6813.3951 | I26: 15205.795 | J26: 8392.4001 | K26: 2.2317501 | L26: 40 | M26: 14031.418 | N26: 108.36963

Sheet Завершенные данные ДГД
B1: Дата обновления информации | C1: Код ДГД | D1: Департамент | E1: БИН/ИИН | F1: Наименование НП | G1: №предписания | H1: ИСНА-ИНИС | I1: № акта | J1: Дата открытия дела | K1: Дата вручения предписания | L1: Дата окон-о акта | M1: Дата вручения уведомления | N1: Форма проверки | O1: Форма проверки - правильная | R1: Проверяемый период | T1: Ф.И.О. ответственного исполнителя | U1: Субъектность (по данным МНЭ РК) | V1: Мониторинг/Недрапользователь | W1: Фактический вид деятельности (не по ИНИС) | X1: Орган инициирования (заявление НП/Приказ КГД МФ РК/ Список выборочных проверок/в рамках ВУД/требование Прокуратуры и т.д.) | Y1: Приказ КГД МФ РК | AA1: Другие органы | AD1: СГД общее за проверяемый период, в тенге | AE1: КНН средний | AG1: Результаты КЭР | AS1: Управление | AT1: Взыскание Принято - да; не принято - нет | AU1: ДР март | AV1: КЭР прошлые года | AW1: Донач-Взыскание | AX1: Взыскание налог ПП | AY1: Взыскание налог переплата | AZ1: Взыскание пеня ПП | BA1: Взыскание пеня переплата | BB1: Штраф | BC1: Примечание по взысканию | BD1: Донач ИНИС/ИСНА | BE1: Примечание | BF1: ЗПЛ | BG1: ЗПЛ | BH1: ЗПЛ
R2: С (ДД.ММ.ГГГГ) | S2: По (ДД.ММ.ГГГГ) | Y2: Номер | Z2: Дата | AA2: Наименование органа | AB2: Номер | AC2: дата | AG2: КБК | AH2: доначислено всего | AI2: доначислено | AK2: уменьшенный убыток | AL2: штраф | AM2: взыскано всего | AN2: взыскано | BI2: Сумма ДР за март
AI3: налог | AJ3: пеня | AN3: налог | AP3: пеня | AR3: штраф
AN4: ПП | AO4: переплата | AP4: ПП | AQ4: переплата | BF4: 2025г. | BG4: 2024г. | BH4: 2023г.
AH5: =SUBTOTAL(9,AH7:AH1048576) -> 1.3498718e+09 | AI5: =SUBTOTAL(9,AI7:AI1048576) -> 1.2389594e+09 | AJ5: =SUBTOTAL(9,AJ7:AJ1048576) -> 110912482 | AK5: =SUBTOTAL(9,AK7:AK1048576) -> 0 | AL5: =SUBTOTAL(9,AL7:AL1048576) -> 0 | AM5: =SUBTOTAL(9,AM7:AM1048576) -> 148596233 | AN5: =SUBTOTAL(9,AN7:AN1048576) -> 10454725 | AO5: =SUBTOTAL(9,AO7:AO1048576) -> 26949647 | ... AR5: =SUBTOTAL(9,AR7:AR1048576) -> 0 | BD5: фыв | BF5: 3.0089094e+09 | BG5: #N/A | BH5: #N/A | BI5: 2.2574002e+09
A6: 0 | B6: 1 | C6: 2 | D6: 3 | E6: 4 | F6: 5 | G6: 6 | H6: 6 | I6: 7 | J6: 8 | K6: 9 | L6: 10 | M6: 11 | N6: 12 | O6: 12 | R6: 13 | S6: 14 | T6: 15 | U6: 16 | V6: 17 | W6: 18 | X6: 19 | Y6: 20 | Z6: 21 | AA6: 22 | AB6: 23 | AC6: 24 | AD6: 25 | AE6: 26 | AG6: 27 | AH6: 28 | AI6: 29 | AJ6: 30 | AK6: 31 | AL6: 32 | AM6: 33 | AN6: 34 | AO6: 35 | AP6: 36 | AQ6: 37 | AR6: 38 | BI6: фыв
A7: =CONCATENATE(C7,"-",E7,"-",G7) -> 60xx-750125400329-815 | B7: 46107 | C7: 60xx | D7: г.Алматы | E7: 750125400329 | F7: КЕМЕЛЬБАЕВА САНДУГАШ САДЫКОВНА | G7: 815 | H7: ИНИС | I7: 815 | J7: 45432 | K7: 45432 | L7: 45685 | O7: тематическая | R7: 44197 | S7: 45291 | T7: Асхамбаева Г.Х. | U7: нет данных | W7: <нет данных> | X7: Заявление налогоплательщика на ликвидацию | AF7: МБ | AG7: 101202 | AH7: =AI7+AJ7 -> 3864438381 | AI7: 2966066099 | AJ7: 898372282 | AK7: 0 | AL7: 0 | AM7: =AN7+AO7+AP7+AQ7+AR7 -> 4418066099 | AN7: 2926066099 | AO7: 40000000 | AP7: 1452000000 | AQ7: 0 | AR7: 0 | AS7: #N/A | AT7: да | AU7: нет | AV7: правильно | AW7: правильно | AX7: да | AY7: да | AZ7: да | BD7: правильно
A8: =CONCATENATE(C8,"-",E8,"-",G8) -> 15xx-980441001505-23 | B8: 46064 | C8: 15xx | D8: Атырауская | E8: 980441001505 | F8: "ФИЛИАЛ КОМПАНИИ С ОГРАНИЧЕННОЙ ОТВЕТСТВЕННОСТЬЮ БЕЙКЕР ХЬЮЗ СЕРВИСЕЗ ИНТЕРНЕШНЛ ЛЛСи (BAKER HUGHES SERVICES INTERNATIONAL LLC) В КАЗАХСТАНЕ". | G8: 23 | H8: ИНИС | I8: 40277 | J8: 40460 | L8: 46013 | O8: тематическая | R8: 44562 | S8: 45657 | T8: Байсалбаев М | U8: крупный | W8: роизводство продуктов нефтепереработки | X8: КГД МФ РК | AF8: РБ | AG8: 101110 | AH8: =AI8+AJ8 -> 1020721614 | AI8: 1020721614 | AJ8: 0 | AK8: 0 | AL8: 0 | AM8: =AN8+AO8+AP8+AQ8+AR8 -> 1020721614 | AN8: 1020721614 | AO8: 0 | AP8: 0 | AQ8: 0 | AR8: 0 | AS8: #N/A | AT8: да | AU8: 0 | AV8: правильно | AW8: правильно | AZ8: да | BD8: правильно
A9: =CONCATENATE(C9,"-",E9,"-",G9) -> 18xx-941040000097-180120250916TAC0006 | B9: 46071 | C9: 18xx | D9: ВКО | E9: 941040000097 | F9: АО "УМЗ" | G9: 180120250916TAC0006 | H9: ИСНА | I9: 180120250929OAP0001 | J9: 45916 | K9: 45924 | L9: 46002 | M9: 46006 | N9: тематическая | O9: Тематическая проверка | R9: 43831 | S9: 45291 | T9: Амирова Ж.К | U9: СКП | W9: Переработка ядерного топлива | X9: Приказ КГД МФ РК | Y9: 878 | Z9: 45912 | AD9: 357410759825 | AE9: 7.6 | AF9: РБ | AG9: 101110 | AH9: =AI9+AJ9 -> 983602729 | AI9: 983602729 | AJ9: 0 | AK9: 0 | AL9: 393441092 | AM9: =AN9+AO9+AP9+AQ9+AR9 -> 983602729 | AN9: 0 | AO9: 983602729 | AP9: 0 | AQ9: 0 | AR9: 0 | AS9: #N/A | AT9: нет | AU9: нет | AV9: правильно | AW9: правильно | AY9: да | BB9: да | BD9: правильно | BE9: мониторинг
A10: =CONCATENATE(C10,"-",E10,"-",G10) -> 03xx-20840001753-364 | B10: 46085 | C10: 03xx | D10: Акмолинская | E10: 20840001753 | F10: ГКП на ПХВ "Термо-Транзит" при отделе жилищно-коммунального хозяйства и жилищной инспекции Бурабайского района | G10: 364 | H10: ИНИС | I10: 364 | J10: 43712 | K10: 43719 | L10: 43839 | M10: 43840 | N10: тематическая | O10: #N/A | R10: 41640 | S10: 43465 | T10: Ертаев Е.А. | U10: микро | W10: Производство тепловой энергии самостоятельными котельными | X10: Решение государственного органа | AD10: 9269373333 | AE10: 0.8 | AF10: МБ | AG10: 101111 | AH10: =AI10+AJ10 -> 521587658 | AI10: 475920026 | AJ10: 45667632 | AK10: 0 | AL10: 111459660 | AM10: =AN10+AO10+AP10+AQ10+AR10 -> 924440127 | AN10: 410995906 | AO10: 0 | AP10: 401984561 | AQ10: 0 | AR10: 111459660 | AS10: #N/A | AT10: да | AU10: нет | AV10: норм | AW10: правильно | AX10: да | AZ10: да | BB10: да | BD10: правильно | BF10: 0 | BG10: #N/A | BH10: 0
A11: =CONCATENATE(C11,"-",E11,"-",G11) -> 21xx-81040006263-43 | B11: 46036 | C11: 21xx | D11: Жамбылская | E11: 81040006263 | F11: ТОО "Golden Compass Capital" | G11: 43 | H11: ИНИС | I11: 43 | J11: 45183 | K11: 45211 | L11: 45337 | M11: 45337 | O11: комплексная | R11: 43831 | S11: 44926 | T11: Косдаулетов К. | U11: Субъекты среднего предпринимательства | V11: нет | W11: Производство благородных (драгоценных) металлов | X11: Представление прокуратуры | Y11: 02-07-23-09120 | Z11: 45173 | AD11: 26529391912 | AE11: 0.8 | AF11: РБ | AG11: 101110 | AH11: =AI11+AJ11 -> 829029945 | AI11: 675597762 | AJ11: 153432183 | AK11: 1455198032 | AL11: 0 | AM11: =AN11+AO11+AP11+AQ11+AR11 -> 601870000 | AN11: 601870000 | AO11: 0 | AP11: 0 | AQ11: 0 | AR11: 0 | AS11: #N/A | AT11: да | AU11: 0 | AV11: правильно | AW11: правильно | AX11: да | BD11: правильно
A12: =CONCATENATE(C12,"-",E12,"-",G12) -> 60xx-970440003326-2302 | B12: 46078 | C12: 60xx | D12: г.Алматы | E12: 970440003326 | F12: АО Колеса | G12: 2302 | H12: ИНИС | I12: 2302 | J12: 45636 | K12: 45636 | L12: 46048 | O12: Тематическая | R12: 43466 | S12: 45291 | T12: Тынымбаев М.А. | U12: Крупное предпринимательство | X12: КГД МФ РК | AF12: РБ | AG12: 101110 | AH12: =AI12+AJ12 -> 12929864771 | AI12: 7834799272 | AJ12: 5095065499 | AK12: 0 | AL12: 0 | AM12: =AN12+AO12+AP12+AQ12+AR12 -> 405000000 | AN12: 405000000 | AO12: 0 | AP12: 0 | AQ12: 0 | AR12: 0 | AS12: УНА | AT12: да | AU12: да | AV12: 2026г. | AW12: правильно | AX12: да | BD12: правильно | BI12: 405000000
A13: =CONCATENATE(C13,"-",E13,"-",G13) -> 60xx-640004487-865 | B13: 46085 | C13: 60xx | D13: г.Алматы | E13: 640004487 | F13: ТОО "Мэри Кэй(Казахстан)" | G13: 865 | H13: ИНИС | I13: 865 | J13: 45160 | K13: 45160 | L13: 45260 | M13: 45261 | O13: тематическая | R13: 43101 | S13: 44926 | T13: Турешбаева Г.А. | U13: Крупное предпринимательство | W13: N47751 | X13: КГД МФ РК | AF13: РБ | AG13: 101110 | AH13: =AI13+AJ13 -> 2271513577 | AI13: 1370327728 | AJ13: 901185849 | AK13: 0 | AL13: 0 | AM13: =AN13+AO13+AP13+AQ13+AR13 -> 366120540 | AN13: 0 | AO13: 0 | AP13: 0 | AQ13: 0 | AR13: 366120540 | AS13: #N/A | AT13: да | AU13: нет | AV13: штраф | AW13: правильно | BB13: да | BD13: правильно
A14: =CONCATENATE(C14,"-",E14,"-",G14) -> 06xx-40540006757-120 | B14: 46050 | C14: 06xx | D14: Актюбинская | E14: 40540006757 | F14: ТОО "Актобе-Саулет" | G14: 120 | H14: ИНИС | I14: 120 | J14: 45810 | K14: 45818 | L14: 46048 | M14: 46048 | O14: Тематическая | R14: 44562 | S14: 45657 | T14: Жумашева Г. | U14: ССП | V14: - | W14: Строительство | X14: КГД МФ РК | Y14: - | Z14: - | AA14: - | AB14: - | AC14: - | AD14: 9147359571 | AE14: 7.05 | AF14: РБ | AG14: 105101 | AH14: =AI14+AJ14 -> 293606999 | AI14: 273931989 | AJ14: 19675010 | AK14: 0 | AL14: 0 | AM14: =AN14+AO14+AP14+AQ14+AR14 -> 293606999 | AN14: 96582043 | AO14: 177349946 | AP14: 19675010 | AQ14: 0 | AR14: 0 | AS14: УНА | AT14: да | AU14: да | AV14: 2026г. | AW14: правильно | AX14: да | AY14: да | AZ14: да | BD14: правильно | BI14: 423131
A15: =CONCATENATE(C15,"-",E15,"-",G15) -> 06xx-31040005996-060120250813TAC0002 | B15: 45713 | C15: 06xx | D15: Актюбинская | E15: 31040005996 | F15: ТОО "Актобе мунай маш комплект" | G15: 060120250813TAC0002 | H15: ИСНА | I15: 060120250813TAC0002 | J15: 45882 | K15: 45894 | L15: 46042 | M15: 46042 | N15: тематическая | O15: Тематическая проверка | R15: 44835 | S15: 45199 | T15: Жумашева Г. | U15: СКП | V15: - | W15: Строительство | X15: КГД МФ РК | Y15: 780 | Z15: 45880 | AA15: - | AB15: - | AC15: - | AD15: 46394970209 | AE15: 7.35 | AF15: РБ | AG15: 105101 | AH15: =AI15+AJ15 -> 223817148 | AI15: 146510138 | AJ15: 77307010 | AK15: 0 | AL15: 0 | AM15: =AN15+AO15+AP15+AQ15+AR15 -> 282421203 | AN15: 146510138 | AO15: 0 | AP15: 77307010 | AQ15: 0 | AR15: 58604055 | AS15: УНА | AT15: да | AU15: 0 | AV15: 2026г. | AW15: правильно | AX15: да | AZ15: да | BB15: да | BD15: правильно
A16: =CONCATENATE(C16,"-",E16,"-",G16) -> 03xx-100740005561-182 | B16: 46085 | C16: 03xx | D16: Акмолинская | E16: 100740005561 | F16: ТОО "Казахстанская Агро Инновационная Корпорация" | G16: 182 | H16: ИНИС | I16: 182 | J16: 45496 | K16: 45510 | L16: 46042 | M16: 46042 | O16: Тематическая | R16: 43831 | S16: 45291 | T16: Ертаев Е.А. | U16: крупный | W16: Производство сельскохозяйственных машин | X16: КГД МФ РК | Y16: 257 | Z16: 45490 | AD16: 184361097431 | AE16: 2.8 | AF16: РБ | AG16: 101110 | AH16: =AI16+AJ16 -> 561571384 | AI16: 462625583 | AJ16: 98945801 | AK16: 0 | AL16: 0 | AM16: =AN16+AO16+AP16+AQ16+AR16 -> 254878740 | AN16: 254878740 | AO16: 0 | AP16: 0 | AQ16: 0 | AR16: 0 | AS16: ДКН/СД | AT16: нет | AU16: нет | AV16: 2026г. | AW16: правильно | AX16: да | BD16: правильно | BE16: мониторинг | BI16: -
A17: =CONCATENATE(C17,"-",E17,"-",G17) -> 60xx-31040005137-605 | B17: 46078 | C17: 60xx | D17: г.Алматы | E17: 31040005137 | F17: ТОО "Euroasia Transit Group" ("Евразия Транзит Груп") | G17: 605 | H17: ИНИС | I17: 605 | J17: 45799 | K17: 45799 | L17: 46036 | O17: Комплексная | R17: 44562 | S17: 45291 | T17: Митаева Б.Т. | U17: Среднее предпринимательство | X17: Другие заявления налогоплательщика | AF17: МБ | AG17: 101111 | AH17: =AI17+AJ17 -> 925034682 | AI17: 686146554 | AJ17: 238888128 | AK17: 0 | AL17: 0 | AM17: =AN17+AO17+AP17+AQ17+AR17 -> 250619000 | AN17: 0 | AO17: 0 | AP17: 250619000 | AQ17: 0 | AR17: 0 | AS17: УНА | AT17: да | AU17: нет | AV17: 2026г. | AW17: правильно | AZ17: да | BD17: правильно
A18: =CONCATENATE(C18,"-",E18,"-",G18) -> 06xx-70340011917-44 | B18: 45713 | C18: 06xx | D18: Актюбинская | E18: 70340011917 | F18: ТОО "AктобеНефтегазстрой" | G18: 44 | H18: ИНИС | I18: 44 | J18: 44644 | K18: 44656 | L18: 44830 | M18: 44830 | O18: комплексная | R18: 43101 | S18: 44561 | T18: Жумашева Г. | U18: ССП | V18: - | W18: Прочие строительно-монтажные работы, не включенные в другие группировки | X18: Список проверок, проводимых по особому порядку | Y18: - | AE18: 10.02 | AF18: МБ | AG18: 101111 | AH18: =AI18+AJ18 -> 319472941 | AI18: 266493541 | AJ18: 52979400 | AK18: 0 | AL18: 0 | AM18: =AN18+AO18+AP18+AQ18+AR18 -> 241632909 | AN18: 241632909 | AO18: 0 | AP18: 0 | AQ18: 0 | AR18: 0 | AS18: #N/A | AT18: да | AU18: нет | AV18: норм | AW18: правильно | AX18: да | BD18: правильно | BF18: 0 | BG18: #N/A | BH18: 0
A19: =CONCATENATE(C19,"-",E19,"-",G19) -> 60xx-100140009384-1849 | B19: 46078 | C19: 60xx | D19: г.Алматы | E19: 100140009384 | F19: ТОО ЗМ Казахстан | G19: 1849 | H19: ИНИС | I19: 1849 | J19: 45601 | K19: 45601 | L19: 46006 | O19: комплексная | R19: 44197 | S19: 45594 | T19: Аблаева А.М. | U19: Среднее предпринимательство | W19: N46909 | X19: Заявление налогоплательщика на ликвидацию | AF19: РБ | AG19: 105101 | AH19: =AI19+AJ19 -> 235591191 | AI19: 170325213 | AJ19: 65265978 | AK19: 0 | AL19: 42581303 | AM19: =AN19+AO19+AP19+AQ19+AR19 -> 2.1426688e+08 | AN19: 0 | AO19: 1.7036885e+08 | AP19: =43898035 -> 43898035 | AQ19: 0 | AR19: 0 | AS19: #N/A | AT19: да | AU19: да | AW19: правильно | AY19: да | AZ19: да | BB19: да | BD19: правильно | BF19: 0 | BG19: 0 | BH19: 0 | BI19: 43898035
A20: =CONCATENATE(C20,"-",E20,"-",G20) -> 62xx-70240003251-420 | B20: 46113 | C20: 62xx | D20: г.Астана | E20: 70240003251 | F20: ТОО "Мегастрой лтд" | G20: 420 | H20: ИНИС | I20: 420 | J20: 45407 | K20: 45427 | L20: 45677 | M20: 45677 | O20: тематическая | R20: 43831 | S20: 45291 | T20: Есеркепова А.Р. | U20: смп | W20: Строительство | X20: КГД МФ РК | Y20: 148 | Z20: 45406 | AD20: 112636262215 | AF20: РБ | AG20: 105101 | AH20: =AI20+AJ20 -> 1.7020908e+08 | AI20: 130497109 | AJ20: 39711970 | AK20: 0 | AL20: 0 | AM20: =AN20+AO20+AP20+AQ20+AR20 -> 209449328 | AN20: 209449328 | AO20: 0 | AP20: 0 | AQ20: 0 | AR20: 0 | AS20: #N/A | AT20: да | AU20: да | AW20: взыскание больше донач | AX20: да | BD20: правильно | BF20: 0 | BG20: 0 | BH20: 0 | BI20: 209449328
A21: =CONCATENATE(C21,"-",E21,"-",G21) -> 18xx-80240021886-180120250814TAC0001 | B21: 46085 | C21: 18xx | D21: ВКО | E21: 80240021886 | F21: ТОО "ОблШығысЖол" | G21: 180120250814TAC0001 | H21: ИСНА | I21: 180120250924OAP0002 | J21: 45883 | K21: 45924 | L21: 46020 | M21: 46022 | N21: тематическая | O21: Тематическая проверка | R21: 43831 | S21: 45657 | T21: Ханжин В.А | U21: СКП | W21: Деятельность по организации строительства | X21: приказ КГД МФ РК | Y21: 744 | Z21: 45877 | AD21: 94358058806 | AE21: 6.2 | AF21: РБ | AG21: 101110 | AH21: =AI21+AJ21 -> 1.4235878e+08 | AI21: 1.1677258e+08 | AJ21: 25586202 | AK21: 0 | AL21: 0 | AM21: =AN21+AO21+AP21+AQ21+AR21 -> 1.6535878e+08 | AN21: 116772583 | AO21: 0 | AP21: 25586202 | AQ21: 0 | AR21: 23000000 | AS21: #N/A | AT21: да | AU21: 0 | AW21: правильно | AX21: да | AZ21: да | BB21: да | BD21: правильно | BF21: 0
A22: =CONCATENATE(C22,"-",E22,"-",G22) -> 45xx-10240007203-45 | B22: 46107 | C22: 45xx | D22: Павлодарская | E22: 10240007203 | F22: ТОО "NFC Kazakhstan" | G22: 45 | H22: ИНИС | I22: 45 | J22: 45393 | K22: 45453 | L22: 45701 | M22: 45701 | O22: тематическая | R22: 43466 | S22: 44926 | T22: Сыздыкбаев К.А. | U22: крупного | X22: Решение органа государственных доходов | Y22: 587 | Z22: 45274 | AF22: РБ | AG22: 101110 | AH22: =AI22+AJ22 -> 3.3272263e+08 | AI22: 286794866 | AJ22: 45927766 | AK22: 0 | AL22: 0 | AM22: =AN22+AO22+AP22+AQ22+AR22 -> 141000000 | AN22: 141000000 | AO22: 0 | AP22: 0 | AQ22: 0 | AR22: 0 | AS22: #N/A | AT22: да | AU22: да | AW22: правильно | AX22: да | BD22: правильно | BF22: 0 | BG22: 0 | BH22: 0 | BI22: 141000000
A23: =CONCATENATE(C23,"-",E23,"-",G23) -> 21xx-41140005608-50 | B23: 46099 | C23: 21xx | D23: Жамбылская | E23: 41140005608 | F23: АО "Таразэнергоцентр" | G23: 50 | H23: ИНИС | I23: 50 | J23: 44482 | K23: 44487 | L23: 44648 | M23: 45252 | O23: комплексная | R23: 43101 | S23: 44377 | T23: Кожабекова Р.С. | U23: Субъекты крупного предпринимательства | V23: нет | W23: Производство и реализация электроэнергии | AA23: СУ ДЭР по жамбылской области | AD23: 14759969293 | AE23: 5.1 | AF23: РБ | AG23: 105101 | AH23: =AI23+AJ23 -> 487764397 | AI23: 412474959 | AJ23: 75289438 | AK23: 0 | AL23: 0 | AM23: =AN23+AO23+AP23+AQ23+AR23 -> 138294200 | AN23: 75685735 | AO23: 0 | AP23: 62608465 | AQ23: 0 | AR23: 0 | AS23: #N/A | AT23: да | AU23: да | AV23: правильно | AW23: правильно | AX23: да | AZ23: да | BD23: правильно | BF23: 319509422 | BG23: #N/A | BH23: 0 | BI23: 40000000
A24: =CONCATENATE(C24,"-",E24,"-",G24) -> 30xx-180340015589-265 | B24: 46099 | C24: 30xx | D24: Карагандинская | E24: 180340015589 | F24: ТОО "ТазалыкЭксперт" | G24: 265 | H24: ИНИС | I24: 265 | J24: 44790 | K24: 44812 | L24: 44980 | O24: комплексная | R24: 43172 | S24: 44742 | T24: Шалбаева М.Ш. | U24: 3. СКП | X24: периодическая проверка | AF24: РБ | AG24: 105101 | AH24: =AI24+AJ24 -> 603139287 | AI24: 603139287 | AJ24: 0 | AK24: 0 | AL24: 0 | AM24: =AN24+AO24+AP24+AQ24+AR24 -> 121900000 | AN24: 121900000 | AO24: 0 | AP24: 0 | AQ24: 0 | AR24: 0 | AS24: #N/A | AT24: да | AU24: да | AV24: норм | AW24: правильно | AX24: да | BD24: правильно | BF24: 210858675 | BG24: #N/A | BH24: #N/A | BI24: 121900000
A25: =CONCATENATE(C25,"-",E25,"-",G25) -> 62xx-70240003251-420 | B25: 46113 | C25: 62xx | D25: г.Астана | E25: 70240003251 | F25: ТОО "Мегастрой лтд" | G25: 420 | H25: ИНИС | I25: 420 | J25: 45407 | K25: 45427 | L25: 45677 | M25: 45677 | O25: тематическая | R25: 43831 | S25: 45291 | T25: Есеркепова А.Р. | U25: смп | W25: Строительство | X25: КГД МФ РК | Y25: 148 | Z25: 45406 | AD25: 112636262215 | AF25: РБ | AG25: 101110 | AH25: =AI25+AJ25 -> 117822648 | AI25: 117822648 | AJ25: 0 | AK25: 0 | AL25: 0 | AM25: =AN25+AO25+AP25+AQ25+AR25 -> 117822648 | AN25: 117822648 | AO25: 0 | AP25: 0 | AQ25: 0 | AR25: 0 | AS25: #N/A | AT25: да | AU25: да | AW25: правильно | AX25: да | BD25: правильно | BF25: 0 | BG25: 0 | BH25: 0 | BI25: 117822648
A26: =CONCATENATE(C26,"-",E26,"-",G26) -> 62xx-180540013718-816 | B26: 46107 | C26: 62xx | D26: г.Астана | E26: 180540013718 | F26: ТОО "BCD Company" | G26: 816 | H26: ИНИС | I26: 816 | J26: 45511 | K26: 45525 | L26: 45602 | O26: Тематическая | R26: 44927 | S26: 45291 | T26: Илгельдин К.К. | X26: КГД МФ РК | AF26: МБ | AG26: 101111 | AH26: =AI26+AJ26 -> 1180043317 | AI26: =1069130835 -> 1069130835 | AJ26: 110912482 | AK26: 0 | AL26: 0 | AM26: =AN26+AO26+AP26+AQ26+AR26 -> 110912482 | AN26: 0 | AO26: 0 | AP26: 110912482 | AQ26: 0 | AR26: 0 | AS26: #N/A | AT26: да | AU26: нет | AW26: правильно | AZ26: да | BD26: правильно | BF26: 0 | BG26: 0 | BH26: 0
A27: =CONCATENATE(C27,"-",E27,"-",G27) -> 06xx-70340011917-44 | B27: 45713 | C27: 06xx | D27: Актюбинская | E27: 70340011917 | F27: ТОО "AктобеНефтегазстрой" | G27: 44 | H27: ИНИС | I27: 44 | J27: 44644 | K27: 44656 | L27: 44830 | M27: 44830 | O27: комплексная | R27: 43101 | S27: 44561 | T27: Жумашева Г. | U27: ССП | V27: - | W27: Прочие строительно-монтажные работы, не включенные в другие группировки | X27: Список проверок, проводимых по особому порядку | Y27: - | AE27: 10.02 | AF27: РБ | AG27: 105101 | AH27: =AI27+AJ27 -> 110928567 | AI27: 101914485 | AJ27: 9014082 | AK27: 0 | AL27: 0 | AM27: =AN27+AO27+AP27+AQ27+AR27 -> 103890702 | AN27: 102490702 | AO27: 0 | AP27: 1400000 | AQ27: 0 | AR27: 0 | AS27: #N/A | AT27: да | AU27: 0 | AV27: правильно | AW27: правильно | AX27: да | AZ27: да | BD27: правильно | BF27: 1500000 | BG27: #N/A | BH27: 0
A28: =CONCATENATE(C28,"-",E28,"-",G28) -> 27xx-971240023128-102 | B28: 46112 | C28: 27xx | D28: ЗКО | E28: 971240023128 | F28: ТОО "Восход" | G28: 102 | H28: ИНИС | I28: 102 | J28: 44050 | K28: 44060 | L28: 44169 | M28: 44169 | O28: тематическая | R28: 42736 | S28: 44013 | T28: Берниязова М.Р. | U28: 1. СМП | W28: Прочие строительные работы, требующие специальных профессий | X28: В рамках ВУД | AD28: 1308253517 | AE28: 3.3356 | AF28: МБ | AG28: 101111 | AH28: =AI28+AJ28 -> 128286813 | AI28: 103703466 | AJ28: 24583347 | AK28: 610930796 | AL28: 0 | AM28: =AN28+AO28+AP28+AQ28+AR28 -> 103702502 | AN28: 103702502 | AO28: 0 | AP28: 0 | AQ28: 0 | AR28: 0 | AS28: #N/A | AT28: да | AU28: нет | AV28: норм | AW28: правильно | AX28: да | BD28: правильно | BF28: 0 | BG28: #N/A | BH28: #N/A
A29: =CONCATENATE(C29,"-",E29,"-",G29) -> 27xx-931240001388-159 | B29: 46045 | C29: 27xx | D29: ЗКО | E29: 931240001388 | F29: АО "Уральскводстрой" | G29: 159 | H29: ИНИС | I29: 159 | J29: 45846 | K29: 45852 | L29: 46010 | M29: 46010 | O29: тематическая | R29: 44562 | S29: 45291 | T29: Мураткалиева С.Т. | U29: 2. ССП | W29: Строительство водных сооружений | X29: Приказ КГД МФ РК | Y29: 588 | Z29: 45842 | AD29: 3237228712 | AE29: 3.9 | AF29: МБ | AG29: 101111 | AH29: =AI29+AJ29 -> 99406656 | AI29: 80572570 | AJ29: 18834086 | AK29: 7738643 | AL29: 20143142 | AM29: =AN29+AO29+AP29+AQ29+AR29 -> 99406656 | AN29: 80000000 | AO29: 572570 | AP29: 0 | AQ29: 18834086 | AR29: 0 | AS29: #N/A | AT29: да | AU29: нет | AV29: правильно | AW29: правильно | AX29: да | AY29: да | BA29: да | BD29: правильно | BF29: 20143142 | BG29: 0 | BH29: 0
A30: =CONCATENATE(C30,"-",E30,"-",G30) -> 60xx-51240001472-600120250805TAC0111 | B30: 46085 | C30: 60xx | D30: г.Алматы | E30: 51240001472 | F30: ТОО "Market Rent Company" | G30: 600120250805TAC0111 | H30: ИСНА | I30: 600120250821OAP0008 | J30: 45874 | K30: 45890 | L30: 46022 | N30: тематическая | O30: Тематическая проверка | R30: 44562 | S30: 45657 | T30: Ажимуратова Жанар Дуйсенбековна | U30: СМП | W30: Аренда (субаренда) и управление собственной или арендованной жилой недвижимостью | X30: КГД МФ РК | Y30: Приказ КГД МФ РК №699 | Z30: 45843 | AD30: 1499372046 | AE30: 6.4 | AF30: МБ | AG30: 101111 | AH30: =AI30+AJ30 -> 87371063 | AI30: 73345424 | AJ30: 14025639 | AK30: 0 | AL30: 7504527 | AM30: =AN30+AO30+AP30+AQ30+AR30 -> 94705606 | AN30: 73345424 | AO30: 0 | AP30: 14025639 | AQ30: 0 | AR30: 7334543 | AS30: #N/A | AT30: да | AU30: нет | AW30: правильно | AX30: да | AZ30: да | BB30: да | BD30: правильно | BF30: 0
A31: =CONCATENATE(C31,"-",E31,"-",G31) -> 60xx-41140004401-1358 | B31: 46078 | C31: 60xx | D31: г.Алматы | E31: 41140004401 | F31: АО "Дочерняя организация Народного Банка Казахстана "Halyk Finance" | G31: 1358 | H31: ИНИС | I31: 1358 | J31: 45513 | K31: 45513 | L31: 46020 | O31: тематическая | R31: 44197 | S31: 45291 | T31: Сабитова А.С. | U31: Среднее предпринимательство | W31: N66122 | X31: КГД МФ РК | AF31: РБ | AG31: 101110 | AH31: =AI31+AJ31 -> 77958580 | AI31: 61811090 | AJ31: 16147490 | AK31: 0 | AL31: 0 | AM31: =AN31+AO31+AP31+AQ31+AR31 -> 93411352 | AN31: 61811090 | AO31: 0 | AP31: 16147490 | AQ31: 0 | AR31: 15452772 | AS31: #N/A | AT31: да | AU31: 0 | AW31: правильно | AX31: да | AZ31: да | BB31: да | BD31: правильно | BF31: 0 | BG31: 0 | BH31: 0
A32: =CONCATENATE(C32,"-",E32,"-",G32) -> 18xx-40540002030-180120251106TAC0108 | B32: 46085 | C32: 18xx | D32: ВКО | E32: 40540002030 | F32: ТОО "ЭЛХОН" | G32: 180120251106TAC0108 | H32: ИСНА | I32: 180120251119OAP0001 | J32: 45967 | K32: 45978 | L32: 46021 | M32: 46027 | N32: тематическая | O32: Тематическая проверка | R32: 43466 | S32: 44926 | T32: Фазылова Р.А. | U32: СКП | W32: ПРОИЗВОДСТВО КИРПИЧА, ЧЕРЕПИЦЫ И ПРОЧИХ СТРОИТЕЛЬНЫХ ИЗДЕЛИЙ ИЗ ОБОЖЖЕННОЙ ГЛИНЫ | X32: Приказ КГД МФ РК | Y32: 1079 | Z32: 45961 | AD32: 11061693403 | AE32: 7.9 | AF32: РБ | AG32: 101110 | AH32: =AI32+AJ32 -> 98348995 | AI32: 50424755 | AJ32: 47924240 | AK32: 0 | AL32: 0 | AM32: =AN32+AO32+AP32+AQ32+AR32 -> 91939262 | AN32: 50424755 | AO32: 0 | AP32: 21344605 | AQ32: 0 | AR32: 20169902 | AS32: #N/A | AT32: да | AU32: 0 | AW32: правильно | AX32: да | AZ32: да | BB32: да | BD32: правильно | BF32: 0
A33: =CONCATENATE(C33,"-",E33,"-",G33) -> 30xx-970240005008-682 | B33: 46112 | C33: 30xx | D33: Карагандинская | E33: 970240005008 | F33: ТОО "Центрметаллургстрой" | G33: 682 | H33: ИНИС | I33: 682 | J33: 42949 | K33: 42957 | L33: 43020 | N33: тематическая | O33: #N/A | R33: 41275 | S33: 42369 | T33: Калдыбаев О. | AF33: МБ | AG33: 101111 | AH33: =AI33+AJ33 -> 136084365 | AI33: 88608376 | AJ33: 47475989 | AK33: 0 | AL33: 0 | AM33: =AN33+AO33+AP33+AQ33+AR33 -> 88498700 | AN33: 88498700 | AO33: 0 | AP33: 0 | AQ33: 0 | AR33: 0 | AS33: #N/A | AT33: да | AU33: нет | AW33: правильно | AX33: да | BD33: правильно | BF33: 0 | BG33: 0 | BH33: 0
A34: =CONCATENATE(C34,"-",E34,"-",G34) -> 30xx-201240025383-300120251113TAC0011 | B34: 46036 | C34: 30xx | D34: Карагандинская | E34: 201240025383 | F34: ТОО "АВТОТЕХИНМАШ" | G34: 300120251113TAC0011 | H34: ИСНА | I34: 300120251202OAP0024 | J34: 45974 | K34: 45993 | L34: 46017 | N34: тематическая | O34: Тематическая проверка | R34: 44562 | S34: 45291 | T34: Кайроллаев Р.А. | U34: 2. ССП | W34: 33125 РЕМОНТ И ТЕХНИЧЕСКОЕ ОБСЛУЖИВАНИЕ ПРОЧИХ МАШИН И ОБОРУДОВАНИЯ СПЕЦИАЛЬНОГО НАЗНАЧЕНИЯ | X34: Приказ КГД МФ РК | Y34: 1137 | Z34: 45971 | AF34: МБ | AG34: 101111 | AH34: =AI34+AJ34 -> 94426265 | AI34: 94426265 | AJ34: 0 | AK34: 0 | AL34: 0 | AM34: =AN34+AO34+AP34+AQ34+AR34 -> 88311833 | AN34: 58193491 | AO34: 0 | AP34: 30118342 | AQ34: 0 | AR34: 0 | AS34: #N/A | AT34: да | AU34: нет | AV34: правильно | AW34: правильно | AX34: да | AZ34: да | BD34: правильно | BF34: 14412865
A35: =CONCATENATE(C35,"-",E35,"-",G35) -> 59xx-190540011466-590120250730TAC0012 | B35: 46112 | C35: 59xx | D35: г.Шымкент | E35: 190540011466 | F35: ТОО "Управляющая компания "Shymkent Bus" | G35: 590120250730TAC0012 | H35: ИСНА | I35: 590120250806OAP0015 | J35: 45868 | K35: 45875 | L35: 46100 | M35: 46100 | N35: тематическая | O35: Тематическая проверка | R35: 44197 | S35: 45657 | T35: Лим О.П, Мирзабеков А.А. | U35: СКП | W35: Перевозки автобусами | X35: КГД МФ РК | Y35: 674 | Z35: 45867 | AD35: 29784039001 | AE35: 1.6 | AF35: МБ | AG35: 101111 | AH35: =AI35+AJ35 -> 64888378 | AI35: 54014301 | AJ35: 10874077 | AK35: 0 | AL35: 21605721 | AM35: =AN35+AO35+AP35+AQ35+AR35 -> 86494798 | AN35: 54015000 | AO35: 0 | AP35: 10874077 | AQ35: 0 | AR35: 21605721 | AS35: УНА | AT35: да | AU35: 0 | AV35: 0 | AW35: правильно | BD35: правильно
A36: =CONCATENATE(C36,"-",E36,"-",G36) -> 62xx-141040008957-398 | B36: 46071 | C36: 62xx | D36: г.Астана | E36: 141040008957 | F36: ТОО "КТЦ Казахстан" | G36: 398 | H36: ИНИС | I36: 398 | J36: 44797 | K36: 44813 | L36: 45190 | N36: комплексная | O36: #N/A | R36: 43466 | S36: 44561 | T36: Омарова Ж.Е. | X36: По особому порядку | AF36: МБ | AG36: 101111 | AH36: =AI36+AJ36 -> 2.5328768e+08 | AI36: =192515418 -> 192515418 | AJ36: =60772258.67 -> 60772259 | AK36: 0 | AL36: 0 | AM36: =AN36+AO36+AP36+AQ36+AR36 -> 85327993 | AN36: 60703950 | AO36: 0 | AP36: 24624043 | AQ36: 0 | AR36: 0 | AS36: #N/A | AT36: да | AU36: нет | AW36: правильно | AX36: да | AZ36: да | BD36: правильно | BF36: 0 | BG36: 0 | BH36: #N/A
A37: =CONCATENATE(C37,"-",E37,"-",G37) -> 18xx-80240004717-180120250822TAC0011 | B37: 46099 | C37: 18xx | D37: ВКО | E37: 80240004717 | F37: ТОО "Ostara Group" | G37: 180120250822TAC0011 | H37: ИСНА | I37: 180120250826OAP0016 | J37: 45891 | K37: 45895 | L37: 46072 | M37: 46073 | N37: тематическая | O37: Тематическая проверка | R37: 44562 | S37: 45657 | T37: Ильяшенко Ж.Е | U37: СКП | W37: Строительство жилых зданий | X37: КГД МФ РК | Y37: 716 | Z37: 45873 | AD37: 55891182231 | AE37: 6.8 | AF37: РБ | AG37: 101110 | AH37: =AI37+AJ37 -> 65083254 | AI37: 49768744 | AJ37: 15314509 | AK37: 0 | AL37: 19907498 | AM37: =AN37+AO37+AP37+AQ37+AR37 -> 84990751 | AN37: 49768744 | AO37: 0 | AP37: 15314509 | AQ37: 0 | AR37: 19907498 | AS37: УНА | AT37: да | AU37: да | AV37: 2026г. | AW37: правильно | AX37: да | AZ37: да | BB37: да | BD37: правильно | BI37: 84990751
A38: =CONCATENATE(C38,"-",E38,"-",G38) -> 62xx-160140017257-392 | B38: 46113 | C38: 62xx | D38: г.Астана | E38: 160140017257 | F38: ТОО "Казахстанско-российская сталепромышленная компания" | G38: 392 | H38: ИНИС | I38: 392 | L38: 45254 | O38: комплексная | R38: 43466 | S38: 44561 | T38: Рамазанова Самал Набихановна | AF38: РБ | AG38: 101110 | AH38: =AI38+AJ38 -> 301122478 | AI38: =301122478 -> 301122478 | AJ38: 0 | AK38: 0 | AL38: 0 | AM38: =AN38+AO38+AP38+AQ38+AR38 -> 80316591 | AN38: =80316591 -> 80316591 | AO38: 0 | AP38: 0 | AQ38: 0 | AR38: 0 | AS38: #N/A | AT38: да | AU38: да | AW38: правильно | AX38: да | BD38: правильно | BF38: 0 | BG38: 0 | BH38: #N/A | BI38: 80316591
A39: =CONCATENATE(C39,"-",E39,"-",G39) -> 09xx-50540004574-57 | B39: 46099 | C39: 09xx | D39: Алматинская | E39: 50540004574 | F39: ТОО "ASIAN BEVERAGE COMPANY" | G39: 57 | H39: ИНИС | I39: 57 | J39: 45132 | K39: 45153 | L39: 45441 | M39: 45441 | O39: Комплексная | R39: 43101 | S39: 44926 | T39: Сейдахметов Нурберген Буребаевич | U39: ССП | V39: - | W39: Дистилляция, ректификация и смешивание спиртных напитков | X39: КГД МФ РК | Y39: 7 | Z39: 45096 | AA39: - | AB39: - | AC39: - | AD39: 8712568943 | AE39: 7 | AF39: РБ | AG39: 105101 | AH39: =AI39+AJ39 -> 116647632 | AI39: 84377564 | AJ39: 32270068 | AK39: 0 | AL39: 0 | AM39: =AN39+AO39+AP39+AQ39+AR39 -> 78345424 | AN39: 56045350 | AO39: 0 | AP39: 22300074 | AQ39: 0 | AR39: 0 | AS39: #N/A | AT39: да | AU39: да | AV39: норм | AW39: правильно | AX39: да | AZ39: да | BD39: правильно | BF39: 0 | BG39: #N/A | BH39: #N/A | BI39: 78345424
A40: =CONCATENATE(C40,"-",E40,"-",G40) -> 06xx-180640033373-060120250813TAC0003 | B40: 46071 | C40: 06xx | D40: Актюбинская | E40: 180640033373 | F40: ТОО "RAMCO Refinery" | G40: 060120250813TAC0003 | H40: ИСНА | I40: 060120250813TAC0003 | J40: 45882 | K40: 45894 | L40: 46050 | M40: 46050 | N40: тематическая | O40: Тематическая проверка | R40: 44743 | S40: 45291 | T40: Сагинаева А. | U40: ССП | V40: - | W40: Производство продуктов нефтепереработки | X40: КГД МФ РК | Y40: 785 | Z40: 45880 | AA40: - | AB40: - | AC40: - | AD40: 10291718823 | AE40: 1.895 | AF40: РБ | AG40: 105101 | AH40: =AI40+AJ40 -> 203279032 | AI40: 188326108 | AJ40: 14952924 | AK40: 0 | AL40: 0 | AM40: =AN40+AO40+AP40+AQ40+AR40 -> 73563280 | AN40: 0 | AO40: 73563280 | AP40: 0 | AQ40: 0 | AR40: 0 | AS40: УНА | AT40: да | AU40: нет | AV40: 2026г. | AW40: правильно | AY40: да | BD40: правильно
A41: =CONCATENATE(C41,"-",E41,"-",G41) -> 18xx-950740001044-84 | B41: 46071 | C41: 18xx | D41: ВКО | E41: 950740001044 | F41: АО "МАЙ" | G41: 84 | H41: ИНИС | I41: 84 | J41: 44712 | K41: 44713 | L41: 44817 | M41: 44817 | O41: тематическая | R41: 44378 | S41: 44469 | T41: Байкенова Н.М. | U41: CКП | W41: ПРОИЗВОДСТВО НЕОЧИЩЕННЫХ МАСЕЛ И ЖИРОВ | X41: Приказа КГД МФ РК | Y41: 331 | Z41: 44704 | AD41: 0 | AE41: 0 | AF41: РБ | AG41: 101110 | AH41: =AI41+AJ41 -> 1.0502898e+08 | AI41: 91067856 | AJ41: 13961125 | AK41: 0 | AL41: 0 | AM41: =AN41+AO41+AP41+AQ41+AR41 -> 72854285 | AN41: 0 | AO41: 0 | AP41: 0 | AQ41: 0 | AR41: 72854285 | AS41: #N/A | AT41: да | AU41: нет | AV41: штраф | AW41: правильно | BB41: да | BD41: правильно
A42: =CONCATENATE(C42,"-",E42,"-",G42) -> 70xx-170341017003-27 | B42: 46112 | C42: 70xx | D42: Жетісу | E42: 170341017003 | F42: Казахстанский филиал "ТОО Корпорация Луцяо провинции Шаньдун" | G42: 27 | H42: ИНИС | I42: 27 | J42: 45800 | K42: 45834 | L42: 46092 | O42: Тематическая | R42: 44197 | S42: 45657 | T42: Сабдикенова С.С. | U42: средний | W42: Строительство дорог и автомагистралей | X42: Другие заявления налогоплательщика | AF42: РБ | AG42: 105101 | AH42: =AI42+AJ42 -> 61547215 | AI42: 45696987 | AJ42: 15850228 | AK42: 0 | AL42: 9226597 | AM42: =AN42+AO42+AP42+AQ42+AR42 -> 70743812 | AN42: 45696987 | AO42: 0 | AP42: 15820228 | AQ42: 0 | AR42: 9226597 | AS42: УНА | AT42: да | AU42: да | AV42: 2026г. | AW42: правильно | AX42: да | AZ42: да | BB42: да | BD42: правильно | BI42: 70743812
A43: =CONCATENATE(C43,"-",E43,"-",G43) -> 62xx-210940900312-333 | B43: 46099 | C43: 62xx | D43: г.Астана | E43: 210940900312 | F43: ЧК "Kazakhstan Future Energy Co., Ltd." | G43: 333 | H43: ИНИС | I43: 333 | J43: 45083 | L43: 45279 | N43: тематическая | O43: #N/A | R43: 44652 | S43: 44834 | T43: Бимухамбетов С.Т. | X43: Прочее | AF43: РБ | AG43: 105101 | AH43: =AI43+AJ43 -> 212307403 | AI43: 196915193 | AJ43: 15392210 | AK43: 0 | AL43: 0 | AM43: =AN43+AO43+AP43+AQ43+AR43 -> 70030000 | AN43: 70030000 | AO43: 0 | AP43: 0 | AQ43: 0 | AR43: 0 | AS43: #N/A | AT43: да | AU43: да | AW43: правильно | AX43: да | BD43: правильно | BF43: 0 | BG43: 0 | BH43: #N/A | BI43: 70030000
A44: =CONCATENATE(C44,"-",E44,"-",G44) -> 71xx-930340000251-710120250805TAC0001 | B44: 46108 | C44: 71xx | D44: Абай | E44: 930340000251 | F44: ТОО "БГП" | G44: 710120250805TAC0001 | H44: ИСНА | I44: 710120250818OAP0001 | J44: 45874 | K44: 45882 | L44: 46070 | M44: 46071 | N44: тематическая | O44: Тематическая проверка | R44: 44197 | S44: 45291 | T44: Узакова И.Р | U44: КрНП | W44: ДОБЫЧА ДРАГОЦЕННЫХ МЕТАЛЛОВ И РУД РЕДКИХ МЕТАЛЛОВ | X44: Приказ КГД МФ РК | Y44: 696 | Z44: 45870 | AD44: 708035588956 | AE44: 5 | AF44: РБ | AG44: 101110 | AH44: =AI44+AJ44 -> 135000000 | AI44: 135000000 | AJ44: 0 | AK44: 0 | AL44: 0 | AM44: =AN44+AO44+AP44+AQ44+AR44 -> 66000000 | AN44: 66000000 | AO44: 0 | AP44: 0 | AQ44: 0 | AR44: 0 | AS44: УНА | AT44: да | AU44: да | AV44: 0 | AW44: правильно | BD44: правильно | BE44: мониторинг | BI44: 66000000
A45: =CONCATENATE(C45,"-",E45,"-",G45) -> 09xx-50540004574-57 | B45: 46099 | C45: 09xx | D45: Алматинская | E45: 50540004574 | F45: ТОО "ASIAN BEVERAGE COMPANY" | G45: 57 | H45: ИНИС | I45: 57 | J45: 45132 | K45: 45153 | L45: 45441 | M45: 45441 | O45: Комплексная | R45: 43101 | S45: 44926 | T45: Сейдахметов Нурберген Буребаевич | U45: ССП | V45: - | W45: Дистилляция, ректификация и смешивание спиртных напитков | X45: КГД МФ РК | Y45: 7 | Z45: 45096 | AA45: - | AB45: - | AC45: - | AD45: 8712568943 | AE45: 7 | AF45: МБ | AG45: 101111 | AH45: =AI45+AJ45 -> 133286732 | AI45: 80539769 | AJ45: 52746963 | AK45: 0 | AL45: 0 | AM45: =AN45+AO45+AP45+AQ45+AR45 -> 65790040 | AN45: 48562499 | AO45: 0 | AP45: 17227541 | AQ45: 0 | AR45: 0 | AS45: #N/A | AT45: да | AU45: нет | AV45: норм | AW45: правильно | AX45: да | AZ45: да | BD45: правильно | BF45: 0 | BG45: #N/A | BH45: #N/A
A46: =CONCATENATE(C46,"-",E46,"-",G46) -> 21xx-40340001818-119 | B46: 46078 | C46: 21xx | D46: Жамбылская | E46: 40340001818 | F46: ТОО КА-СТРОЙ ЛТД | G46: 119 | H46: ИНИС | I46: 119 | J46: 45646 | K46: 45650 | L46: 45695 | M46: 45695 | O46: тематическая | R46: 43466 | S46: 43830 | T46: Сауранбаев Д. | U46: Субъекты крупного предпринимательства | V46: нет | W46: Строительно-монтажные работы | X46: КГД МФ РК | Y46: 578 | Z46: 45645 | AD46: 9963918901 | AE46: 3.29 | AF46: РБ | AG46: 101110 | AH46: =AI46+AJ46 -> 43110182 | AI46: 28268039 | AJ46: 14842143 | AK46: 0 | AL46: 22614431 | AM46: =AN46+AO46+AP46+AQ46+AR46 -> 65670121 | AN46: 28268039 | AO46: 0 | AP46: 14787757 | AQ46: 0 | AR46: 22614325 | AS46: #N/A | AT46: да | AU46: 0 | AW46: правильно | AX46: да | AZ46: да | BB46: да | BD46: правильно | BF46: 0 | BG46: 0 | BH46: 0
A47: =CONCATENATE(C47,"-",E47,"-",G47) -> 27xx-40240006230-270120250826TAC0002 | B47: 46045 | C47: 27xx | D47: ЗКО | E47: 40240006230 | F47: ТОО "Батысгазстрой" | G47: 270120250826TAC0002 | H47: ИСНА | I47: 270120250917ОАР0005 | J47: 45895 | K47: 45917 | L47: 46001 | M47: 46001 | N47: тематическая | O47: Тематическая проверка | R47: 44562 | S47: 45657 | T47: Любавина О.В. | U47: 1. СМП | W47: Строительство нефтяных и газовых магистральных трубопроводов | X47: Приказ КГД МФ РК | Y47: 825 | Z47: 45894 | AD47: 5253448483 | AE47: 6.62 | AF47: МБ | AG47: 101111 | AH47: =AI47+AJ47 -> 81152800 | AI47: 65325616 | AJ47: 15827184 | AK47: 0 | AL47: 16331404 | AM47: =AN47+AO47+AP47+AQ47+AR47 -> 65325616 | AN47: 0 | AO47: 65325616 | AP47: 0 | AQ47: 0 | AR47: 0 | AS47: #N/A | AT47: да | AU47: нет | AV47: норм | AW47: правильно | AY47: да | BA47: да | BD47: правильно | BF47: 16331404
A48: =CONCATENATE(C48,"-",E48,"-",G48) -> 62xx-970340004013-460 | B48: 46057 | C48: 62xx | D48: г.Астана | E48: 970340004013 | F48: ТОО "Antarium Group" | G48: 460 | H48: ИНИС | I48: 460 | J48: 45792 | K48: 45824 | L48: 45988 | M48: 45992 | O48: тематическая | R48: 44562 | S48: 45657 | T48: Муратов М.Ж. | U48: СМП | W48: СТРОИТЕЛЬСТВО | X48: КГД МФ РК | Y48: 304 | Z48: 45791 | AD48: 14096831398 | AE48: 8.2 | AF48: МБ | AG48: 101111 | AH48: =AI48+AJ48 -> 65270268 | AI48: 57111965 | AJ48: 8158303 | AK48: 0 | AL48: 0 | AM48: =AN48+AO48+AP48+AQ48+AR48 -> 65270268 | AN48: 57111965 | AO48: 0 | AP48: 8158303 | AQ48: 0 | AR48: 0 | AS48: #N/A | AT48: да | AU48: нет | AW48: правильно | AX48: да | AZ48: да | BD48: правильно | BF48: 0 | BG48: 0 | BH48: 0
A49: =CONCATENATE(C49,"-",E49,"-",G49) -> 48xx-40640004576-216 | B49: 46113 | C49: 48xx | D49: СКО | E49: 40640004576 | F49: ТОО "Агрофирма Эксимнан" | G49: 216 | H49: ИНИС | I49: 216 | J49: 45531 | K49: 45567 | L49: 45677 | M49: 45679 | O49: комплексная | R49: 43466 | S49: 44561 | T49: Кучуков Е.К. | U49: Субъекты крупного предпринимательства | V49: нет | W49: Выращивание зерновых и зернобобовых культур, включая семеноводство | X49: КГД МФ РК | Y49: 324 | Z49: 45436 | AD49: 9140819296 | AE49: 3.56 | AF49: РБ | AG49: 105101 | AH49: =AI49+AJ49 -> 14437929 | AI49: 14437929 | AJ49: 0 | AK49: 0 | AL49: 71816650 | AM49: =AN49+AO49+AP49+AQ49+AR49 -> 60495748 | AN49: 0 | AO49: 0 | AP49: 0 | AQ49: 0 | AR49: 60495748 | AS49: #N/A | AT49: да | AU49: нет | AV49: штраф | AW49: правильно | BB49: да | BD49: правильно
A50: =CONCATENATE(C50,"-",E50,"-",G50) -> 30xx-211240033910-136 | B50: 46078 | C50: 30xx | D50: Карагандинская | E50: 211240033910 | F50: ТОО "NORD Production Group" | G50: 136 | H50: ИНИС | I50: 136 | J50: 45385 | K50: 45416 | L50: 45742 | O50: комплексная | R50: 44560 | S50: 45291 | T50: Казначеева Е.А. | U50: 2. ССП | W50: Производство сборных железобетонных и бетонных конструкций и изделий | X50: периодическая проверка | AD50: 19060544529 | AE50: 5.87 | AF50: МБ | AG50: 101111 | AH50: =AI50+AJ50 -> 91644560 | AI50: 91644560 | AJ50: 0 | AK50: 0 | AL50: 0 | AM50: =AN50+AO50+AP50+AQ50+AR50 -> 56801673 | AN50: 0 | AO50: 0 | AP50: 21958787 | AQ50: 0 | AR50: 34842886 | AS50: #N/A | AT50: да | AU50: нет | AV50: норм | AW50: правильно | AZ50: да | BB50: да | BD50: правильно | BF50: 49715764 | BG50: 0 | BH50: 0
A51: =CONCATENATE(C51,"-",E51,"-",G51) -> 62xx-190340002747-282 | B51: 46099 | C51: 62xx | D51: г.Астана | E51: 190340002747 | F51: ТОО "ПЗТМ LTD" | G51: 282 | H51: ИНИС | I51: 282 | J51: 45749 | K51: 45770 | L51: 45985 | M51: 45994 | O51: тематическая | R51: 44562 | S51: 45657 | T51: Канафина Ж.А. | U51: СМП | W51: ОБРАБАТЫВАЮЩАЯ ПРОМЫШЛЕННОСТЬ | X51: КГД МФ РК | Y51: 172 | Z51: 45747 | AD51: 1834731470 | AF51: МБ | AG51: 101111 | AH51: =AI51+AJ51 -> 187443748 | AI51: 123596726 | AJ51: 63847022 | AK51: 35990390 | AL51: 0 | AM51: =AN51+AO51+AP51+AQ51+AR51 -> 54118026 | AN51: 53223026 | AO51: 0 | AP51: 895000 | AQ51: 0 | AR51: 0 | AS51: #N/A | AT51: да | AU51: нет | AV51: норм | AW51: правильно | AX51: да | AZ51: да | BD51: правильно | BF51: 6179836 | BG51: 0 | BH51: 0
A52: =CONCATENATE(C52,"-",E52,"-",G52) -> 06xx-90740016433-127 | B52: 46099 | C52: 06xx | D52: Актюбинская | E52: 90740016433 | F52: ТОО "СӘТ 888" | G52: 127 | H52: ИНИС | I52: 127 | J52: 45819 | K52: 45827 | L52: 46017 | M52: 46017 | O52: тематическая | R52: 44562 | S52: 45291 | T52: Ильясов А. | U52: ССП | V52: - | W52: Строительство | X52: КГД МФ РК | Y52: 424 | Z52: 45812 | AA52: - | AB52: - | AC52: - | AD52: 12494528134 | AE52: 6.1478 | AF52: МБ | AG52: 101111 | AH52: =AI52+AJ52 -> 39283761 | AI52: 34504031 | AJ52: 4779730 | AK52: 0 | AL52: 12544536 | AM52: =AN52+AO52+AP52+AQ52+AR52 -> 51828297 | AN52: 0 | AO52: 34504031 | AP52: 4779730 | AQ52: 0 | AR52: 12544536 | AS52: #N/A | AT52: да | AU52: нет | AW52: правильно | AY52: да | AZ52: да | BB52: да | BD52: правильно | BF52: 0 | BG52: 0 | BH52: 0
A53: =CONCATENATE(C53,"-",E53,"-",G53) -> 15xx-150840022544-101 | B53: 46071 | C53: 15xx | D53: Атырауская | E53: 150840022544 | F53: ТОО СЕВЕРН | G53: 101 | H53: ИНИС | I53: 101 | J53: 45824 | K53: 45833 | L53: 46016 | M53: 46017 | O53: комплексная | R53: 44562 | S53: 45797 | T53: Байсалбаев М | U53: средний | W53: Деятельность агентов по торговле товарами широкого ассортимента | X53: Заявление налогоплательщика на ликвидацию | AF53: РБ | AG53: 105104 | AH53: =AI53+AJ53 -> 38285315 | AI53: 38285315 | AJ53: 0 | AK53: 0 | AL53: 0 | AM53: =AN53+AO53+AP53+AQ53+AR53 -> 51278971 | AN53: 25987312 | AO53: 0 | AP53: 12298003 | AQ53: 0 | AR53: 12993656 | AS53: #N/A | AT53: да | AU53: да | AW53: правильно | AX53: да | AZ53: да | BB53: да | BD53: правильно | BF53: 0 | BG53: 0 | BH53: 0 | BI53: 51278971
A54: =CONCATENATE(C54,"-",E54,"-",G54) -> 62xx-130440029256-620120251209TAC0083 | B54: 46113 | C54: 62xx | D54: г.Астана | E54: 130440029256 | F54: ТОО "VIP Клиника" (ВИП Клиника) | G54: 620120251209TAC0083 | H54: ИСНА | I54: 620120251223OAP0003 | J54: 46000 | K54: 46014 | L54: 46112 | N54: тематическая | O54: Тематическая проверка | R54: 44562 | S54: 31.12.2024 | T54: Амангельдинова Надира Мұратқызы | U54: ССП | W54: Предоставление гостиничных услуг с ресторанами для официальных мероприятий | X54: КГД МФ РК | Y54: 1312 | Z54: 45999 | AD54: 10100837228 | AF54: МБ | AG54: 101111 | AH54: =AI54+AJ54 -> 2.0635264e+08 | AI54: 1.7063852e+08 | AJ54: 35714116 | AK54: 4455132972 | AL54: 0 | AM54: =AN54+AO54+AP54+AQ54+AR54 -> 50000000 | AN54: 50000000 | AO54: 0 | AP54: 0 | AQ54: 0 | AR54: 0 | AS54: УНА | AT54: да | AU54: нет | AV54: 2026г. | AW54: правильно | AX54: да | BD54: правильно
A55: =CONCATENATE(C55,"-",E55,"-",G55) -> 06xx-931240000101-82 | B55: 46112 | C55: 06xx | D55: Актюбинская | E55: 931240000101 | F55: АО "Авиаремонтный завод №406 гражданской авиации" | G55: 82 | H55: ИНИС | I55: 82 | J55: 44302 | K55: 44308 | L55: 44469 | M55: 44469 | O55: тематическая | R55: 43101 | S55: 44196 | T55: Жумашева | U55: ССП | V55: - | W55: Производство воздушных летательных аппаратов | X55: КГД МФ РК | Y55: - | AE55: 10.03 | AF55: МБ | AG55: 101111 | AH55: =AI55+AJ55 -> 376972522 | AI55: 311259181 | AJ55: 65713341 | AK55: 51952593 | AL55: 0 | AM55: =AN55+AO55+AP55+AQ55+AR55 -> 49679644 | AN55: 44954564 | AO55: 0 | AP55: 4725080.3 | AQ55: 0 | AR55: 0 | AS55: #N/A | AT55: да | AU55: нет | AV55: норм | AW55: правильно | AX55: да | AZ55: да | BD55: правильно | BF55: 209708034 | BG55: #N/A | BH55: 0
A56: =CONCATENATE(C56,"-",E56,"-",G56) -> 62xx-60340012936-620120250929TAC0017 | B56: 46085 | C56: 62xx | D56: г.Астана | E56: 60340012936 | F56: ТОО "M50 Consulting Group" ( М50 Консалтинг Групп) | G56: 620120250929TAC0017 | H56: ИСНА | I56: 620120251015OAP0574 | J56: 45929 | K56: 45945 | L56: 46078 | N56: тематическая | O56: Тематическая проверка | R56: 44562 | S56: 31.12.2024 | T56: Кабиев Жандос Талғатұлы | U56: ССП | W56: Профессиональная, научная и техническая деятельность | X56: КГД МФ РК | Y56: 932 | Z56: 45922 | AD56: 6867881286 | AF56: МБ | AG56: 101111 | AH56: =AI56+AJ56 -> 479383360 | AI56: 332155195 | AJ56: 147228165 | AK56: 0 | AL56: 0 | AM56: =AN56+AO56+AP56+AQ56+AR56 -> 48774910 | AN56: 19774910 | AO56: 29000000 | AP56: 0 | AQ56: 0 | AR56: 0 | AS56: УНА | AT56: да | AU56: нет | AV56: 2026г. | AW56: правильно | AX56: да | BD56: правильно
A57: =CONCATENATE(C57,"-",E57,"-",G57) -> 30xx-970240005008-682 | B57: 46112 | C57: 30xx | D57: Карагандинская | E57: 970240005008 | F57: ТОО "Центрметаллургстрой" | G57: 682 | H57: ИНИС | I57: 682 | J57: 42949 | K57: 42957 | L57: 43020 | N57: тематическая | O57: #N/A | R57: 41275 | S57: 42369 | T57: Калдыбаев О. | AF57: РБ | AG57: 105101 | AH57: =AI57+AJ57 -> 61474826 | AI57: 61474826 | AJ57: 0 | AK57: 0 | AL57: 0 | AM57: =AN57+AO57+AP57+AQ57+AR57 -> 48197036 | AN57: 48197036 | AO57: 0 | AP57: 0 | AQ57: 0 | AR57: 0 | AS57: #N/A | AT57: да | AU57: да | AW57: правильно | AX57: да | BD57: правильно | BF57: 0 | BG57: 0 | BH57: 0 | BI57: 48197036
A58: =CONCATENATE(C58,"-",E58,"-",G58) -> 62xx-41140005856-123 | B58: 46113 | C58: 62xx | D58: г.Астана | E58: 41140005856 | F58: ТОО "Астанастройэнерго" | G58: 123 | H58: ИНИС | I58: 123 | J58: 44659 | K58: 44671 | L58: 44845 | M58: 44845 | O58: тематическая | R58: 43466 | S58: 44196 | T58: Несіпбай Ж.М. | U58: скп | W58: Деятельность грузового автомобильного транспорта | X58: КГД МФ РК | Y58: 661 | Z58: 44876 | AF58: РБ | AG58: 105101 | AH58: =AI58+AJ58 -> 46972586 | AI58: 46972586 | AJ58: 0 | AK58: 0 | AL58: 0 | AM58: =AN58+AO58+AP58+AQ58+AR58 -> 46972586 | AN58: 46972586 | AO58: 0 | AP58: 0 | AQ58: 0 | AR58: 0 | AS58: #N/A | AT58: да | AU58: да | AV58: правильно | AW58: правильно | AX58: да | BD58: правильно | BF58: 79871954 | BG58: 0 | BH58: #N/A | BI58: 46972586
A59: =CONCATENATE(C59,"-",E59,"-",G59) -> 43xx-800808303430-214 | B59: 46100 | C59: 43xx | D59: Мангистауская | E59: 800808303430 | F59: БЕКБАУЛИЕВ МУРАТ МАДРЕЙМОВИЧ (РНН: 430120291295) | G59: 214 | H59: ИНИС | I59: 214 | J59: 45650 | L59: 45883 | O59: тематическая | R59: 44470 | S59: 45291 | T59: Тилеков Ж. | U59: 0 | W59: ОПТОВАЯ ТОРГОВЛЯ ШИРОКИМ АССОРТИМЕНТОМ ТОВАРОВ БЕЗ КАКОЙ-ЛИБО КОНКРЕТИЗАЦИИ | X59: КГД МФ РК | AF59: РБ | AG59: 105101 | AH59: =AI59+AJ59 -> 189727246 | AI59: 122387472 | AJ59: 67339774 | AK59: 0 | AL59: 0 | AM59: =AN59+AO59+AP59+AQ59+AR59 -> 46111524 | AN59: 46111524 | AO59: 0 | AP59: 0 | AQ59: 0 | AR59: 0 | AS59: #N/A | AT59: да | AU59: да | AW59: правильно | AX59: да | BD59: правильно | BF59: 0 | BG59: 0 | BH59: 0 | BI59: 46111524
A60: =CONCATENATE(C60,"-",E60,"-",G60) -> 39xx-10740002706-390120251209TAC0007 | B60: 46112 | C60: 39xx | D60: Костанайская | E60: 10740002706 | F60: ТОО "Светотехника - 1" | G60: 390120251209TAC0007 | H60: ИСНА | I60: 390120251211OAP0027 | J60: 46000 | K60: 46002 | L60: 46041 | M60: 46041 | N60: тематическая | O60: Тематическая проверка | R60: 44562 | S60: 45657 | T60: Оралова К.Д. | U60: ССП | W60: Оптовая торговля прочими машинами и оборудованиями | X60: КГД МФ РК | Y60: 1319 | Z60: 45999 | AD60: 17795089276 | AE60: 6.7 | AF60: МБ | AG60: 101111 | AH60: =AI60+AJ60 -> 37148112 | AI60: 30377473 | AJ60: 6770639 | AK60: 0 | AL60: 7594369 | AM60: =AN60+AO60+AP60+AQ60+AR60 -> 44742481 | AN60: 30377473 | AO60: 0 | AP60: 6770639 | AQ60: 0 | AR60: 7594369 | AS60: УНА | AT60: да | AU60: нет | AV60: 2026г. | AW60: правильно | AX60: да | AZ60: да | BB60: да | BD60: правильно
A61: =CONCATENATE(C61,"-",E61,"-",G61) -> 18xx-71040010874-64 | B61: 46064 | C61: 18xx | D61: ВКО | E61: 71040010874 | F61: ТОО "ДИМ Строй". | G61: 64 | H61: ИНИС | I61: 64 | J61: 45791 | K61: 45797 | L61: 46017 | M61: 46017 | O61: тематическая | R61: 43831 | S61: 45657 | T61: Касенжарова Ж.А. | U61: СКП | W61: Прочие строительно-монтажные работы | X61: Приказ КГД МФ РК | Y61: 284 | Z61: 45789 | AD61: 74369077256 | AE61: 8.7 | AF61: РБ | AG61: 101110 | AH61: =AI61+AJ61 -> 43682283 | AI61: 42242968 | AJ61: 1439315 | AK61: 0 | AL61: 0 | AM61: =AN61+AO61+AP61+AQ61+AR61 -> 43682283 | AN61: 0 | AO61: 42242968 | AP61: 0 | AQ61: 1439315 | AR61: 0 | AS61: #N/A | AT61: да | AU61: нет | AV61: правильно | AW61: правильно | AY61: да | BA61: да | BD61: правильно | BF61: 18361903 | BG61: 0 | BH61: 0
A62: =CONCATENATE(C62,"-",E62,"-",G62) -> 45xx-970740002243-13 | B62: 46112 | C62: 45xx | D62: Павлодарская | E62: 970740002243 | F62: ТОО "Вершина" | G62: 13 | H62: ИНИС | I62: 13 | J62: 44249 | K62: 44280 | L62: 44456 | M62: 44456 | O62: комплексная | R62: 43101 | S62: 44196 | T62: Садвакасова Г.С. | U62: среднего | X62: Периодическая налоговая проверка на основе оценки степени риска | AD62: 8013850552 | AF62: РБ | AG62: 105101 | AH62: =AI62+AJ62 -> 2.6294343e+08 | AI62: 218767062 | AJ62: 44176372 | AK62: 0 | AL62: 0 | AM62: =AN62+AO62+AP62+AQ62+AR62 -> 42596661 | AN62: 30903867 | AO62: 0 | AP62: 11692794 | AQ62: 0 | AR62: 0 | AS62: #N/A | AT62: нет | AU62: нет | AV62: убрать полностью | AW62: правильно | AX62: да | AZ62: да | BD62: правильно | BF62: 170386644 | BG62: 0 | BH62: #N/A
A63: =CONCATENATE(C63,"-",E63,"-",G63) -> 62xx-141040008957-398 | B63: 46071 | C63: 62xx | D63: г.Астана | E63: 141040008957 | F63: ТОО "КТЦ Казахстан" | G63: 398 | H63: ИНИС | I63: 398 | J63: 44797 | K63: 44813 | L63: 45190 | N63: комплексная | O63: #N/A | R63: 43466 | S63: 44561 | T63: Омарова Ж.Е. | X63: По особому порядку | AF63: РБ | AG63: 105104 | AH63: =AI63+AJ63 -> 42553658 | AI63: 29728320 | AJ63: 12825338 | AK63: 0 | AL63: 0 | AM63: =AN63+AO63+AP63+AQ63+AR63 -> 42553658 | AN63: 29728320 | AO63: 0 | AP63: 12825338 | AQ63: 0 | AR63: 0 | AS63: #N/A | AT63: да | AU63: 0 | AW63: правильно | AX63: да | AZ63: да | BD63: правильно | BF63: 0 | BG63: 0 | BH63: #N/A
A64: =CONCATENATE(C64,"-",E64,"-",G64) -> 09xx-200140009286-228 | B64: 46099 | C64: 09xx | D64: Алматинская | E64: 200140009286 | F64: ТОО "A-Class Medical" ("А-Класс Медикал") | G64: 228 | H64: ИНИС | I64: 228 | J64: 45652 | K64: 45657 | L64: 45777 | M64: 45779 | O64: тематическая | R64: 44562 | S64: 45291 | T64: Исмаилов М.Т. | U64: ССП | V64: - | W64: Общая врачебная практика | X64: КГД МФ РК | Y64: 418 | Z64: 45652 | AA64: - | AB64: - | AC64: - | AD64: 3281973380 | AE64: 1 | AF64: МБ | AG64: 101111 | AH64: =AI64+AJ64 -> 53991942 | AI64: 45135001 | AJ64: 8856941 | AK64: 0 | AL64: 11283750 | AM64: =AN64+AO64+AP64+AQ64+AR64 -> 41848911 | AN64: 24154245 | AO64: 0 | AP64: 17694666 | AQ64: 0 | AR64: 0 | AS64: #N/A | AT64: нет | AU64: нет | AV64: убрать полностью | AW64: правильно | AX64: да | AZ64: да | BD64: правильно | BF64: 53996068 | BG64: 0 | BH64: 0
A65: =CONCATENATE(C65,"-",E65,"-",G65) -> 62xx-50841007822-620120250709TAC0001 | B65: 46027 | C65: 62xx | D65: г.Астана | E65: 50841007822 | F65: Филиал Компании «DONGIL CONSTRUCTION CO. LTD» в городе Астана | G65: 620120250709TAC0001 | H65: ИСНА | I65: 620120250826OAP0001 | J65: 45847 | K65: 45895 | L65: 46017 | N65: тематическая | O65: Тематическая проверка | R65: 44562 | S65: 31.12.2024 | T65: Жайлауов Дулат Байжанұлы | U65: СМП | W65: СТРОИТЕЛЬСТВО | X65: КГД МФ РК | Y65: 584 | Z65: 45842 | AD65: 11597720491 | AF65: МБ | AG65: 101111 | AH65: =AI65+AJ65 -> 38242861 | AI65: 32957356 | AJ65: 5285505 | AK65: 0 | AL65: 0 | AM65: =AN65+AO65+AP65+AQ65+AR65 -> 41538596 | AN65: 32957356 | AO65: 0 | AP65: 5285505 | AQ65: 0 | AR65: 3295735 | AS65: #N/A | AT65: да | AU65: нет | AW65: правильно | AX65: да | AZ65: да | BB65: да | BD65: правильно | BF65: 0
A66: =CONCATENATE(C66,"-",E66,"-",G66) -> 33xx-50740006290-330120250725TAC0001 | B66: 46064 | C66: 33xx | D66: Кызылординская | E66: 50740006290 | F66: ТОО "Кумколь Транс Сервис" | G66: 330120250725TAC0001 | H66: ИСНА | I66: 330120250729OAP0004 | J66: 45863 | K66: 45867 | L66: 46013 | M66: 46013 | N66: тематическая | O66: Тематическая проверка | R66: 43831 | S66: 45657 | T66: Оралбаев А. Коспанбетов А. | U66: СКП | X66: Приказ КГД МФ РК | Y66: 643 | Z66: 45860 | AF66: РБ | AG66: 101110 | AH66: =AI66+AJ66 -> 40996088 | AI66: 40996088 | AJ66: 0 | AK66: 0 | AL66: 0 | AM66: =AN66+AO66+AP66+AQ66+AR66 -> 40996088 | AN66: 30720850 | AO66: 0 | AP66: 10275238 | AQ66: 0 | AR66: 0 | AS66: #N/A | AT66: нет | AU66: нет | AV66: правильно | AW66: правильно | AX66: да | AZ66: да | BD66: правильно | BE66: мониторинг | BI66: -
A67: =CONCATENATE(C67,"-",E67,"-",G67) -> 06xx-941240001954-114 | B67: 46057 | C67: 06xx | D67: Актюбинская | E67: 941240001954 | F67: ПК "Нектар" | G67: 114 | H67: ИНИС | I67: 114 | J67: 45800 | K67: 45819 | L67: 46021 | M67: 46021 | O67: тематическая | R67: 44562 | S67: 45291 | T67: Жанасова Б. | U67: ССП | V67: - | W67: Строительство | X67: КГД МФ РК | Y67: 324 | Z67: 45797 | AA67: - | AB67: - | AC67: - | AD67: 8780334856 | AE67: 3.815 | AF67: МБ | AG67: 101111 | AH67: =AI67+AJ67 -> 38869152 | AI67: 38869152 | AJ67: 0 | AK67: 0 | AL67: 0 | AM67: =AN67+AO67+AP67+AQ67+AR67 -> 38869152 | AN67: 0 | AO67: 38869152 | AP67: 0 | AQ67: 0 | AR67: 0 | AS67: #N/A | AT67: да | AU67: нет | AW67: правильно | AY67: да | BD67: правильно | BF67: 0 | BG67: 0 | BH67: 0
A68: =CONCATENATE(C68,"-",E68,"-",G68) -> 59xx-70340006408-181 | B68: 45967 | C68: 59xx | D68: г.Шымкент | E68: 70340006408 | F68: ТОО "Корпорация "Сити-Строй" | G68: 181 | H68: ИНИС | I68: 181 | J68: 43445 | K68: 43461 | L68: 44106 | M68: 44106 | O68: комплексная | R68: 43466 | S68: 43830 | T68: Зияев Я.Р. | U68: ССП | X68: Особый порядок | AF68: РБ | AG68: 105101 | AH68: =AI68+AJ68 -> 51733314 | AI68: 42521510 | AJ68: 9211804 | AK68: 0 | AL68: 0 | AM68: =AN68+AO68+AP68+AQ68+AR68 -> 38110749 | AN68: 38110749 | AO68: 0 | AP68: 0 | AQ68: 0 | AR68: 0 | AS68: #N/A | AT68: нет | AU68: нет | AV68: убрать полностью | AW68: правильно | AX68: да | BD68: правильно | BF68: 0 | BG68: #N/A | BH68: #N/A
A69: =CONCATENATE(C69,"-",E69,"-",G69) -> 60xx-50940003194-600 | B69: 46030 | C69: 60xx | D69: г.Алматы | E69: 50940003194 | F69: ТОО "ТУР-ХАН" | G69: 600 | H69: ИНИС | I69: 600 | J69: 45799 | K69: 45799 | L69: 46021 | M69: 46022 | O69: тематическая | R69: 44562 | S69: 45291 | T69: Ажимуратова Ж.Д. | U69: Среднее предпринимательство | W69: N43298 | X69: КГД МФ РК | AF69: МБ | AG69: 101111 | AH69: =AI69+AJ69 -> 31920003 | AI69: 24725754 | AJ69: 7194249 | AK69: 0 | AL69: 0 | AM69: =AN69+AO69+AP69+AQ69+AR69 -> 38101442 | AN69: 24725754 | AO69: 0 | AP69: 7194249 | AQ69: 0 | AR69: 6181439 | AS69: #N/A | AT69: да | AU69: нет | AW69: правильно | AX69: да | AZ69: да | BB69: да | BD69: правильно | BF69: 0 | BG69: 0 | BH69: 0
A70: =CONCATENATE(C70,"-",E70,"-",G70) -> 18xx-50440005717-154 | B70: 46112 | C70: 18xx | D70: ВКО | E70: 50440005717 | F70: ТОО "BUILDER GOLD" | G70: 154 | H70: ИНИС | I70: 154 | J70: 43998 | K70: 44004 | L70: 44095 | M70: 44095 | O70: тематическая | R70: 43101 | S70: 43830 | T70: Абугалий Ж | U70: ССП | W70: Строительство | X70: в рамках ВУД | AD70: 1539533117 | AE70: 1.97 | AF70: МБ | AG70: 101111 | AH70: =AI70+AJ70 -> 190119893 | AI70: 158342922 | AJ70: 31776971 | AK70: 0 | AL70: 0 | AM70: =AN70+AO70+AP70+AQ70+AR70 -> 37500000 | AN70: 37500000 | AO70: 0 | AP70: 0 | AQ70: 0 | AR70: 0 | AS70: #N/A | AT70: да | AU70: нет | AV70: норм | AW70: правильно | AX70: да | BD70: правильно | BF70: 18000000 | BG70: #N/A | BH70: #N/A
A71: =CONCATENATE(C71,"-",E71,"-",G71) -> 18xx-50440005717-154 | B71: 46112 | C71: 18xx | D71: ВКО | E71: 50440005717 | F71: ТОО "BUILDER GOLD" | G71: 154 | H71: ИНИС | I71: 154 | J71: 43998 | K71: 44004 | L71: 44095 | M71: 44095 | O71: тематическая | R71: 43101 | S71: 43830 | T71: Абугалий Ж | U71: ССП | W71: Строительство | X71: в рамках ВУД | AD71: 1539533117 | AE71: 1.97 | AF71: РБ | AG71: 105101 | AH71: =AI71+AJ71 -> 103342910 | AI71: 80010963 | AJ71: 23331947 | AK71: 0 | AL71: 0 | AM71: =AN71+AO71+AP71+AQ71+AR71 -> 37500000 | AN71: 37500000 | AO71: 0 | AP71: 0 | AQ71: 0 | AR71: 0 | AS71: #N/A | AT71: да | AU71: да | AV71: норм | AW71: правильно | AX71: да | BD71: правильно | BF71: 17500000 | BG71: #N/A | BH71: #N/A | BI71: 25000000
A72: =CONCATENATE(C72,"-",E72,"-",G72) -> 60xx-71240002008-600120250717TAC0004 | B72: 46108 | C72: 60xx | D72: г.Алматы | E72: 71240002008 | F72: АО "Кристалл Менеджмент" | G72: 600120250717TAC0004 | H72: ИСНА | I72: 600120250731OAP0027 | J72: 45855 | K72: 45869 | L72: 46108 | N72: тематическая | O72: Тематическая проверка | R72: 43831 | S72: 45657 | T72: Естаев Нуртай Куанышбекұлы | V72: недропользователь | X72: КГД МФ РК | AF72: РБ | AG72: 101110 | AH72: =AI72+AJ72 -> 30591059 | AI72: 25539926 | AJ72: 5051133 | AK72: 0 | AL72: 6384981.5 | AM72: =AN72+AO72+AP72+AQ72+AR72 -> 36976040 | AN72: 25539926 | AO72: 0 | AP72: 5051133 | AQ72: 0 | AR72: 6384981.5 | AS72: УНА | AT72: да | AU72: да | AV72: 2026г. | AW72: правильно | AX72: да | AZ72: да | BB72: да | BD72: правильно | BI72: 36976040
A73: =CONCATENATE(C73,"-",E73,"-",G73) -> 09xx-110240016194-191 | B73: 46099 | C73: 09xx | D73: Алматинская | E73: 110240016194 | F73: ТОО "BeyAzh Trans" | G73: 191 | H73: ИНИС | I73: 191 | J73: 45607 | K73: 45617 | L73: 45744 | M73: 45754 | O73: тематическая | R73: 43831 | S73: 45291 | T73: Исмаилов М.Т. | U73: СКП | V73: - | W73: Сбор, обработка и распределение воды | X73: КГД МФ РК | Y73: 461 | Z73: 45607 | AA73: - | AB73: - | AC73: - | AD73: 3109011752 | AE73: 2 | AF73: РБ | AG73: 105101 | AH73: =AI73+AJ73 -> 404568524 | AI73: 278414446 | AJ73: 126154078 | AK73: 0 | AL73: 0 | AM73: =AN73+AO73+AP73+AQ73+AR73 -> 36257121 | AN73: 20217351 | AO73: 0 | AP73: 16039770 | AQ73: 0 | AR73: 0 | AS73: #N/A | AT73: да | AU73: да | AV73: норм | AW73: правильно | AX73: да | AZ73: да | BD73: правильно | BF73: 104936181 | BG73: 0 | BH73: 0 | BI73: 14432297
A74: =CONCATENATE(C74,"-",E74,"-",G74) -> 62xx-141040008957-398 | B74: 46113 | C74: 62xx | D74: г.Астана | E74: 141040008957 | F74: ТОО "КТЦ Казахстан" | G74: 398 | H74: ИНИС | I74: 398 | J74: 44797 | K74: 44813 | L74: 45190 | N74: комплексная | O74: #N/A | R74: 43466 | S74: 44561 | T74: Омарова Ж.Е. | X74: По особому порядку | AF74: МБ | AG74: 101111 | AH74: =AI74+AJ74 -> 36037949 | AI74: 0 | AJ74: 36037949 | AK74: 0 | AL74: 0 | AM74: =AN74+AO74+AP74+AQ74+AR74 -> 36037949 | AN74: 0 | AO74: 0 | AP74: 36037949 | AQ74: 0 | AR74: 0 | AS74: #N/A | AT74: да | AU74: нет | AW74: правильно | AZ74: да | BD74: правильно | BF74: 0 | BG74: 0 | BH74: #N/A
A75: =CONCATENATE(C75,"-",E75,"-",G75) -> 60xx-50940003194-600 | B75: 46030 | C75: 60xx | D75: г.Алматы | E75: 50940003194 | F75: ТОО "ТУР-ХАН" | G75: 600 | H75: ИНИС | I75: 600 | J75: 45799 | K75: 45799 | L75: 46021 | O75: тематическая | R75: 44562 | S75: 45291 | T75: Ажимуратова Ж.Д. | U75: Среднее предпринимательство | W75: N43298 | X75: КГД МФ РК | AF75: РБ | AG75: 105101 | AH75: =AI75+AJ75 -> 34413100 | AI75: 28177675 | AJ75: 6235425 | AK75: 0 | AL75: 0 | AM75: =AN75+AO75+AP75+AQ75+AR75 -> 35222094 | AN75: 28177675 | AO75: 0 | AP75: 0 | AQ75: 0 | AR75: 7044419 | AS75: #N/A | AT75: да | AU75: 0 | AW75: правильно | AX75: да | BB75: да | BD75: правильно | BF75: 0 | BG75: 0 | BH75: 0
A76: =CONCATENATE(C76,"-",E76,"-",G76) -> 72xx-150540022385-720120251008TAC0018 | B76: 46112 | C76: 72xx | D76: Ұлытау | E76: 150540022385 | F76: ТОО "Амарант KZ" | G76: 720120251008TAC0018 | H76: ИСНА | I76: 720120251008TAC0018 | J76: 45938 | K76: 45967 | L76: 46021 | M76: 46021 | N76: тематическая | O76: Тематическая проверка | R76: 44562 | S76: 45657 | T76: Шайхыспарова Б.А. | U76: СМП | W76: строительство газопровода | X76: Приказ КГД МФ РК/ | Y76: 940 | Z76: 45892 | AF76: МБ | AG76: 101111 | AH76: =AI76+AJ76 -> 31825394 | AI76: 26586343 | AJ76: 5239051 | AK76: 0 | AL76: 2658634 | AM76: =AN76+AO76+AP76+AQ76+AR76 -> 34532996 | AN76: 25855040 | AO76: 532277.6 | AP76: 5487044 | AQ76: 0 | AR76: 2658634 | AS76: #N/A | AT76: да | AU76: нет | AW76: норм | AX76: да | AY76: да | AZ76: да | BB76: да | BD76: правильно | BF76: 0
A77: =CONCATENATE(C77,"-",E77,"-",G77) -> 62xx-140440007316-620120250808TAC0047 | B77: 46092 | C77: 62xx | D77: г.Астана | E77: 140440007316 | F77: ТОО "Каз Бетон Компани" | G77: 620120250808TAC0047 | H77: ИСНА | I77: 620120251008OAP0042 | J77: 45877 | K77: 45938 | L77: 46021 | N77: тематическая | O77: Тематическая проверка | R77: 44562 | S77: 31.12.2024 | T77: Муратов Мейрбек Жанатович | U77: СМП | W77: ОБРАБАТЫВАЮЩАЯ ПРОМЫШЛЕННОСТЬ | X77: КГД МФ РК | Y77: 733 | Z77: 45873 | AD77: 34912535803 | AF77: РБ | AG77: 101110 | AH77: =AI77+AJ77 -> 34270453 | AI77: 28987448 | AJ77: 5283005 | AK77: 0 | AL77: 0 | AM77: =AN77+AO77+AP77+AQ77+AR77 -> 34270453 | AN77: 28987448 | AO77: 0 | AP77: 5283005 | AQ77: 0 | AR77: 0 | AS77: #N/A | AT77: да | AU77: да | AV77: правильно | AW77: правильно | AX77: да | AZ77: да | BD77: правильно | BI77: 34270453
A78: =CONCATENATE(C78,"-",E78,"-",G78) -> 60xx-40340009487-600120250728TAC0037 | B78: 46078 | C78: 60xx | D78: г.Алматы | E78: 40340009487 | F78: ТОО "Elif Construction" | G78: 600120250728TAC0037 | H78: ИСНА | I78: 600120250812OAP0007 | J78: 45881 | K78: 45881 | L78: 46056 | M78: 46056 | N78: тематическая | O78: Тематическая проверка | R78: 44562 | S78: 45657 | T78: Есимханов Ержан Алтаевич | U78: СМП | W78: Строительство жилых зданий | X78: приказ КГД МФ РК | Y78: 653 | Z78: 45861 | AD78: 4812193048 | AE78: 2.23 | AF78: МБ | AG78: 101111 | AH78: =AI78+AJ78 -> 30747985 | AI78: 26381918 | AJ78: 4366067 | AK78: 0 | AL78: 2638192 | AM78: =AN78+AO78+AP78+AQ78+AR78 -> 33386177 | AN78: 26381918 | AO78: 0 | AP78: 4366067 | AQ78: 0 | AR78: 2638192 | AS78: УНА | AT78: да | AU78: нет | AV78: 2026г. | AW78: правильно | AX78: да | AZ78: да | BB78: да | BD78: правильно
A79: =CONCATENATE(C79,"-",E79,"-",G79) -> 62xx-181140004360-436 | B79: 46027 | C79: 62xx | D79: г.Астана | E79: 181140004360 | F79: ТОО"Sezim Arena" | G79: 436 | H79: ИНИС | I79: 436 | J79: 45777 | K79: 45818 | L79: 46020 | O79: тематическая | R79: 44562 | S79: 31.12.2022 | T79: Турымканова Л.Ж. | U79: СМП | W79: Строительство | X79: КГД МФ РК | Y79: 191 | Z79: 45761 | AD79: 20089142424 | AF79: МБ | AG79: 101111 | AH79: =AI79+AJ79 -> 30968303 | AI79: 20179071 | AJ79: 10789232 | AK79: 0 | AL79: 0 | AM79: =AN79+AO79+AP79+AQ79+AR79 -> 32986210 | AN79: 20179071 | AO79: 0 | AP79: 10789232 | AQ79: 0 | AR79: 2017907 | AS79: #N/A | AT79: да | AU79: нет | AV79: штраф | AW79: правильно | AX79: да | AZ79: да | BD79: правильно | BF79: 0 | BG79: 0 | BH79: 0
A80: =CONCATENATE(C80,"-",E80,"-",G80) -> 27xx-971240023128-102 | B80: 46112 | C80: 27xx | D80: ЗКО | E80: 971240023128 | F80: ТОО "Восход" | G80: 102 | H80: ИНИС | I80: 102 | J80: 44050 | K80: 44060 | L80: 44169 | M80: 44169 | O80: тематическая | R80: 42736 | S80: 44013 | T80: Берниязова М.Р. | U80: 1. СМП | W80: Прочие строительные работы, требующие специальных профессий | X80: В рамках ВУД | AD80: 1308253517 | AE80: 3.3356 | AF80: РБ | AG80: 105101 | AH80: =AI80+AJ80 -> 63621162 | AI80: 56707167 | AJ80: 6913995 | AK80: 0 | AL80: 0 | AM80: =AN80+AO80+AP80+AQ80+AR80 -> 32875467 | AN80: 32635467 | AO80: 240000 | AP80: 0 | AQ80: 0 | AR80: 0 | AS80: #N/A | AT80: да | AU80: да | AV80: норм | AW80: правильно | AX80: да | AY80: да | BD80: правильно | BF80: 20198000 | BG80: #N/A | BH80: #N/A | BI80: 26635467
A81: =CONCATENATE(C81,"-",E81,"-",G81) -> 58xx-11040005321-580120251205TAC0001 | B81: 46071 | C81: 58xx | D81: Туркестанская | E81: 11040005321 | F81: ТОО "Нүрі-Л-Жетісай" | G81: 580120251205TAC0001 | H81: ИСНА | I81: 580120251205TAC0001 | J81: 45996 | K81: 46014 | L81: 46059 | M81: 46059 | N81: тематическая | O81: Тематическая проверка | R81: 44562 | S81: 45657 | T81: Утебаев Сеил Абдыхалыкулы | U81: ССП | W81: Строительство нежилых зданий | X81: КГД МФ РК | Y81: 1246 | Z81: 45989 | AD81: 5795150401 | AE81: 5.9 | AF81: МБ | AG81: 101111 | AH81: =AI81+AJ81 -> 30512605 | AI81: 25792413 | AJ81: 4720191.8 | AK81: 0 | AL81: 6448103 | AM81: =AN81+AO81+AP81+AQ81+AR81 -> 32240516 | AN81: 0 | AO81: 25792413 | AP81: 0 | AQ81: 0 | AR81: 6448103 | AS81: УНА | AT81: да | AU81: нет | AV81: 2026г. | AW81: правильно | AY81: да | BB81: да | BD81: правильно
A82: =CONCATENATE(C82,"-",E82,"-",G82) -> 33xx-40241006672-330120250807TAC0001 | B82: 46064 | C82: 33xx | D82: Кызылординская | E82: 40241006672 | F82: Филиал "ПетроКазахстан Венчерс Инк." | G82: 330120250807TAC0001 | H82: ИСНА | I82: 330120250808OAP0001 | J82: 45876 | K82: 45877 | L82: 46009 | M82: 46009 | N82: тематическая | O82: Тематическая проверка | R82: 43831 | S82: 45657 | T82: Жаппасбай Б. | U82: СКП | X82: Приказ КГД МФ РК | Y82: 759 | Z82: 45874 | AF82: РБ | AG82: 105101 | AH82: =AI82+AJ82 -> 86595764 | AI82: 86595764 | AJ82: 0 | AK82: 0 | AL82: 0 | AM82: =AN82+AO82+AP82+AQ82+AR82 -> 30000000 | AN82: 30000000 | AO82: 0 | AP82: 0 | AQ82: 0 | AR82: 0 | AS82: #N/A | AT82: нет | AU82: нет | AV82: правильно | AW82: правильно | AX82: да | BD82: правильно | BE82: СД | BI82: 30000000
A83: =CONCATENATE(C83,"-",E83,"-",G83) -> 48xx-40640004576-315 | B83: 46092 | C83: 48xx | D83: СКО | E83: 40640004576 | F83: ТОО "Агрофирма Эксимнан" | G83: 315 | H83: ИНИС | I83: 315 | J83: 45628 | K83: 45632 | L83: 45817 | M83: 45818 | O83: комплексная | R83: 44562 | S83: 45291 | T83: Тлеубердина А.С. | U83: Субъекты крупного предпринимательства | V83: нет | W83: Выращивание зерновых и зернобобовых культур, включая семеноводство | X83: КГД МФ РК | Y83: 324 | Z83: 45436 | AD83: 4834268665 | AE83: 4.2 | AF83: РБ | AG83: 101110 | AH83: =AI83+AJ83 -> 70880385 | AI83: 58222878 | AJ83: 12657507 | AK83: 0 | AL83: 46578302 | AM83: =AN83+AO83+AP83+AQ83+AR83 -> 30000000 | AN83: 30000000 | AO83: 0 | AP83: 0 | AQ83: 0 | AR83: 0 | AS83: #N/A | AT83: да | AU83: да | AV83: правильно | AW83: правильно | AX83: да | BD83: правильно | BI83: 30000000
A84: =CONCATENATE(C84,"-",E84,"-",G84) -> 09xx-60240002985-090120250925TAC0026 | B84: 46076 | C84: 09xx | D84: Алматинская | E84: 60240002985 | F84: ТОО "Гунн Строй сервис" | G84: 090120250925TAC0026 | H84: ИСНА | I84: 090120250925TAC0026 | J84: 45925 | K84: 45959 | L84: 46022 | M84: 46022 | N84: тематическая | O84: Тематическая проверка | R84: 01.01.2022 | S84: 31.12.2024 | T84: Алдарбергенов Алмат Талгатович | U84: ССП | W84: Прочие строительно-монтажные работы | X84: КГД МФ РК | Y84: 956 | Z84: 45925 | AD84: 7128818536 | AE84: 15 | AF84: МБ | AG84: 101111 | AH84: =AI84+AJ84 -> 22750882 | AI84: 18977603 | AJ84: 3773279 | AK84: 0 | AL84: 4744401 | AM84: =AN84+AO84+AP84+AQ84+AR84 -> 28032117 | AN84: 18977603 | AO84: 0 | AP84: 4310113 | AQ84: 0 | AR84: 4744401 | AS84: #N/A | AT84: да | AU84: нет | AW84: норм | AX84: да | AZ84: да | BB84: да | BD84: правильно | BF84: 0
A85: =CONCATENATE(C85,"-",E85,"-",G85) -> 62xx-70240003350-1143 | B85: 46113 | C85: 62xx | D85: г.Астана | E85: 70240003350 | F85: ТОО "StroyТех-2030" | G85: 1143 | H85: ИНИС | I85: 1143 | L85: 45526 | N85: комплексная | O85: Тематическая | T85: Буркутбаева М.М. | AF85: РБ | AG85: 105101 | AH85: =AI85+AJ85 -> 39493567 | AI85: 39493567 | AJ85: 0 | AK85: 0 | AL85: 0 | AM85: =AN85+AO85+AP85+AQ85+AR85 -> 26949647 | AN85: 0 | AO85: 26949647 | AP85: 0 | AQ85: 0 | AR85: 0 | AS85: #N/A | AT85: да | AU85: нет | AW85: правильно | AY85: да | BD85: правильно | BF85: 0 | BG85: 0 | BH85: #N/A
A86: =CONCATENATE(C86,"-",E86,"-",G86) -> 27xx-21040000015-21 | B86: 46108 | C86: 27xx | D86: ЗКО | E86: 21040000015 | F86: ТОО "БАТАЛАСУ" | G86: 21 | H86: ИНИС | I86: 21 | J86: 45735 | K86: 45755 | L86: 45859 | M86: 45860 | O86: комплексная | R86: 44197 | S86: 45657 | T86: Галиуллин Ж.Е. | U86: 1. СМП | W86: Производство строительных стальных конструкций | X86: Особый порядок | Y86: 873 | Z86: 45650 | AD86: 2795380810 | AE86: 1.8 | AF86: РБ | AG86: 105101 | AH86: =AI86+AJ86 -> 28553668 | AI86: 19660779 | AJ86: 8892889 | AK86: 365041498 | AL86: 0 | AM86: =AN86+AO86+AP86+AQ86+AR86 -> 26892889 | AN86: 18000000 | AO86: 0 | AP86: =8892889 -> 8892889 | AQ86: 0 | AR86: 0 | AS86: #N/A | AT86: да | AU86: да | AV86: норм | AW86: правильно | AX86: да | AZ86: да | BD86: правильно | BF86: 2476957 | BG86: 0 | BH86: 0 | BI86: 26892889
A87: =CONCATENATE(C87,"-",E87,"-",G87) -> 33xx-991140005209-160 | B87: 46112 | C87: 33xx | D87: Кызылординская | E87: 991140005209 | F87: ТОО "Ансар-сервис" | G87: 160 | H87: ИНИС | I87: 160 | J87: 43370 | K87: 43371 | L87: 43591 | M87: 43591 | O87: тематическая | R87: 41275 | S87: 43100 | T87: Сыдыкова Ш. | U87: СМП | X87: Приказ КГД МФ РК | AF87: МБ | AG87: 101111 | AH87: =AI87+AJ87 -> 44111519 | AI87: 39906131 | AJ87: 4205387.5 | AK87: 0 | AL87: 0 | AM87: =AN87+AO87+AP87+AQ87+AR87 -> 26365124 | AN87: 26365124 | AO87: 0 | AP87: 0 | AQ87: 0 | AR87: 0 | AS87: #N/A | AT87: да | AU87: нет | AV87: норм | AW87: правильно | AX87: да | BD87: правильно | BF87: 0 | BG87: #N/A | BH87: 0
A88: =CONCATENATE(C88,"-",E88,"-",G88) -> 06xx-50140011681-57 | B88: 46099 | C88: 06xx | D88: Актюбинская | E88: 50140011681 | F88: ТОО Казпромстройгрупп | G88: 57 | H88: ИНИС | I88: 57 | J88: 43185 | K88: 43194 | L88: 43488 | M88: 43488 | O88: комплексная | R88: 41275 | S88: 43100 | T88: Сарина Ш. | U88: ССП | V88: - | W88: Прочие строительно-монтажные работы | X88: Список проверок, проводимых по особому порядку | Y88: - | AE88: 6.91 | AF88: МБ | AG88: 101111 | AH88: =AI88+AJ88 -> 750598813 | AI88: 508317532 | AJ88: 242281281 | AK88: 0 | AL88: 0 | AM88: =AN88+AO88+AP88+AQ88+AR88 -> 26206000 | AN88: 26206000 | AO88: 0 | AP88: 0 | AQ88: 0 | AR88: 0 | AS88: #N/A | AT88: да | AU88: нет | AV88: норм | AW88: правильно | AX88: да | BD88: правильно | BF88: 16074317 | BG88: 0 | BH88: #N/A
A89: =CONCATENATE(C89,"-",E89,"-",G89) -> 27xx-990840000052-270120250731TAC0008 | B89: 46055 | C89: 27xx | D89: ЗКО | E89: 990840000052 | F89: ТОО "СКФ "Жаиксельстрой" | G89: 270120250731TAC0008 | H89: ИСНА | I89: 270120250811ОАР0010 | J89: 45869 | K89: 45880 | L89: 46017 | M89: 46017 | N89: тематическая | O89: Тематическая проверка | R89: 44197 | S89: 45291 | T89: Мураткалиева С.Т. | U89: 2. ССП | W89: Строительство жилых зданий | X89: Приказ КГД МФ РК | Y89: 690 | Z89: 45867 | AD89: 5821223275 | AE89: 7.5 | AF89: МБ | AG89: 101111 | AH89: =AI89+AJ89 -> 26127961 | AI89: 19934846 | AJ89: 6193115 | AK89: 0 | AL89: 0 | AM89: =AN89+AO89+AP89+AQ89+AR89 -> 26127961 | AN89: 19934846 | AO89: 0 | AP89: 6193115 | AQ89: 0 | AR89: 0 | AS89: #N/A | AT89: да | AU89: нет | AW89: правильно | AX89: да | AZ89: да | BD89: правильно | BF89: 0
A90: =CONCATENATE(C90,"-",E90,"-",G90) -> 60xx-50840014087-600120250805TAC0112 | B90: 46085 | C90: 60xx | D90: г.Алматы | E90: 50840014087 | F90: ТОО "Компания "Ремпуть" | G90: 600120250805TAC0112 | H90: ИСНА | I90: 600120250814OAP0001 | J90: 45874 | K90: 45883 | L90: 46021 | M90: 46022 | N90: тематическая | O90: Тематическая проверка | R90: 44562 | S90: 45657 | T90: Валиев Жандос Джамбулович | U90: ССП | W90: СМП | X90: КГД МФ РК | Y90: №720 | Z90: 45873 | AD90: 12719717336 | AE90: 4 | AF90: МБ | AG90: 101111 | AH90: =AI90+AJ90 -> 21274252 | AI90: 18184188 | AJ90: 3090064 | AK90: 2857224 | AL90: 4546047 | AM90: =AN90+AO90+AP90+AQ90+AR90 -> 25820299 | AN90: 18184188 | AO90: 0 | AP90: 3090064 | AQ90: 0 | AR90: 4546047 | AS90: #N/A | AT90: нет | AU90: нет | AV90: убрать полностью | AW90: правильно | AX90: да | AZ90: да | BB90: да | BD90: правильно | BF90: 21274253
A91: =CONCATENATE(C91,"-",E91,"-",G91) -> 60xx-21240006160-1931 | B91: 46030 | C91: 60xx | D91: г.Алматы | E91: 21240006160 | F91: ТОО "АТРИКС-СТРОЙ" | G91: 1931 | H91: ИНИС | I91: 1931 | J91: 45614 | K91: 45614 | L91: 46022 | M91: 46022 | O91: тематическая | R91: 44197 | S91: 45291 | T91: Кулбаев А.Б. | U91: Среднее предпринимательство | W91: N43298 | X91: КГД МФ РК | AF91: МБ | AG91: 101111 | AH91: =AI91+AJ91 -> 142835014 | AI91: 102773515 | AJ91: 40061499 | AK91: 0 | AL91: 0 | AM91: =AN91+AO91+AP91+AQ91+AR91 -> 25693379 | AN91: 0 | AO91: 0 | AP91: 0 | AQ91: 0 | AR91: 25693379 | AS91: #N/A | AT91: да | AU91: нет | AV91: штраф | AW91: правильно | BB91: да | BD91: правильно
A92: =CONCATENATE(C92,"-",E92,"-",G92) -> 60xx-61040000012-600120251113TAC0081 | B92: 46045 | C92: 60xx | D92: г.Алматы | E92: 61040000012 | F92: ТОО "Медико-Инновационные Технологии" | G92: 600120251113TAC0081 | H92: ИСНА | I92: 600120251117OAP0018 | J92: 45974 | K92: 45978 | L92: 46037 | N92: Тематическая | O92: Тематическая проверка | R92: 43831 | S92: 44926 | T92: Жапарова Гульжан Ораловна | U92: Среднее предпринимательство | X92: КГД МФ РК | AF92: РБ | AG92: 101110 | AH92: =AI92+AJ92 -> 8.0176615e+08 | AI92: 397376894 | AJ92: 4.0438925e+08 | AK92: 0 | AL92: 0 | AM92: =AN92+AO92+AP92+AQ92+AR92 -> 25500000 | AN92: 20000000 | AO92: 0 | AP92: 5500000 | AQ92: 0 | AR92: 0 | AS92: УНА | AT92: да | AU92: 0 | AV92: 2026г. | AW92: правильно | AX92: да | AZ92: да | BD92: правильно
A93: =CONCATENATE(C93,"-",E93,"-",G93) -> 06xx-931240000101-82 | B93: 46112 | C93: 06xx | D93: Актюбинская | E93: 931240000101 | F93: АО "Авиаремонтный завод №406 гражданской авиации" | G93: 82 | H93: ИНИС | I93: 82 | J93: 44302 | K93: 44308 | L93: 44469 | M93: 44469 | O93: тематическая | R93: 43101 | S93: 44196 | T93: Жумашева | U93: ССП | V93: - | W93: Производство воздушных летательных аппаратов | X93: КГД МФ РК | AE93: 10.03 | AF93: РБ | AG93: 105101 | AH93: =AI93+AJ93 -> 193530430 | AI93: 159159825 | AJ93: 34370605 | AK93: 0 | AL93: 0 | AM93: =AN93+AO93+AP93+AQ93+AR93 -> 25057233 | AN93: 23195608 | AO93: 0 | AP93: 1861625 | AQ93: 0 | AR93: 0 | AS93: #N/A | AT93: да | AU93: да | AV93: норм | AW93: правильно | AX93: да | AZ93: да | BD93: правильно | BF93: 105334342 | BG93: #N/A | BH93: 0 | BI93: 441965
A94: =CONCATENATE(C94,"-",E94,"-",G94) -> 21xx-40340001818-119 | B94: 46078 | C94: 21xx | D94: Жамбылская | E94: 40340001818 | F94: ТОО КА-СТРОЙ ЛТД | G94: 119 | H94: ИНИС | I94: 119 | J94: 45646 | K94: 45650 | L94: 45695 | M94: 45695 | O94: тематическая | R94: 43466 | S94: 43830 | T94: Сауранбаев Д. | U94: Субъекты крупного предпринимательства | V94: нет | W94: Строительно-монтажные работы | X94: КГД МФ РК | Y94: 578 | Z94: 45645 | AD94: 9963918901 | AE94: 3.29 | AF94: РБ | AG94: 105101 | AH94: =AI94+AJ94 -> 58403750 | AI94: 46120577 | AJ94: 12283173 | AK94: 0 | AL94: 13250271 | AM94: =AN94+AO94+AP94+AQ94+AR94 -> 24651187 | AN94: 0 | AO94: 0 | AP94: 11400916 | AQ94: 0 | AR94: 13250271 | AS94: #N/A | AT94: да | AU94: 0 | AV94: норм | AW94: правильно | AZ94: да | BB94: да | BD94: правильно | BF94: 46120577 | BG94: 0 | BH94: 0
A95: =CONCATENATE(C95,"-",E95,"-",G95) -> 59xx-70340006408-179 | B95: 45967 | C95: 59xx | D95: г.Шымкент | E95: 70340006408 | F95: ТОО "Корпорация "Сити-Строй" | G95: 179 | H95: ИНИС | I95: 179 | J95: 45153 | K95: 45170 | L95: 45391 | M95: 45391 | O95: Комплексная | R95: 43466 | S95: 43830 | T95: Зияев Я.Р. | U95: ССП | X95: Особый порядок | AF95: МБ | AG95: 101111 | AH95: =AI95+AJ95 -> 218116226 | AI95: 180049862 | AJ95: 38066364 | AK95: 0 | AL95: 0 | AM95: =AN95+AO95+AP95+AQ95+AR95 -> 24552256 | AN95: 24552256 | AO95: 0 | AP95: 0 | AQ95: 0 | AR95: 0 | AS95: #N/A | AT95: да | AU95: нет | AW95: правильно | AX95: да | AZ95: да | BD95: правильно | BF95: 0 | BG95: 0 | BH95: 0
A96: =CONCATENATE(C96,"-",E96,"-",G96) -> 59xx-970640006196-590120250728TAC0001 | B96: 46112 | C96: 59xx | D96: г.Шымкент | E96: 970640006196 | F96: ТОО "Shymkent Group Строй" | G96: 590120250728TAC0001 | H96: ИСНА | I96: 590120250801OAP0013 | J96: 45866 | K96: 45870 | L96: 46112 | M96: 46112 | N96: тематическая | O96: Тематическая проверка | R96: 44562 | S96: 45657 | T96: Серғұлыұлы А., Зияев Я.Р. | U96: СКП | W96: Строительство | X96: КГД МФ РК | Y96: 668 | Z96: 45862 | AD96: 108196473055 | AE96: 1.4 | AF96: РБ | AG96: 101110 | AH96: =AI96+AJ96 -> 44546979 | AI96: 33674637 | AJ96: 10872342 | AK96: 0 | AL96: 13469855 | AM96: =AN96+AO96+AP96+AQ96+AR96 -> 24342197 | AN96: 0 | AO96: 0 | AP96: 10872342 | AQ96: 0 | AR96: 13469855 | AS96: УНА | AT96: да | AU96: да | AV96: 2026г. | AW96: правильно | AZ96: да | BB96: да | BD96: правильно | BI96: 24342197
A97: =CONCATENATE(C97,"-",E97,"-",G97) -> 30xx-50540012941-300120250714TAC0001 | B97: 46036 | C97: 30xx | D97: Карагандинская | E97: 50540012941 | F97: ТОО "Каз Строй АкЖол Курылыс" | G97: 300120250714TAC0001 | H97: ИСНА | I97: 300120250805OAP0001 | J97: 45852 | K97: 45874 | L97: 46021 | N97: тематическая | O97: Тематическая проверка | R97: 44562 | S97: 45657 | T97: Оспанова А.С. | U97: 2. ССП | W97: 41202 Строительство нежилых зданий, за исключением стационарных торговых объектов категорий 1, 2 | X97: Приказ КГД МФ РК | Y97: 579 | Z97: 45842 | AF97: РБ | AG97: 101110 | AH97: =AI97+AJ97 -> 78395516 | AI97: 72450741 | AJ97: 5944775 | AK97: 0 | AL97: 0 | AM97: =AN97+AO97+AP97+AQ97+AR97 -> 24057460 | AN97: 18112685 | AO97: 0 | AP97: 5944775 | AQ97: 0 | AR97: 0 | AS97: #N/A | AT97: да | AU97: да | AV97: правильно | AW97: правильно | AX97: да | AZ97: да | BD97: правильно | BI97: 24057460
A98: =CONCATENATE(C98,"-",E98,"-",G98) -> 48xx-970940002514-480120250827TAC0001 | B98: 46099 | C98: 48xx | D98: СКО | E98: 970940002514 | F98: ТОО "Стройкомпания" | G98: 480120250827TAC0001 | H98: ИСНА | I98: 480120250912OAP0001 | J98: 45896 | K98: 45911 | L98: 46020 | M98: 46021 | N98: тематическая | O98: Тематическая проверка | R98: 44562 | S98: 45629 | T98: Сосновская Н.М. | U98: СМП | V98: нет | W98: Строительство жилых зданий | X98: Приказ КГД МФ РК | Y98: 821 | Z98: 45897 | AF98: МБ | AG98: 101111 | AH98: =AI98+AJ98 -> 19536996 | AI98: 16527851 | AJ98: 3009145.2 | AK98: 0 | AL98: 4131963 | AM98: =AN98+AO98+AP98+AQ98+AR98 -> 23668959 | AN98: 0 | AO98: 16527851 | AP98: 3009145.2 | AQ98: 0 | AR98: 4131963 | AS98: #N/A | AT98: да | AU98: нет | AW98: правильно | AY98: да | AZ98: да | BB98: да | BD98: правильно | BF98: 0
A99: =CONCATENATE(C99,"-",E99,"-",G99) -> 43xx-10340002721-430120250919TAC0007 | B99: 46045 | C99: 43xx | D99: Мангистауская | E99: 10340002721 | F99: ТОО ОЙЛ СНАБ ЛТД | G99: 430120250919TAC0007 | H99: ИСНА | I99: 430120251006OAP0019 | J99: 45919 | K99: 45933 | L99: 45979 | N99: комплексная | O99: Комплексная проверка | R99: 44562 | S99: 45657 | T99: Кадырова Д. | U99: крупный | W99: Оптовая торговля широким ассортиментом товаров без какой-либо конкретизации | X99: КГД МФ РК | AF99: РБ | AG99: 101110 | AH99: =AI99+AJ99 -> 23982243 | AI99: 22942207 | AJ99: 1040036 | AK99: 0 | AL99: 9176883 | AM99: =AN99+AO99+AP99+AQ99+AR99 -> 22942207 | AN99: 22942207 | AO99: 0 | AP99: 0 | AQ99: 0 | AR99: 0 | AS99: #N/A | AT99: нет | AU99: нет | AV99: убрать полностью | AW99: правильно | AX99: да | AZ99: да | BB99: да | BD99: правильно | BF99: 33159126
A100: =CONCATENATE(C100,"-",E100,"-",G100) -> 15xx-991140002442-124 | B100: 46045 | C100: 15xx | D100: Атырауская | E100: 991140002442 | F100: ТОО "Мунай Сервис,ЛТД" | G100: 124 | H100: ИНИС | I100: 124 | J100: 45833 | K100: 45861 | L100: 46022 | M100: 45658 | O100: тематическая | R100: 44562 | S100: 45657 | T100: Ерниязов А.А | U100: Средний | W100: Услуги, связанные с добычей нефти и газа | X100: КГД МФ РК | Y100: 239 | Z100: 45772 | AD100: 35809285694 | AE100: 3.2 | AF100: РБ | AG100: 101110 | AH100: =AI100+AJ100 -> 51356742 | AI100: 51356742 | AJ100: 0 | AK100: 0 | AL100: 0 | AM100: =AN100+AO100+AP100+AQ100+AR100 -> 22833578 | AN100: 3759591 | AO100: 0 | AP100: 8313069 | AQ100: 0 | AR100: 10760918 | AS100: #N/A | AT100: да | AU100: 0 | AV100: норм | AW100: правильно | AX100: да | AZ100: да | BB100: да | BD100: правильно | BF100: 39284081 | BG100: 0 | BH100: 0
...

Sheet Завершенные ИНИС и ИСНА
A1: Ф | B1: Орган гос. доходов | C1: Код ДГД | D1: ИНИС/ИСНА | E1: Отдел ответственного исполнителя | F1: Ф.И.О. ответственного исполнителя | G1: № дела | H1: Дата открытия дела | I1: Дата окончания проверки | J1: Вид проверки | K1: Проверка косвенным методом | L1: Проверяемый период | N1: Орган инициирования | O1: РНН проверяемого н/п | P1: ИИН/БИН проверяемого н/п | Q1: Наименование проверяемого н/п | R1: ОКЭД проверяемого н/п | S1: Субъект предпринимательства | T1: Управление на 01.04.2026 | U1: Доначислено | AD1: Штраф по КоАП | AG1: Уменьшено | AJ1: Уменьшенный убыток | AK1: Приказ УНА | AL1: Мониторинг | AM1: Приказ УДМ
U2: Всего | X2: в том числе:
X3: Налог | AA3: Пеня
L4: с | M4: по | U4: Доначислено | V4: Взыскано | W4: % взыскания | X4: Доначислено | Y4: Взыскано | Z4: % взыскания | AA4: Доначислено | AB4: Взыскано | AC4: % взыскания | AD4: Доначислено | AE4: Взыскано | AF4: % взыскания | AG4: Всего | AH4: Налог | AI4: Пеня
U5: =SUBTOTAL(9,U7:U1048576) -> 7.0368473e+10 | V5: =SUBTOTAL(9,V7:V1048576) -> 5.3291317e+08 | W5: =SUBTOTAL(9,W7:W1048576) -> 125.82 | X5: =SUBTOTAL(9,X7:X1048576) -> 4.8367092e+10 | Y5: =SUBTOTAL(9,Y7:Y1048576) -> 274256283 | Z5: =SUBTOTAL(9,Z7:Z1048576) -> 100 | AA5: =SUBTOTAL(9,AA7:AA1048576) -> 2.2001382e+10 | AB5: =SUBTOTAL(9,AB7:AB1048576) -> 2.5865689e+08 | ... AJ5: =SUBTOTAL(9,AJ7:AJ1048576) -> 47717236637
J6: фыв | P6: фыв | U6: фыв | AJ6: asd
A7: =CONCATENATE(C7,"-",P7,"-",G7) -> 60xx-970440003326-2302 | B7: 6001 ДГД по г.Алматы | C7: 60xx | D7: ИНИС | E7: отдел аудита №6 | F7: Тынымбаев М.А. | G7: 2302 | H7: 45636 | I7: 46048 | J7: Тематическая | K7: Нет | L7: 43466 | M7: 45291 | N7: КГД МФ РК | O7: 600400073886 | P7: 970440003326 | Q7: АО Колеса | R7: N63114 | S7: Субъекты крупного предпринимательства | T7: УНА | U7: 1.2929865e+10 | V7: 0 | W7: 0 | X7: 7834799272 | Y7: 0 | Z7: 0 | AA7: 5.0950655e+09 | AB7: 0 | AC7: 0 | AD7: 0 | AE7: 0 | AF7: 0 | AG7: 0 | AH7: 0 | AI7: 0 | AJ7: 0 | AK7: 45601 | AL7: #N/A | AM7: #N/A
A8: =CONCATENATE(C8,"-",P8,"-",G8) -> 60xx-950540000024-530 | B8: 6001 ДГД по г.Алматы | C8: 60xx | D8: ИНИС | E8: отдел аудита №6 | F8: Хинизов Э.К. | G8: 530 | H8: 45792 | I8: 46078 | J8: Тематическая | K8: Нет | L8: 44197 | M8: 45291 | N8: КГД МФ РК | O8: 600900079784 | P8: 950540000024 | Q8: АО "Страховая компания "Евразия" | R8: N65122 | S8: Субъекты крупного предпринимательства | T8: ДКН/СД | U8: 8.5971301e+09 | V8: 0 | W8: 0 | X8: 5651000821 | Y8: 0 | Z8: 0 | AA8: 2.9461292e+09 | AB8: 0 | AC8: 0 | AD8: 0 | AE8: 0 | AF8: 0 | AG8: 0 | AH8: 0 | AI8: 0 | AJ8: 0 | AK8: #N/A | AL8: 2024-2025гг. | AM8: #N/A
A9: =CONCATENATE(C9,"-",P9,"-",G9) -> 06xx-40340008667-271 | B9: 601 ДГД по Актюбинской области | C9: 06xx | D9: ИНИС | E9: Управление крупных налогоплательщиков и международного налогообложения | F9: Джусупова М.С. | G9: 271 | H9: 45611 | I9: 46028 | J9: Комплексная | K9: Нет | L9: 43466 | M9: 45291 | N9: КГД МФ РК | O9: 61800229455 | P9: 40340008667 | Q9: ТОО "Актюбинская медная компания" | R9: N07292 | S9: Субъекты крупного предпринимательства | T9: ДКН/СД | U9: 4.7371376e+09 | V9: 0 | W9: 0 | X9: 3367375451 | Y9: 0 | Z9: 0 | AA9: 1.3697621e+09 | AB9: 0 | AC9: 0 | AD9: 0 | AE9: 0 | AF9: 0 | AG9: 0 | AH9: 0 | AI9: 0 | AJ9: 1495113150 | AK9: #N/A | AL9: 2024-2025гг. | AM9: #N/A
A10: =CONCATENATE(C10,"-",P10,"-",G10) -> 15xx-1240000920-77 | B10: 1501 ДГД по Атырауской области | C10: 15xx | D10: ИНИС | E10: Управление крупных налогоплательщиков и международного налогообложение | F10: Тажиева Ж. | G10: 77 | H10: 45792 | I10: 46049 | J10: Комплексная | K10: Нет | L10: 43831 | M10: 45657 | N10: КГД МФ РК | O10: 150100003416 | P10: 1240000920 | Q10: ТОО "Болашак-Атырау" | R10: N78301 | S10: Субъекты крупного предпринимательства | T10: ДКН/СД | U10: 4.2013402e+09 | V10: 0 | W10: 0 | X10: 2717911235 | Y10: 0 | Z10: 0 | AA10: 1.4834289e+09 | AB10: 0 | AC10: 0 | AD10: 0 | AE10: 0 | AF10: 0 | AG10: 0 | AH10: 0 | AI10: 0 | AJ10: 0 | AK10: #N/A | AL10: 2024-2025гг. | AM10: #N/A
A11: =CONCATENATE(C11,"-",P11,"-",G11) -> 45xx-61140001916-42 | B11: 4501 ДГД по Павлодарской области | C11: 45xx | D11: ИНИС | E11: Управление крупных налогоплательщиков | F11: Жуматаев С.А. | G11: 42 | H11: 45747 | I11: 46056 | J11: Тематическая | K11: Нет | L11: 43831 | M11: 45291 | N11: КГД МФ РК | O11: 451600220104 | P11: 61140001916 | Q11: ТОО "Проммашкомплект" | R11: N24100 | S11: Субъекты крупного предпринимательства | T11: ДКН/СД | U11: 3.8800898e+09 | V11: 0 | W11: 0 | X11: 2524701150 | Y11: 0 | Z11: 0 | AA11: 1.3553886e+09 | AB11: 0 | AC11: 0 | AD11: 0 | AE11: 0 | AF11: 0 | AG11: 0 | AH11: 0 | AI11: 0 | AJ11: 0 | AK11: #N/A | AL11: 2024-2025гг. | AM11: #N/A
A12: =CONCATENATE(C12,"-",P12,"-",G12) -> 59xx-50940002443-285 | B12: 5901 ДГД по г. Шымкент | C12: 59xx | D12: ИНИС | E12: отдел аудита № 1 | F12: Сергулыулы А. | G12: 285 | H12: 45601 | I12: 46080 | J12: Тематическая | K12: Нет | L12: 44197 | M12: 45291 | N12: КГД МФ РК | O12: 581100215260 | P12: 50940002443 | Q12: ТОО "High Industrial Lubricants & Liquids Corporation" (HILL)" | R12: N20599 | S12: Субъекты крупного предпринимательства | T12: УНА | U12: 3.4800301e+09 | V12: 0 | W12: 0 | X12: 2244700429 | Y12: 0 | Z12: 0 | AA12: 1.2353297e+09 | AB12: 0 | AC12: 0 | AD12: 0 | AE12: 0 | AF12: 0 | AG12: 0 | AH12: 0 | AI12: 0 | AJ12: 0 | AK12: 45593 | AL12: #N/A | AM12: #N/A
A13: =CONCATENATE(C13,"-",P13,"-",G13) -> 45xx-41240000988-84 | B13: 4501 ДГД по Павлодарской области | C13: 45xx | D13: ИНИС | E13: Управление крупных налогоплательщиков | F13: Жуматаев С.А. | G13: 84 | H13: 45811 | I13: 46111 | J13: Тематическая | K13: Нет | L13: 43831 | M13: 45291 | N13: КГД МФ РК | O13: 451500226319 | P13: 41240000988 | Q13: ТОО "KDV Казахстан" | R13: N46389 | S13: Субъекты крупного предпринимательства | T13: ДКН/СД | U13: 2.5949917e+09 | V13: 0 | W13: 0 | X13: 1607113200 | Y13: 0 | Z13: 0 | AA13: 9.8787851e+08 | AB13: 0 | AC13: 0 | AD13: 0 | AE13: 0 | AF13: 0 | AG13: 0 | AH13: 0 | AI13: 0 | AJ13: 0 | AK13: #N/A | AL13: 2024-2025гг. | AM13: #N/A
A14: =CONCATENATE(C14,"-",P14,"-",G14) -> 30xx-30540002821-300120251209TAC0038 | B14: 3001 ДГД по Карагандинской области | C14: 30xx | D14: ИСНА | E14: Отдел аудита №2 | F14: Оспанова Айнагуль Сейтпаевна | G14: 300120251209TAC0038 | H14: 46000 | J14: Тематическая проверка | L14: 44562 | M14: 45657 | N14: КГД МФ РК | O14: 302000232846 | P14: 30540002821 | Q14: АО "Акционерный инвестиционный фонд недвижимости "ЦУМ" | T14: УНА | U14: 2.3692289e+09 | V14: 0 | W14: 0 | X14: 1870456034 | Y14: 0 | Z14: 0 | AA14: 4.9877283e+08 | AB14: 0 | AC14: 0 | AD14: 0 | AE14: 0 | AF14: 0 | AG14: 0 | AH14: 0 | AI14: 0 | AJ14: 731968877
A15: =CONCATENATE(C15,"-",P15,"-",G15) -> 60xx-960740000122-618 | B15: 6001 ДГД по г.Алматы | C15: 60xx | D15: ИНИС | E15: отдел аудита №6 | F15: Хинизов Э.К. | G15: 618 | H15: 45408 | I15: 46107 | J15: Комплексная | K15: Нет | L15: 43466 | M15: 44926 | N15: КГД МФ РК | O15: 600200107667 | P15: 960740000122 | Q15: ТОО "Торговая Компания "Мегаполис-Казахстан" | R15: N46909 | S15: Субъекты крупного предпринимательства | T15: ДКН/СД | U15: 2.3308726e+09 | V15: 0 | W15: 0 | X15: 1510902372 | Y15: 0 | Z15: 0 | AA15: 8.1997026e+08 | AB15: 0 | AC15: 0 | AD15: 0 | AE15: 0 | AF15: 0 | AG15: 0 | AH15: 0 | AI15: 0 | AJ15: 0 | AK15: #N/A | AL15: 2024-2025гг. | AM15: #N/A
A16: =CONCATENATE(C16,"-",P16,"-",G16) -> 43xx-71040008357-430120251209TAC0099 | B16: 4301 ДГД по Мангистауской области | C16: 43xx | D16: ИСНА | E16: Отдел аудита | F16: Утепов Еркебулан Арысбайұлы | G16: 430120251209TAC0099 | H16: 46000 | J16: Тематическая проверка | L16: 44927 | M16: 45291 | N16: КГД МФ РК | O16: 430100254973 | P16: 71040008357 | Q16: АО "Социально-предпринимательская корпорация "Каспий" | T16: УНА | U16: 2.0440046e+09 | V16: 0 | W16: 0 | X16: 1.4742299e+09 | Y16: 0 | Z16: 0 | AA16: 5.6977471e+08 | AB16: 0 | AC16: 0 | AD16: 0 | AE16: 0 | AF16: 0 | AG16: 0 | AH16: 0 | AI16: 0 | AJ16: 3628850501
A17: =CONCATENATE(C17,"-",P17,"-",G17) -> 70xx-211240012650-22 | B17: 7001 ДГД по области Жетысу | C17: 70xx | D17: ИНИС | E17: Отдел аудита | F17: Сабдикенова С.С. | G17: 22 | H17: 45779 | I17: 46071 | J17: Тематическая | K17: Нет | L17: 44562 | M17: 45291 | N17: КГД МФ РК | O17: 91900221327 | P17: 211240012650 | Q17: ТОО "Art logistik group" | R17: N52299 | S17: Субъекты среднего предпринимательства | T17: УНА | U17: 1.7093773e+09 | V17: 0 | W17: 0 | X17: 1265469000 | Y17: 0 | Z17: 0 | AA17: 4.4390827e+08 | AB17: 0 | AC17: 0 | AD17: 0 | AE17: 0 | AF17: 0 | AG17: 0 | AH17: 0 | AI17: 0 | AJ17: 0 | AK17: 45772 | AL17: #N/A | AM17: #N/A
A18: =CONCATENATE(C18,"-",P18,"-",G18) -> 60xx-110240013139-405 | B18: 6001 ДГД по г.Алматы | C18: 60xx | D18: ИНИС | E18: Отдел аудита №1 | F18: Куришбаева Ж.Т. | G18: 405 | H18: 45735 | I18: 46035 | J18: Тематическая | K18: Нет | L18: 44562 | M18: 45291 | N18: КГД МФ РК | O18: 600900640842 | P18: 110240013139 | Q18: ТОО "ТЕХНОБЕЛ" | R18: N49420 | S18: Субъекты крупного предпринимательства | T18: УНА | U18: 1.3515571e+09 | V18: 0 | W18: 0 | X18: 977288139 | Y18: 0 | Z18: 0 | AA18: 3.7426894e+08 | AB18: 0 | AC18: 0 | AD18: 0 | AE18: 0 | AF18: 0 | AG18: 0 | AH18: 0 | AI18: 0 | AJ18: 0 | AK18: 45652 | AL18: #N/A | AM18: #N/A
A19: =CONCATENATE(C19,"-",P19,"-",G19) -> 09xx-131040006572-116 | B19: 901 ДГД по Алматинской области | C19: 09xx | D19: ИНИС | E19: Отдел аудита №2 | F19: Сейдахметов Н.Б. | G19: 116 | H19: 45834 | I19: 46041 | J19: Тематическая | K19: Нет | L19: 44562 | M19: 45291 | N19: КГД МФ РК | O19: 600400664826 | P19: 131040006572 | Q19: ТОО "Silk Road KazTrans logistics" | R19: N49410 | S19: Субъекты среднего предпринимательства | T19: УНА | U19: 1.2675543e+09 | V19: 0 | W19: 0 | X19: 895770401 | Y19: 0 | Z19: 0 | AA19: 3.7178393e+08 | AB19: 0 | AC19: 0 | AD19: 0 | AE19: 0 | AF19: 0 | AG19: 0 | AH19: 0 | AI19: 0 | AJ19: 0 | AK19: 45831 | AL19: #N/A | AM19: #N/A
A20: =CONCATENATE(C20,"-",P20,"-",G20) -> 60xx-61040000012-600120251113TAC0081 | B20: 6001 ДГД по г.Алматы | C20: 60xx | D20: ИСНА | E20: Отдел аудита №6 | F20: Жапарова Гульжан Ораловна | G20: 600120251113TAC0081 | H20: 45974 | J20: Тематическая проверка | L20: 43831 | M20: 44926 | N20: КГД МФ РК | O20: 600500559512 | P20: 61040000012 | Q20: ТОО "Медико-Инновационные Технологии" | T20: УНА | U20: 975496108 | V20: 0 | W20: 0 | X20: 562328792 | Y20: 0 | Z20: 0 | AA20: 413167316 | AB20: 0 | AC20: 0 | AD20: 0 | AE20: 0 | AF20: 0 | AG20: 0 | AH20: 0 | AI20: 0 | AJ20: 0
A21: =CONCATENATE(C21,"-",P21,"-",G21) -> 60xx-31040005137-605 | B21: 6001 ДГД по г.Алматы | C21: 60xx | D21: ИНИС | E21: отдел аудита №5 | F21: Митаева Б.Т. | G21: 605 | H21: 45799 | I21: 46036 | J21: Комплексная | K21: Нет | L21: 44562 | M21: 45291 | N21: Другие заявления налогоплательщика | O21: 600700529903 | P21: 31040005137 | Q21: ТОО "Euroasia Transit Group" ("Евразия Транзит Груп") | R21: N77391 | S21: Субъекты среднего предпринимательства | T21: УНА | U21: 925034682 | V21: 238888028 | W21: 25.82 | X21: 686146554 | Y21: 0 | Z21: 0 | AA21: 238888128 | AB21: 238888028 | AC21: 100 | AD21: 0 | AE21: 0 | AF21: 0 | AG21: 0 | AH21: 0 | AI21: 0 | AJ21: 0 | AK21: #N/A | AL21: #N/A | AM21: #N/A
A22: =CONCATENATE(C22,"-",P22,"-",G22) -> 60xx-110540018776-618 | B22: 6001 ДГД по г.Алматы | C22: 60xx | D22: ИНИС | E22: Отдел аудита №3 | F22: Сегизбаева А.А. | G22: 618 | H22: 45805 | I22: 46076 | J22: Тематическая | K22: Нет | L22: 43831 | M22: 45657 | N22: КГД МФ РК | O22: 600900643989 | P22: 110540018776 | Q22: ТОО "OIL RELOADING CORP" | R22: N06100 | S22: Субъекты крупного предпринимательства | T22: УНА | U22: 8.394108e+08 | V22: 0 | W22: 0 | X22: 489354389 | Y22: 0 | Z22: 0 | AA22: 3.5005641e+08 | AB22: 0 | AC22: 0 | AD22: 0 | AE22: 0 | AF22: 0 | AG22: 0 | AH22: 0 | AI22: 0 | AJ22: 11926768 | AK22: #N/A | AL22: #N/A | AM22: #N/A
A23: =CONCATENATE(C23,"-",P23,"-",G23) -> 60xx-231040001661-600120250718TAC0005 | B23: 6001 ДГД по г.Алматы | C23: 60xx | D23: ИСНА | E23: Отдел аудита №2 | F23: Дарибаев Даурен Тлеуханович | G23: 600120250718TAC0005 | H23: 45856 | J23: Тематическая проверка | L23: 45201 | M23: 45697 | N23: Департамент экономических расследований КФМ РК | O23: 600300772295 | P23: 231040001661 | Q23: ТОО "Kaz Cordyceps" | T23: УНА | U23: 8.1050638e+08 | V23: 0 | W23: 0 | X23: 6.7116132e+08 | Y23: 0 | Z23: 0 | AA23: 1.3934506e+08 | AB23: 0 | AC23: 0 | AD23: 0 | AE23: 0 | AF23: 0 | AG23: 0 | AH23: 0 | AI23: 0 | AJ23: 0
A24: =CONCATENATE(C24,"-",P24,"-",G24) -> 45xx-181240001419-450120251120TAC0023 | B24: 4501 ДГД по Павлодарской области | C24: 45xx | D24: ИСНА | E24: Отдел аудита | F24: Ахметова Зарина Ахметжановна | G24: 450120251120TAC0023 | H24: 45981 | J24: Тематическая проверка | L24: 44562 | M24: 45291 | N24: КГД МФ РК | O24: 451500338000 | P24: 181240001419 | Q24: ТОО "Голден Азия КЗ" | T24: УНА | U24: 7.6807164e+08 | V24: 0 | W24: 0 | X24: 6.109008e+08 | Y24: 0 | Z24: 0 | AA24: 1.5717085e+08 | AB24: 0 | AC24: 0 | AD24: 0 | AE24: 0 | AF24: 0 | AG24: 0 | AH24: 0 | AI24: 0 | AJ24: 1679309077
A25: =CONCATENATE(C25,"-",P25,"-",G25) -> 06xx-980240000128-060120250825TAC0030 | B25: 0601 ДГД по Актюбинской области | C25: 06xx | D25: ИСНА | E25: Отдел аудита | F25: Кукеева Кляш Байдуловна | G25: 060120250825TAC0030 | H25: 45894 | J25: Тематическая проверка | L25: 44562 | M25: 45291 | N25: КГД МФ РК | O25: 060100000698 | P25: 980240000128 | Q25: ТОО "Кентавр" | T25: УНА | U25: 7.1445332e+08 | V25: 0 | W25: 0 | X25: 6.2224411e+08 | Y25: 0 | Z25: 0 | AA25: 92209206 | AB25: 0 | AC25: 0 | AD25: 0 | AE25: 0 | AF25: 0 | AG25: 0 | AH25: 0 | AI25: 0 | AJ25: 0
A26: =CONCATENATE(C26,"-",P26,"-",G26) -> 60xx-90940003479-1823 | B26: 6001 ДГД по г.Алматы | C26: 60xx | D26: ИНИС | E26: отдел аудита №6 | F26: Сабитова А.С. | G26: 1823 | H26: 45588 | I26: 46037 | J26: Тематическая | K26: Нет | L26: 43466 | M26: 45291 | N26: КГД МФ РК | O26: 600900623699 | P26: 90940003479 | Q26: ТОО "Ритейл Групп Казахстан" | R26: N47713 | S26: Субъекты крупного предпринимательства | T26: ДКН/СД | U26: 6.9792905e+08 | V26: 0 | W26: 0 | X26: 475826742 | Y26: 0 | Z26: 0 | AA26: 2.2210231e+08 | AB26: 0 | AC26: 0 | AD26: 0 | AE26: 0 | AF26: 0 | AG26: 0 | AH26: 0 | AI26: 0 | AJ26: 0 | AK26: #N/A | AL26: 2024-2025гг. | AM26: #N/A
A27: =CONCATENATE(C27,"-",P27,"-",G27) -> 18xx-970640000261-180120251031TAC0132 | B27: 1801 ДГД по Восточно-Казахстанской области | C27: 18xx | D27: ИСНА | E27: Отдел аудита №1 | F27: Алиева Айгуль Есмуратовна | G27: 180120251031TAC0132 | H27: 45961 | J27: Тематическая проверка | L27: 44562 | M27: 44926 | N27: КГД МФ РК | O27: 181600043631 | P27: 970640000261 | Q27: ТОО "Kurylys Group RK" | T27: УНА | U27: 6.3814764e+08 | V27: 0 | W27: 0 | X27: 406936980 | Y27: 0 | Z27: 0 | AA27: 2.3121066e+08 | AB27: 0 | AC27: 0 | AD27: 0 | AE27: 0 | AF27: 0 | AG27: 0 | AH27: 0 | AI27: 0 | AJ27: 0
A28: =CONCATENATE(C28,"-",P28,"-",G28) -> 48xx-931240000240-480120251125TAC0018 | B28: 4801 ДГД по Северо-Казахстанской области | C28: 48xx | D28: ИСНА | E28: Отдел аудита №1 | F28: Байбусинова Валентина Александровна | G28: 480120251125TAC0018 | H28: 45986 | J28: Тематическая проверка | L28: 44927 | M28: 45657 | N28: КГД МФ РК | O28: 481400000270 | P28: 931240000240 | Q28: ТОО "ЗИКСТО" | T28: УНА | U28: 6.1643236e+08 | V28: 0 | W28: 0 | X28: 5.2158947e+08 | Y28: 0 | Z28: 0 | AA28: 94842892 | AB28: 0 | AC28: 0 | AD28: 0 | AE28: 0 | AF28: 0 | AG28: 0 | AH28: 0 | AI28: 0 | AJ28: 0
A29: =CONCATENATE(C29,"-",P29,"-",G29) -> 03xx-100740005561-182 | B29: 301 ДГД по Акмолинской области | C29: 03xx | D29: ИНИС | E29: Управление аудита | F29: Ертаев Е.А. | G29: 182 | H29: 45496 | I29: 46042 | J29: Тематическая | K29: Нет | L29: 43831 | M29: 45291 | N29: КГД МФ РК | O29: 32600244338 | P29: 100740005561 | Q29: ТОО "Казахстанская Агро Инновационная Корпорация" | R29: N28302 | S29: Субъекты крупного предпринимательства | T29: ДКН/СД | U29: 5.6157138e+08 | V29: 0 | W29: 0 | X29: 462625583 | Y29: 0 | Z29: 0 | AA29: 98945801 | AB29: 0 | AC29: 0 | AD29: 0 | AE29: 0 | AF29: 0 | AG29: 0 | AH29: 0 | AI29: 0 | AJ29: 0 | AK29: #N/A | AL29: 2024-2025гг. | AM29: #N/A
A30: =CONCATENATE(C30,"-",P30,"-",G30) -> 06xx-41040001453-060120250806TAC0002 | B30: 0601 ДГД по Актюбинской области | C30: 06xx | D30: ИСНА | E30: Отдел аудита | F30: Мулькаева Айымгуль Бахитжановна | G30: 060120250806TAC0002 | H30: 45875 | J30: Тематическая проверка | L30: 44197 | M30: 45657 | N30: КГД МФ РК | O30: 061800236392 | P30: 41040001453 | Q30: ТОО "МИЗАМ" | T30: УНА | U30: 5.1013362e+08 | V30: 0 | W30: 0 | X30: 3.0575069e+08 | Y30: 0 | Z30: 0 | AA30: 2.0438293e+08 | AB30: 0 | AC30: 0 | AD30: 0 | AE30: 0 | AF30: 0 | AG30: 0 | AH30: 0 | AI30: 0 | AJ30: 50032665
A31: =CONCATENATE(C31,"-",P31,"-",G31) -> 62xx-60340012936-620120250929TAC0017 | B31: 6201 ДГД по г. Астана | C31: 62xx | D31: ИСНА | E31: Отдел аудита №4 | F31: Кабиев Жандос Талғатұлы | G31: 620120250929TAC0017 | H31: 45929 | J31: Тематическая проверка | L31: 44562 | M31: 45657 | N31: КГД МФ РК | O31: 620200271328 | P31: 60340012936 | Q31: ТОО "M50 Consulting Group" ( М50 Консалтинг Групп) | T31: УНА | U31: 4.794761e+08 | V31: 0 | W31: 0 | X31: 3.3223912e+08 | Y31: 0 | Z31: 0 | AA31: 1.4723698e+08 | AB31: 0 | AC31: 0 | AD31: 0 | AE31: 0 | AF31: 0 | AG31: 0 | AH31: 0 | AI31: 0 | AJ31: 0
A32: =CONCATENATE(C32,"-",P32,"-",G32) -> 30xx-60140007328-300120251106TAC0001 | B32: 3001 ДГД по Карагандинской области | C32: 30xx | D32: ИСНА | E32: Отдел аудита №2 | F32: Алибекова Алтынай Актаевна | G32: 300120251106TAC0001 | H32: 45967 | J32: Тематическая проверка | L32: 44562 | M32: 45291 | N32: КГД МФ РК | O32: 600500550882 | P32: 60140007328 | Q32: ТОО "MK-Construction Group" | T32: УНА | U32: 4.7813824e+08 | V32: 0 | W32: 0 | X32: 3.2165722e+08 | Y32: 0 | Z32: 0 | AA32: 1.5648102e+08 | AB32: 0 | AC32: 0 | AD32: 0 | AE32: 0 | AF32: 0 | AG32: 0 | AH32: 0 | AI32: 0 | AJ32: 2992267611
A33: =CONCATENATE(C33,"-",P33,"-",G33) -> 60xx-120240012361-600120251124TAC0024 | B33: 6001 ДГД по г.Алматы | C33: 60xx | D33: ИСНА | E33: Отдел аудита №1 | F33: Аблаева Айша Муратовна | G33: 600120251124TAC0024 | H33: 45985 | J33: Тематическая проверка | L33: 44562 | M33: 45657 | N33: КГД МФ РК | O33: 600900652318 | P33: 120240012361 | Q33: ТОО "Tunahan Construction" (Тунахан Конструктион) | T33: УНА | U33: 4.2192223e+08 | V33: 0 | W33: 0 | X33: 355681676 | Y33: 0 | Z33: 0 | AA33: 66240557 | AB33: 0 | AC33: 0 | AD33: 0 | AE33: 0 | AF33: 0 | AG33: 0 | AH33: 0 | AI33: 0 | AJ33: 0
A34: =CONCATENATE(C34,"-",P34,"-",G34) -> 06xx-180640033373-166 | B34: 601 ДГД по Актюбинской области | C34: 06xx | D34: ИНИС | E34: Отдел аудита | F34: Койшина М.К. | G34: 166 | H34: 45833 | I34: 46050 | J34: Тематическая | K34: Нет | L34: 44562 | M34: 45291 | N34: КГД МФ РК | O34: 61800387575 | P34: 180640033373 | Q34: ТОО "RAMCO Refinery" | R34: N19201 | S34: Субъекты среднего предпринимательства | T34: УНА | U34: 3.7447594e+08 | V34: 0 | W34: 0 | X34: 273005120 | Y34: 0 | Z34: 0 | AA34: 1.0147082e+08 | AB34: 0 | AC34: 0 | AD34: 0 | AE34: 0 | AF34: 0 | AG34: 0 | AH34: 0 | AI34: 0 | AJ34: 358663923 | AK34: 45880 | AL34: #N/A | AM34: #N/A
A35: =CONCATENATE(C35,"-",P35,"-",G35) -> 43xx-120440019970-430120250722TAC0007 | B35: 4301 ДГД по Мангистауской области | C35: 43xx | D35: ИСНА | E35: Отдел ЭКНА | F35: Суюндуков Азамат Ахмедович | G35: 430120250722TAC0007 | H35: 45860 | J35: Тематическая проверка | L35: 44562 | M35: 45657 | N35: КГД МФ РК | O35: 430100286476 | P35: 120440019970 | Q35: Товарищество с ограниченным ответственностью "Каспий Монтаж Сервис" | T35: УНА | U35: 3.5550722e+08 | V35: 0 | W35: 0 | X35: 2.9986371e+08 | Y35: 0 | Z35: 0 | AA35: 55643507 | AB35: 0 | AC35: 0 | AD35: 0 | AE35: 0 | AF35: 0 | AG35: 0 | AH35: 0 | AI35: 0 | AJ35: 29913019
A36: =CONCATENATE(C36,"-",P36,"-",G36) -> 30xx-181040031057-300120250807TAC0015 | B36: 3001 ДГД по Карагандинской области | C36: 30xx | D36: ИСНА | E36: Отдел аудита №1 | F36: Кайроллаев Раимбек Аскарович | G36: 300120250807TAC0015 | H36: 45876 | J36: Тематическая проверка | L36: 44562 | M36: 44926 | N36: КГД МФ РК | O36: 302000411219 | P36: 181040031057 | Q36: Жилищно-строительный кооператив "Jana Sary-Arqa" | T36: УНА | U36: 3.5294866e+08 | V36: 0 | W36: 0 | X36: 2.2462555e+08 | Y36: 0 | Z36: 0 | AA36: 1.2832311e+08 | AB36: 0 | AC36: 0 | AD36: 0 | AE36: 0 | AF36: 0 | AG36: 0 | AH36: 0 | AI36: 0 | AJ36: 173621368
A37: =CONCATENATE(C37,"-",P37,"-",G37) -> 33xx-150240005057-330120251120TAC0001 | B37: 3301 ДГД по Кызылординской области | C37: 33xx | D37: ИСНА | E37: Отдел ЭКНА | F37: Тайгараев Жантуре Балабиевич | G37: 330120251120TAC0001 | H37: 45981 | J37: Комплексная проверка | L37: 44197 | M37: 45930 | N37: Органы национальной безопасности | O37: 620500046358 | P37: 150240005057 | Q37: ТОО "Orda Glass Ltd" (Орда Гласс Лтд) | T37: УНА | U37: 3.4529758e+08 | V37: 0 | W37: 0 | X37: 308556441 | Y37: 0 | Z37: 0 | AA37: 36741142 | AB37: 0 | AC37: 0 | AD37: 0 | AE37: 0 | AF37: 0 | AG37: 0 | AH37: 0 | AI37: 0 | AJ37: 1581784279
A38: =CONCATENATE(C38,"-",P38,"-",G38) -> 43xx-40740002305-430120250812TAC0005 | B38: 4301 ДГД по Мангистауской области | C38: 43xx | D38: ИСНА | E38: Отдел ЭКНА | F38: Изтурганов Алмас Амирович | G38: 430120250812TAC0005 | H38: 45881 | J38: Тематическая проверка | L38: 44562 | M38: 45657 | N38: КГД МФ РК | O38: 061800233684 | P38: 40740002305 | Q38: ТОО "Маяк ЛТД" | T38: УНА | U38: 3.2942251e+08 | V38: 0 | W38: 0 | X38: 2.9383848e+08 | Y38: 0 | Z38: 0 | AA38: 35584029 | AB38: 0 | AC38: 0 | AD38: 0 | AE38: 0 | AF38: 0 | AG38: 0 | AH38: 0 | AI38: 0 | AJ38: 8768508744
A39: =CONCATENATE(C39,"-",P39,"-",G39) -> 39xx-201040026939-390120251030TAC0004 | B39: 3901 ДГД по Костанайской области | C39: 39xx | D39: ИСНА | E39: Отдел ЭКНА | F39: Жумашев Берик Болатович | G39: 390120251030TAC0004 | H39: 45960 | J39: Тематическая проверка | L39: 45292 | M39: 45657 | N39: КГД МФ РК | O39: 390800221004 | P39: 201040026939 | Q39: ТОО "RInna" | T39: УНА | U39: 3.2073493e+08 | V39: 0 | W39: 0 | X39: 2.7678571e+08 | Y39: 0 | Z39: 0 | AA39: 43949211 | AB39: 0 | AC39: 0 | AD39: 0 | AE39: 0 | AF39: 0 | AG39: 0 | AH39: 0 | AI39: 0 | AJ39: 0
A40: =CONCATENATE(C40,"-",P40,"-",G40) -> 60xx-90540011693-358 | B40: 6001 ДГД по г.Алматы | C40: 60xx | D40: ИНИС | E40: отдел аудита №6 | F40: Жилисбаев М.М. | G40: 358 | H40: 45736 | I40: 46050 | J40: Тематическая | K40: Нет | L40: 43831 | M40: 44196 | N40: КГД МФ РК | O40: 600400606844 | P40: 90540011693 | Q40: ТОО "МК-Ломбард" | R40: N64921 | S40: Субъекты крупного предпринимательства | T40: ДКН/СД | U40: 3.1988467e+08 | V40: 0 | W40: 0 | X40: 188650945 | Y40: 0 | Z40: 0 | AA40: 1.3123373e+08 | AB40: 0 | AC40: 0 | AD40: 0 | AE40: 0 | AF40: 0 | AG40: 0 | AH40: 0 | AI40: 0 | AJ40: 0 | AK40: #N/A | AL40: 2024г. | AM40: #N/A
A41: =CONCATENATE(C41,"-",P41,"-",G41) -> 06xx-40540006757-120 | B41: 601 ДГД по Актюбинской области | C41: 06xx | D41: ИНИС | E41: Отдел аудита | F41: Жумашева Г.Г. | G41: 120 | H41: 45810 | I41: 46048 | J41: Тематическая | K41: Нет | L41: 44562 | M41: 45657 | N41: КГД МФ РК | O41: 61800231930 | P41: 40540006757 | Q41: ТОО "Актобе-Саулет" | R41: N41201 | S41: Субъекты среднего предпринимательства | T41: УНА | U41: 2.9402514e+08 | V41: 2.9402514e+08 | W41: 100 | X41: 274256283 | Y41: 274256283 | Z41: 100 | AA41: 19768858 | AB41: 19768858 | AC41: 100 | AD41: 0 | AE41: 0 | AF41: 0 | AG41: 0 | AH41: 0 | AI41: 0 | AJ41: 0 | AK41: 45806 | AL41: #N/A | AM41: #N/A
A42: =CONCATENATE(C42,"-",P42,"-",G42) -> 62xx-50140000262-41 | B42: 6201 ДГД по г. Астана | C42: 62xx | D42: ИНИС | E42: отдел аудита № 1 | F42: Суйеугалиев С.М. | G42: 41 | H42: 45706 | I42: 46049 | J42: Тематическая | K42: Нет | L42: 44562 | M42: 45565 | N42: КГД МФ РК | O42: 620200248884 | P42: 50140000262 | Q42: ТОО "Сатурн-Строй" | R42: N41201 | S42: Субъекты малого предпринимательства | T42: УНА | U42: 2.7954508e+08 | V42: 0 | W42: 0 | X42: 204943088 | Y42: 0 | Z42: 0 | AA42: 74601996 | AB42: 0 | AC42: 0 | AD42: 0 | AE42: 0 | AF42: 0 | AG42: 0 | AH42: 0 | AI42: 0 | AJ42: 0 | AK42: 45694 | AL42: #N/A | AM42: #N/A
A43: =CONCATENATE(C43,"-",P43,"-",G43) -> 62xx-31040004852-620120250530TAC0009 | B43: 6201 ДГД по г. Астана | C43: 62xx | D43: ИСНА | E43: Отдел аудита №3 | F43: Жайлауов Дулат Байжанұлы | G43: 620120250530TAC0009 | H43: 45807 | J43: Тематическая проверка | L43: 44562 | M43: 45657 | N43: КГД МФ РК | O43: 620300232793 | P43: 31040004852 | Q43: ТОО "АСТАНАВОДСЕРВИС" | T43: УНА | U43: 255475670 | V43: 0 | W43: 0 | X43: 243934839 | Y43: 0 | Z43: 0 | AA43: 11540831 | AB43: 0 | AC43: 0 | AD43: 0 | AE43: 0 | AF43: 0 | AG43: 0 | AH43: 0 | AI43: 0 | AJ43: 0
A44: =CONCATENATE(C44,"-",P44,"-",G44) -> 62xx-61040009998-620120250530TAC0010 | B44: 6201 ДГД по г. Астана | C44: 62xx | D44: ИСНА | E44: Отдел аудита №3 | F44: Муканова Асель Днесламовна | G44: 620120250530TAC0010 | H44: 45807 | J44: Тематическая проверка | L44: 44197 | M44: 45657 | N44: КГД МФ РК | O44: 620200285482 | P44: 61040009998 | Q44: ТОО "Digital Future" | T44: УНА | U44: 2.4654309e+08 | V44: 0 | W44: 0 | X44: 2.1450162e+08 | Y44: 0 | Z44: 0 | AA44: 32041465 | AB44: 0 | AC44: 0 | AD44: 0 | AE44: 0 | AF44: 0 | AG44: 0 | AH44: 0 | AI44: 0 | AJ44: 0
A45: =CONCATENATE(C45,"-",P45,"-",G45) -> 43xx-130440009491-430120250801TAC0005 | B45: 4301 ДГД по Мангистауской области | C45: 43xx | D45: ИСНА | E45: Отдел аудита | F45: Утепов Еркебулан Арысбайұлы | G45: 430120250801TAC0005 | H45: 45870 | J45: Тематическая проверка | L45: 44562 | M45: 45657 | N45: КГД МФ РК | O45: 430600006561 | P45: 130440009491 | Q45: ТОО "Қанағат Тағам" | T45: УНА | U45: 2.3377502e+08 | V45: 0 | W45: 0 | X45: 2.0364404e+08 | Y45: 0 | Z45: 0 | AA45: 30130976 | AB45: 0 | AC45: 0 | AD45: 0 | AE45: 0 | AF45: 0 | AG45: 0 | AH45: 0 | AI45: 0 | AJ45: 69588895
A46: =CONCATENATE(C46,"-",P46,"-",G46) -> 06xx-31040005996-060120250813TAC0002 | B46: 0601 ДГД по Актюбинской области | C46: 06xx | D46: ИСНА | E46: Отдел аудита | F46: Жумашева Галия Габдувалиевна | G46: 060120250813TAC0002 | H46: 45882 | J46: Тематическая проверка | L46: 44835 | M46: 45199 | N46: КГД МФ РК | O46: 061200211615 | P46: 31040005996 | Q46: ТОО "Актобе мунай маш комплект" | T46: УНА | U46: 223817148 | V46: 0 | W46: 0 | X46: 146510138 | Y46: 0 | Z46: 0 | AA46: 77307010 | AB46: 0 | AC46: 0 | AD46: 0 | AE46: 0 | AF46: 0 | AG46: 0 | AH46: 0 | AI46: 0 | AJ46: 0
A47: =CONCATENATE(C47,"-",P47,"-",G47) -> 60xx-190840023570-600120250904TAC0003 | B47: 6001 ДГД по г.Алматы | C47: 60xx | D47: ИСНА | E47: Отдел аудита №1 | F47: Якияев Нуржан Панабергенович | G47: 600120250904TAC0003 | H47: 45904 | J47: Тематическая проверка | L47: 44927 | M47: 45657 | N47: КГД МФ РК | O47: 600300698270 | P47: 190840023570 | Q47: ТОО "DAMU CONSTRUTION" | T47: УНА | U47: 2.2154567e+08 | V47: 0 | W47: 0 | X47: 1.9397655e+08 | Y47: 0 | Z47: 0 | AA47: 27569121 | AB47: 0 | AC47: 0 | AD47: 0 | AE47: 0 | AF47: 0 | AG47: 0 | AH47: 0 | AI47: 0 | AJ47: 0
A48: =CONCATENATE(C48,"-",P48,"-",G48) -> 62xx-130440029256-620120251209TAC0083 | B48: 6201 ДГД по г. Астана | C48: 62xx | D48: ИСНА | E48: Отдел аудита №3 | F48: Амангельдинова Надира Мұратқызы | G48: 620120251209TAC0083 | H48: 46000 | J48: Тематическая проверка | L48: 44562 | M48: 45657 | N48: КГД МФ РК | O48: 620500023414 | P48: 130440029256 | Q48: ТОО "VIP Клиника" (ВИП Клиника) | T48: УНА | U48: 2.0785642e+08 | V48: 0 | W48: 0 | X48: 1.721423e+08 | Y48: 0 | Z48: 0 | AA48: 35714116 | AB48: 0 | AC48: 0 | AD48: 0 | AE48: 0 | AF48: 0 | AG48: 0 | AH48: 0 | AI48: 0 | AJ48: 4455132972
A49: =CONCATENATE(C49,"-",P49,"-",G49) -> 45xx-120440014385-5 | B49: 4501 ДГД по Павлодарской области | C49: 45xx | D49: ИНИС | E49: Управление аудита | F49: Билялова З.К. | G49: 5 | H49: 45663 | I49: 46027 | J49: Тематическая | K49: Да | L49: 44197 | M49: 45291 | N49: КГД МФ РК | O49: 451500277390 | P49: 120440014385 | Q49: ТОО "3D Flowers KZ" | R49: N46220 | S49: Субъекты среднего предпринимательства | T49: УНА | U49: 2.0514843e+08 | V49: 0 | W49: 0 | X49: 122408747 | Y49: 0 | Z49: 0 | AA49: 82739680 | AB49: 0 | AC49: 0 | AD49: 0 | AE49: 0 | AF49: 0 | AG49: 0 | AH49: 0 | AI49: 0 | AJ49: 13151769004 | AK49: 45653 | AL49: #N/A | AM49: #N/A
A50: =CONCATENATE(C50,"-",P50,"-",G50) -> 06xx-180640033373-060120250813TAC0003 | B50: 0601 ДГД по Актюбинской области | C50: 06xx | D50: ИСНА | E50: Отдел аудита | F50: Сагинаева Анар Мурзамадиновна | G50: 060120250813TAC0003 | H50: 45882 | J50: Тематическая проверка | L50: 44743 | M50: 45291 | N50: КГД МФ РК | O50: 061800387575 | P50: 180640033373 | Q50: ТОО "RAMCO Refinery" | T50: УНА | U50: 2.0327903e+08 | V50: 0 | W50: 0 | X50: 188326108 | Y50: 0 | Z50: 0 | AA50: 14952924 | AB50: 0 | AC50: 0 | AD50: 0 | AE50: 0 | AF50: 0 | AG50: 0 | AH50: 0 | AI50: 0 | AJ50: 0
A51: =CONCATENATE(C51,"-",P51,"-",G51) -> 62xx-171140039580-620120251016TAC0359 | B51: 6201 ДГД по г. Астана | C51: 62xx | D51: ИСНА | E51: Отдел аудита №1 | F51: Суйеугалиев Сисенгали Мырзагулович | G51: 620120251016TAC0359 | H51: 45946 | J51: Тематическая проверка | L51: 44562 | M51: 45657 | N51: КГД МФ РК | O51: 620500097121 | P51: 171140039580 | Q51: ТОО "AP Company" | T51: УНА | U51: 1.9388507e+08 | V51: 0 | W51: 0 | X51: 1.4020055e+08 | Y51: 0 | Z51: 0 | AA51: 53684519 | AB51: 0 | AC51: 0 | AD51: 0 | AE51: 0 | AF51: 0 | AG51: 0 | AH51: 0 | AI51: 0 | AJ51: 0
A52: =CONCATENATE(C52,"-",P52,"-",G52) -> 59xx-210540030240-121 | B52: 5901 ДГД по г. Шымкент | C52: 59xx | D52: ИНИС | E52: отдел аудита № 1 | F52: Сергулыулы А. | G52: 121 | H52: 45763 | I52: 46112 | J52: Тематическая | K52: Нет | L52: 44562 | M52: 45291 | N52: КГД МФ РК | O52: 590300017601 | P52: 210540030240 | Q52: ТОО "CITY-17" | R52: N41201 | S52: Субъекты среднего предпринимательства | T52: УНА | U52: 1.908115e+08 | V52: 0 | W52: 0 | X52: 136499647 | Y52: 0 | Z52: 0 | AA52: 54311851 | AB52: 0 | AC52: 0 | AD52: 0 | AE52: 0 | AF52: 0 | AG52: 0 | AH52: 0 | AI52: 0 | AJ52: 174763986 | AK52: 45762 | AL52: #N/A | AM52: #N/A
A53: =CONCATENATE(C53,"-",P53,"-",G53) -> 30xx-190840008556-90 | B53: 3001 ДГД по Карагандинской области | C53: 30xx | D53: ИНИС | E53: Управление крупных налогоплательщиков Управление крупных налогоплательщиков | F53: Усимбекова А.У. | G53: 90 | H53: 45755 | I53: 46036 | J53: Комплексная | K53: Нет | L53: 43831 | M53: 45657 | N53: Другие заявления налогоплательщика | O53: 391700319134 | P53: 190840008556 | Q53: ТОО "QazTehna" | R53: N29101 | S53: Субъекты крупного предпринимательства | T53: ДКН/СД | U53: 1.8350211e+08 | V53: 0 | W53: 0 | X53: 138901633 | Y53: 0 | Z53: 0 | AA53: 44600481 | AB53: 0 | AC53: 0 | AD53: 0 | AE53: 0 | AF53: 0 | AG53: 0 | AH53: 0 | AI53: 0 | AJ53: 0 | AK53: #N/A | AL53: 2025г. | AM53: #N/A
A54: =CONCATENATE(C54,"-",P54,"-",G54) -> 30xx-110440020754-300120250911TAC0002 | B54: 3001 ДГД по Карагандинской области | C54: 30xx | D54: ИСНА | E54: Отдел аудита №1 | F54: Рахимберлин Улан Амантайулы | G54: 300120250911TAC0002 | H54: 45911 | J54: Тематическая проверка | L54: 44562 | M54: 45657 | N54: КГД МФ РК | O54: 302000317728 | P54: 110440020754 | Q54: ТОО "Domplast" | T54: УНА | U54: 1.7431665e+08 | V54: 0 | W54: 0 | X54: 1.5249592e+08 | Y54: 0 | Z54: 0 | AA54: 21820737 | AB54: 0 | AC54: 0 | AD54: 0 | AE54: 0 | AF54: 0 | AG54: 0 | AH54: 0 | AI54: 0 | AJ54: 0
A55: =CONCATENATE(C55,"-",P55,"-",G55) -> 60xx-150340019152-600120250722TAC0085 | B55: 6001 ДГД по г.Алматы | C55: 60xx | D55: ИСНА | E55: Отдел аудита №4 | F55: Калекенова Куралай Мухамбеталиевна | G55: 600120250722TAC0085 | H55: 45860 | J55: Тематическая проверка | L55: 44197 | M55: 45657 | N55: КГД МФ РК | O55: 600400692011 | P55: 150340019152 | Q55: ТОО "PARASAT CAPITAL" | T55: УНА | U55: 1.7417939e+08 | V55: 0 | W55: 0 | X55: 1.4692338e+08 | Y55: 0 | Z55: 0 | AA55: 27256013 | AB55: 0 | AC55: 0 | AD55: 0 | AE55: 0 | AF55: 0 | AG55: 0 | AH55: 0 | AI55: 0 | AJ55: 24962865
A56: =CONCATENATE(C56,"-",P56,"-",G56) -> 09xx-50540004574-88 | B56: 901 ДГД по Алматинской области | C56: 09xx | D56: ИНИС | E56: Отдел аудита №1 | F56: Агалиев Е.С. | G56: 88 | H56: 45824 | I56: 46098 | J56: Тематическая | K56: Нет | L56: 44927 | M56: 45657 | N56: КГД МФ РК | O56: 600300531273 | P56: 50540004574 | Q56: ТОО "ASIAN BEVERAGE COMPANY" | R56: N11010 | S56: Субъекты среднего предпринимательства | T56: УНА | U56: 168071000 | V56: 0 | W56: 0 | X56: 129552340 | Y56: 0 | Z56: 0 | AA56: 38518660 | AB56: 0 | AC56: 0 | AD56: 0 | AE56: 0 | AF56: 0 | AG56: 0 | AH56: 0 | AI56: 0 | AJ56: 0 | AK56: 45821 | AL56: #N/A | AM56: 50540004574
A57: =CONCATENATE(C57,"-",P57,"-",G57) -> 72xx-140240021423-720120251113TAC0002 | B57: 7201 ДГД по области Улытау | C57: 72xx | D57: ИСНА | E57: Отдел аудита | F57: Шайхыспарова Багила Асангазыевна | G57: 720120251113TAC0002 | H57: 45974 | J57: Тематическая проверка | L57: 44562 | M57: 45657 | N57: Решение налогового органа | O57: 580500216909 | P57: 140240021423 | Q57: ТОО "А COMPANY" | T57: УНА | U57: 1.5885571e+08 | V57: 0 | W57: 0 | X57: 118975762 | Y57: 0 | Z57: 0 | AA57: 39879951 | AB57: 0 | AC57: 0 | AD57: 0 | AE57: 0 | AF57: 0 | AG57: 0 | AH57: 0 | AI57: 0 | AJ57: 0
A58: =CONCATENATE(C58,"-",P58,"-",G58) -> 06xx-150840022168-060120251030TAC0155 | B58: 0601 ДГД по Актюбинской области | C58: 06xx | D58: ИСНА | E58: Отдел аудита | F58: Бактиярова Гульжахан Максатовна | G58: 060120251030TAC0155 | H58: 45960 | J58: Тематическая проверка | L58: 44927 | M58: 45291 | N58: КГД МФ РК | O58: 061800349962 | P58: 150840022168 | Q58: ТОО "Акшатау ПромСнабСтрой" | T58: УНА | U58: 1.5254594e+08 | V58: 0 | W58: 0 | X58: 1.1037578e+08 | Y58: 0 | Z58: 0 | AA58: 42170165 | AB58: 0 | AC58: 0 | AD58: 0 | AE58: 0 | AF58: 0 | AG58: 0 | AH58: 0 | AI58: 0 | AJ58: 0
A59: =CONCATENATE(C59,"-",P59,"-",G59) -> 58xx-10340004024-580120250902TAC0001 | B59: 5801 ДГД по Туркестанской области | C59: 58xx | D59: ИСНА | E59: Отдел аудита | F59: Елібай Рафаэль Сәуірбекұлы | G59: 580120250902TAC0001 | H59: 45902 | J59: Тематическая проверка | L59: 44562 | M59: 44926 | N59: КГД МФ РК | O59: 582100015458 | P59: 10340004024 | Q59: ТОО "Оңтүстік-құрылыс-сервис" | T59: УНА | U59: 1.495091e+08 | V59: 0 | W59: 0 | X59: 1.480667e+08 | Y59: 0 | Z59: 0 | AA59: 1442399.8 | AB59: 0 | AC59: 0 | AD59: 0 | AE59: 0 | AF59: 0 | AG59: 0 | AH59: 0 | AI59: 0 | AJ59: 950433907
A60: =CONCATENATE(C60,"-",P60,"-",G60) -> 62xx-150440000797-480 | B60: 6201 ДГД по г. Астана | C60: 62xx | D60: ИНИС | E60: отдел аудита № 2 | F60: Несипбай Ж.М. | G60: 480 | H60: 45813 | I60: 46080 | J60: Тематическая | K60: Нет | L60: 44927 | M60: 45291 | N60: КГД МФ РК | O60: 620200480121 | P60: 150440000797 | Q60: ТОО "СтройДеЛюкс" | R60: N41201 | S60: Субъекты среднего предпринимательства | T60: УНА | U60: 1.4083604e+08 | V60: 0 | W60: 0 | X60: 102512340 | Y60: 0 | Z60: 0 | AA60: 38323697 | AB60: 0 | AC60: 0 | AD60: 0 | AE60: 0 | AF60: 0 | AG60: 0 | AH60: 0 | AI60: 0 | AJ60: 0 | AK60: 45806 | AL60: #N/A | AM60: #N/A
A61: =CONCATENATE(C61,"-",P61,"-",G61) -> 62xx-201240028902-620120250911TAC0026 | B61: 6201 ДГД по г. Астана | C61: 62xx | D61: ИСНА | E61: Отдел аудита №2 | F61: Несіпбай Жалғас Маратұлы | G61: 620120250911TAC0026 | H61: 45911 | J61: Тематическая проверка | L61: 44562 | M61: 45657 | N61: КГД МФ РК | O61: 331000093485 | P61: 201240028902 | Q61: ТОО "KAUSAR BUILDING" | T61: УНА | U61: 1.1445999e+08 | V61: 0 | W61: 0 | X61: 96039362 | Y61: 0 | Z61: 0 | AA61: 18420626 | AB61: 0 | AC61: 0 | AD61: 0 | AE61: 0 | AF61: 0 | AG61: 0 | AH61: 0 | AI61: 0 | AJ61: 0
A62: =CONCATENATE(C62,"-",P62,"-",G62) -> 06xx-20714551508-060120251222TAC0002 | B62: 0601 ДГД по Актюбинской области | C62: 06xx | D62: ИСНА | E62: Отдел аудита | F62: Умарова Маржан | G62: 060120251222TAC0002 | H62: 46013 | J62: Тематическая проверка | L62: 44927 | M62: 45657 | N62: КГД МФ РК | O62: 061822159219 | P62: 20714551508 | Q62: ЕМЕЛЬЯНЕНКО ВЛАДИМИР ОЛЕГОВИЧ | T62: УНА | U62: 1.1099992e+08 | V62: 0 | W62: 0 | X62: 90482232 | Y62: 0 | Z62: 0 | AA62: 20517688 | AB62: 0 | AC62: 0 | AD62: 0 | AE62: 0 | AF62: 0 | AG62: 0 | AH62: 0 | AI62: 0 | AJ62: 0
A63: =CONCATENATE(C63,"-",P63,"-",G63) -> 59xx-40140004756-590120250908TAC0006 | B63: 5901 ДГД по г. Шымкент | C63: 59xx | D63: ИСНА | E63: Отдел ЭКНА | F63: Хайтметов Бабур Авазханович | G63: 590120250908TAC0006 | H63: 45908 | J63: Комплексная проверка | L63: 44562 | M63: 45838 | N63: Другие заявления налогоплательщика | O63: 582100230322 | P63: 40140004756 | Q63: Коммунальное государственное учреждение "Специализированная школа-интернат "Өнер" имени Батырбека Отепа" управления образования Туркестанской области | T63: УНА | U63: 1.1016858e+08 | V63: 0 | W63: 0 | X63: 109145461 | Y63: 0 | Z63: 0 | AA63: 1023118.7 | AB63: 0 | AC63: 0 | AD63: 0 | AE63: 0 | AF63: 0 | AG63: 0 | AH63: 0 | AI63: 0 | AJ63: 0
A64: =CONCATENATE(C64,"-",P64,"-",G64) -> 62xx-170840012500-620120250725TAC0002 | B64: 6201 ДГД по г. Астана | C64: 62xx | D64: ИСНА | E64: Отдел аудита №1 | F64: Джаканов Нуржан Манапович | G64: 620120250725TAC0002 | H64: 45863 | J64: Тематическая проверка | L64: 44562 | M64: 45657 | N64: КГД МФ РК | O64: 620200562108 | P64: 170840012500 | Q64: ТОО "M-HARTEK (М-ХАРТЕК)" | T64: УНА | U64: 1.0997077e+08 | V64: 0 | W64: 0 | X64: 83781911 | Y64: 0 | Z64: 0 | AA64: 26188857 | AB64: 0 | AC64: 0 | AD64: 0 | AE64: 0 | AF64: 0 | AG64: 0 | AH64: 0 | AI64: 0 | AJ64: 0
A65: =CONCATENATE(C65,"-",P65,"-",G65) -> 58xx-30340003832-580120251225TAC0001 | B65: 5801 ДГД по Туркестанской области | C65: 58xx | D65: ИСНА | E65: Отдел крупных налогоплательщиков | F65: Ескеров Ер-таргын Серикович | G65: 580120251225TAC0001 | H65: 46016 | J65: Тематическая проверка | L65: 44562 | M65: 45657 | N65: КГД МФ РК | O65: 581400000656 | P65: 30340003832 | Q65: ТОО "АҚ-ЖОЛ" | T65: УНА | U65: 1.0525763e+08 | V65: 0 | W65: 0 | X65: 91628950 | Y65: 0 | Z65: 0 | AA65: 13628679 | AB65: 0 | AC65: 0 | AD65: 0 | AE65: 0 | AF65: 0 | AG65: 0 | AH65: 0 | AI65: 0 | AJ65: 0
A66: =CONCATENATE(C66,"-",P66,"-",G66) -> 71xx-200440006976-710120251205TAC0001 | B66: 7101 ДГД по области Абай | C66: 71xx | D66: ИСНА | E66: Отдел ЭКНА | F66: Ержепбаева Шолпан Жумахановна | G66: 710120251205TAC0001 | H66: 45996 | J66: Тематическая проверка | L66: 44562 | M66: 45657 | N66: КГД МФ РК | O66: 182700276230 | P66: 200440006976 | Q66: ТОО "KREPTO&MONOLIT" | T66: УНА | U66: 1.0373182e+08 | V66: 0 | W66: 0 | X66: 85500075 | Y66: 0 | Z66: 0 | AA66: 18231748 | AB66: 0 | AC66: 0 | AD66: 0 | AE66: 0 | AF66: 0 | AG66: 0 | AH66: 0 | AI66: 0 | AJ66: 0
A67: =CONCATENATE(C67,"-",P67,"-",G67) -> 48xx-950440000566-480120250728TAC0015 | B67: 4801 ДГД по Северо-Казахстанской области | C67: 48xx | D67: ИСНА | E67: Отдел аудита №2 | F67: Шакенов Бахтияр Кабдуллаевич | G67: 480120250728TAC0015 | H67: 45866 | J67: Тематическая проверка | L67: 44562 | M67: 45657 | N67: КГД МФ РК | O67: 481400046532 | P67: 950440000566 | Q67: ТОО "Основание" | T67: УНА | U67: 1.0180685e+08 | V67: 0 | W67: 0 | X67: 86819804 | Y67: 0 | Z67: 0 | AA67: 14987050 | AB67: 0 | AC67: 0 | AD67: 0 | AE67: 0 | AF67: 0 | AG67: 0 | AH67: 0 | AI67: 0 | AJ67: 0
A68: =CONCATENATE(C68,"-",P68,"-",G68) -> 30xx-100240010867-300120250930TAC0001 | B68: 3001 ДГД по Карагандинской области | C68: 30xx | D68: ИСНА | E68: Отдел аудита №2 | F68: Алибекова Алтынай Актаевна | G68: 300120250930TAC0001 | H68: 45930 | J68: Тематическая проверка | L68: 44927 | M68: 45291 | N68: КГД МФ РК | O68: 301300212245 | P68: 100240010867 | Q68: ТОО "Ботақара Құрылыс" | T68: УНА | U68: 96081766 | V68: 0 | W68: 0 | X68: 69732625 | Y68: 0 | Z68: 0 | AA68: 26349141 | AB68: 0 | AC68: 0 | AD68: 0 | AE68: 0 | AF68: 0 | AG68: 0 | AH68: 0 | AI68: 0 | AJ68: 0
A69: =CONCATENATE(C69,"-",P69,"-",G69) -> 59xx-41240002240-590120251225TAC0121 | B69: 5901 ДГД по г. Шымкент | C69: 59xx | D69: ИСНА | E69: Отдел ЭКНА | F69: Серғұлыұлы Ақынжан | G69: 590120251225TAC0121 | H69: 46016 | J69: Тематическая проверка | L69: 44927 | M69: 45291 | N69: КГД МФ РК | O69: 582100241790 | P69: 41240002240 | Q69: ТОО "Корпорация Бастау" | T69: УНА | U69: 78702234 | V69: 0 | W69: 0 | X69: 57271867 | Y69: 0 | Z69: 0 | AA69: 21430368 | AB69: 0 | AC69: 0 | AD69: 0 | AE69: 0 | AF69: 0 | AG69: 0 | AH69: 0 | AI69: 0 | AJ69: 0
A70: =CONCATENATE(C70,"-",P70,"-",G70) -> 70xx-81040013830-28 | B70: 7001 ДГД по области Жетысу | C70: 70xx | D70: ИНИС | E70: Отдел ЭКНА | F70: Тлеубаева Ж.Р. | G70: 28 | H70: 45807 | I70: 46111 | J70: Тематическая | K70: Нет | L70: 44562 | M70: 45657 | N70: Другие заявления налогоплательщика | O70: 91500212906 | P70: 81040013830 | Q70: ТОО "Бағалы - Алакөл" | R70: N43298 | S70: Субъекты малого предпринимательства | T70: УНА | U70: 78554483 | V70: 0 | W70: 0 | X70: 53590950 | Y70: 0 | Z70: 0 | AA70: 24963533 | AB70: 0 | AC70: 0 | AD70: 0 | AE70: 0 | AF70: 0 | AG70: 0 | AH70: 0 | AI70: 0 | AJ70: 0 | AK70: #N/A | AL70: #N/A | AM70: #N/A
A71: =CONCATENATE(C71,"-",P71,"-",G71) -> 59xx-190540011466-590120250730TAC0012 | B71: 5901 ДГД по г. Шымкент | C71: 59xx | D71: ИСНА | E71: Отдел аудита №1 | F71: Лим Ольга Петровна | G71: 590120250730TAC0012 | H71: 45868 | J71: Тематическая проверка | L71: 44197 | M71: 45657 | N71: КГД МФ РК | O71: 590500003818 | P71: 190540011466 | Q71: ТОО "Управляющая компания "Shymkent Bus" | T71: УНА | U71: 77439393 | V71: 0 | W71: 0 | X71: 66565315 | Y71: 0 | Z71: 0 | AA71: 10874078 | AB71: 0 | AC71: 0 | AD71: 0 | AE71: 0 | AF71: 0 | AG71: 0 | AH71: 0 | AI71: 0 | AJ71: 4630197169
A72: =CONCATENATE(C72,"-",P72,"-",G72) -> 45xx-230540009830-450120251219TAC0001 | B72: 4501 ДГД по Павлодарской области | C72: 45xx | D72: ИСНА | E72: Отдел аудита | F72: Айдарова Айнур Темиржановна | G72: 450120251219TAC0001 | H72: 46010 | J72: Тематическая проверка | L72: 45056 | M72: 45291 | N72: Другие органы государственных доходов | O72: 451500381043 | P72: 230540009830 | Q72: ТОО "Алтын Астык Pvl" | T72: УНА | U72: 76734914 | V72: 0 | W72: 0 | X72: 55051030 | Y72: 0 | Z72: 0 | AA72: 21683884 | AB72: 0 | AC72: 0 | AD72: 0 | AE72: 0 | AF72: 0 | AG72: 0 | AH72: 0 | AI72: 0 | AJ72: 0
A73: =CONCATENATE(C73,"-",P73,"-",G73) -> 60xx-50440011682-600120250804TAC0037 | B73: 6001 ДГД по г.Алматы | C73: 60xx | D73: ИСНА | E73: Отдел аудита №3 | F73: Нуржигитов Нурбакыт Сейткулулы | G73: 600120250804TAC0037 | H73: 45873 | J73: Тематическая проверка | L73: 44562 | M73: 45657 | N73: КГД МФ РК | O73: 600700555836 | P73: 50440011682 | Q73: ТОО "Компания "Құрылысшы-Проект" | T73: УНА | U73: 73448608 | V73: 0 | W73: 0 | X73: 58991338 | Y73: 0 | Z73: 0 | AA73: 14457270 | AB73: 0 | AC73: 0 | AD73: 0 | AE73: 0 | AF73: 0 | AG73: 0 | AH73: 0 | AI73: 0 | AJ73: 107813934
A74: =CONCATENATE(C74,"-",P74,"-",G74) -> 62xx-120240019894-451 | B74: 6201 ДГД по г. Астана | C74: 62xx | D74: ИНИС | E74: отдел аудита № 2 | F74: Несипбай Ж.М. | G74: 451 | H74: 45793 | I74: 46076 | J74: Тематическая | K74: Да | L74: 44562 | M74: 45291 | N74: КГД МФ РК | O74: 582200048150 | P74: 120240019894 | Q74: ТОО "Теплоснабторг-Сервис" | R74: N42990 | S74: Субъекты малого предпринимательства | T74: УНА | U74: 68423238 | V74: 0 | W74: 0 | X74: 47086468 | Y74: 0 | Z74: 0 | AA74: 21336770 | AB74: 0 | AC74: 0 | AD74: 0 | AE74: 0 | AF74: 0 | AG74: 0 | AH74: 0 | AI74: 0 | AJ74: 0 | AK74: 45782 | AL74: #N/A | AM74: #N/A
A75: =CONCATENATE(C75,"-",P75,"-",G75) -> 18xx-80240004717-180120250822TAC0011 | B75: 1801 ДГД по Восточно-Казахстанской области | C75: 18xx | D75: ИСНА | E75: Отдел аудита №2 | F75: Ильяшенко Жанна Евгеньевна | G75: 180120250822TAC0011 | H75: 45891 | J75: Тематическая проверка | L75: 44562 | M75: 45657 | N75: КГД МФ РК | O75: 330900211934 | P75: 80240004717 | Q75: ТОО "Ostara Group" | T75: УНА | U75: 65413506 | V75: 0 | W75: 0 | X75: 50008744 | Y75: 0 | Z75: 0 | AA75: 15404762 | AB75: 0 | AC75: 0 | AD75: 0 | AE75: 0 | AF75: 0 | AG75: 0 | AH75: 0 | AI75: 0 | AJ75: 0
A76: =CONCATENATE(C76,"-",P76,"-",G76) -> 58xx-240640010295-580120251110TAC0002 | B76: 5801 ДГД по Туркестанской области | C76: 58xx | D76: ИСНА | E76: Отдел аудита | F76: Байдарбеков Бекболат Калиевич | G76: 580120251110TAC0002 | H76: 45971 | J76: Тематическая проверка | L76: 45292 | M76: 45657 | N76: КГД МФ РК | O76: 581200234722 | P76: 240640010295 | Q76: ТОО "Global Fruits KZ" | T76: УНА | U76: 64976760 | V76: 0 | W76: 0 | X76: 54087871 | Y76: 0 | Z76: 0 | AA76: 10888889 | AB76: 0 | AC76: 0 | AD76: 0 | AE76: 0 | AF76: 0 | AG76: 0 | AH76: 0 | AI76: 0 | AJ76: 2189701
A77: =CONCATENATE(C77,"-",P77,"-",G77) -> 30xx-70540008481-163 | B77: 3001 ДГД по Карагандинской области | C77: 30xx | D77: ИНИС | E77: Управление аудита Отдел аудита №1 | F77: Рахимберлин У.А. | G77: 163 | H77: 45800 | I77: 46087 | J77: Тематическая | K77: Нет | L77: 44197 | M77: 45657 | N77: КГД МФ РК | O77: 302600220195 | P77: 70540008481 | Q77: ТОО "Mustang service 2030" | R77: N46630 | S77: Субъекты микро предпринимательства | T77: УНА | U77: 64025365 | V77: 0 | W77: 0 | X77: 42876793 | Y77: 0 | Z77: 0 | AA77: 21148572 | AB77: 0 | AC77: 0 | AD77: 0 | AE77: 0 | AF77: 0 | AG77: 0 | AH77: 0 | AI77: 0 | AJ77: 11972925 | AK77: 45797 | AL77: #N/A | AM77: #N/A
A78: =CONCATENATE(C78,"-",P78,"-",G78) -> 60xx-60640012075-600120250808TAC0051 | B78: 6001 ДГД по г.Алматы | C78: 60xx | D78: ИСНА | E78: Отдел аудита №4 | F78: Кулбаев Алмат Байбатырович | G78: 600120250808TAC0051 | H78: 45877 | J78: Тематическая проверка | L78: 44562 | M78: 45657 | N78: КГД МФ РК | O78: 582100261564 | P78: 60640012075 | Q78: ТОО "NSS Group" | T78: УНА | U78: 61717422 | V78: 0 | W78: 0 | X78: 41860324 | Y78: 0 | Z78: 0 | AA78: 19857098 | AB78: 0 | AC78: 0 | AD78: 0 | AE78: 0 | AF78: 0 | AG78: 0 | AH78: 0 | AI78: 0 | AJ78: 59190000
A79: =CONCATENATE(C79,"-",P79,"-",G79) -> 70xx-170341017003-27 | B79: 7001 ДГД по области Жетысу | C79: 70xx | D79: ИНИС | E79: Отдел аудита | F79: Сабдикенова С.С. | G79: 27 | H79: 45800 | I79: 46092 | J79: Тематическая | K79: Нет | L79: 44197 | M79: 45657 | N79: Другие заявления налогоплательщика | O79: 92200250570 | P79: 170341017003 | Q79: Казахстанский филиал "ТОО Корпорация Луцяо провинции Шаньдун" | R79: N42111 | S79: Субъекты среднего предпринимательства | T79: УНА | U79: 61547215 | V79: 0 | W79: 0 | X79: 45696987 | Y79: 0 | Z79: 0 | AA79: 15850228 | AB79: 0 | AC79: 0 | AD79: 0 | AE79: 0 | AF79: 0 | AG79: 0 | AH79: 0 | AI79: 0 | AJ79: 0 | AK79: #N/A | AL79: #N/A | AM79: #N/A
A80: =CONCATENATE(C80,"-",P80,"-",G80) -> 59xx-340005962-590120251223TAC0332 | B80: 5901 ДГД по г. Шымкент | C80: 59xx | D80: ИСНА | E80: Отдел ЭКНА | F80: Айдарұлы Жәнібек | G80: 590120251223TAC0332 | H80: 46014 | J80: Тематическая проверка | L80: 44927 | M80: 45657 | N80: Другие заявления налогоплательщика | O80: 581100028754 | P80: 340005962 | Q80: ТОО "Газовое хозяйство "Шымкентгаз" | T80: УНА | U80: 60115348 | V80: 0 | W80: 0 | X80: 58948598 | Y80: 0 | Z80: 0 | AA80: 1166750.5 | AB80: 0 | AC80: 0 | AD80: 0 | AE80: 0 | AF80: 0 | AG80: 0 | AH80: 0 | AI80: 0 | AJ80: 0
A81: =CONCATENATE(C81,"-",P81,"-",G81) -> 58xx-30240001624-580120260113TAC0005 | B81: 5801 ДГД по Туркестанской области | C81: 58xx | D81: ИСНА | E81: Отдел аудита | F81: Лесхан Мейірбек Лесханұлы | G81: 580120260113TAC0005 | H81: 46035 | J81: Тематическая проверка | L81: 44927 | M81: 45657 | N81: КГД МФ РК | O81: 582100220446 | P81: 30240001624 | Q81: ТОО "СтройЖолСервис Kz" | T81: УНА | U81: 57491351 | V81: 0 | W81: 0 | X81: 49513000 | Y81: 0 | Z81: 0 | AA81: 7978351.3 | AB81: 0 | AC81: 0 | AD81: 0 | AE81: 0 | AF81: 0 | AG81: 0 | AH81: 0 | AI81: 0 | AJ81: 0
A82: =CONCATENATE(C82,"-",P82,"-",G82) -> 39xx-10740002706-390120251209TAC0007 | B82: 3901 ДГД по Костанайской области | C82: 39xx | D82: ИСНА | E82: Отдел ЭКНА | F82: Оралова Кымбат Дюсюмбаевна | G82: 390120251209TAC0007 | H82: 46000 | J82: Тематическая проверка | L82: 44562 | M82: 45657 | N82: КГД МФ РК | O82: 391700076206 | P82: 10740002706 | Q82: ТОО "Светотехника - 1" | T82: УНА | U82: 56152350 | V82: 0 | W82: 0 | X82: 48603956 | Y82: 0 | Z82: 0 | AA82: 7548393.7 | AB82: 0 | AC82: 0 | AD82: 0 | AE82: 0 | AF82: 0 | AG82: 0 | AH82: 0 | AI82: 0 | AJ82: 0
A83: =CONCATENATE(C83,"-",P83,"-",G83) -> 09xx-220740029058-090120251016TAC0011 | B83: 0901 ДГД по Алматинской области | C83: 09xx | D83: ИСНА | E83: Отдел аудита №3 | F83: Алдарбергенов Алмат Талгатович | G83: 090120251016TAC0011 | H83: 45946 | J83: Тематическая проверка | L83: 44562 | M83: 45657 | N83: КГД МФ РК | O83: 600900828461 | P83: 220740029058 | Q83: ТОО "ПерспективаСтрой" | T83: УНА | U83: 54736410 | V83: 0 | W83: 0 | X83: 36886071 | Y83: 0 | Z83: 0 | AA83: 17850339 | AB83: 0 | AC83: 0 | AD83: 0 | AE83: 0 | AF83: 0 | AG83: 0 | AH83: 0 | AI83: 0 | AJ83: 0
A84: =CONCATENATE(C84,"-",P84,"-",G84) -> 59xx-970640006196-590120250728TAC0001 | B84: 5901 ДГД по г. Шымкент | C84: 59xx | D84: ИСНА | E84: Отдел ЭКНА | F84: Серғұлыұлы Ақынжан | G84: 590120250728TAC0001 | H84: 45866 | J84: Тематическая проверка | L84: 44562 | M84: 45657 | N84: КГД МФ РК | O84: 301200016263 | P84: 970640006196 | Q84: ТОО "Shymkent Group Строй" | T84: УНА | U84: 44546979 | V84: 0 | W84: 0 | X84: 33674637 | Y84: 0 | Z84: 0 | AA84: 10872342 | AB84: 0 | AC84: 0 | AD84: 0 | AE84: 0 | AF84: 0 | AG84: 0 | AH84: 0 | AI84: 0 | AJ84: 0
A85: =CONCATENATE(C85,"-",P85,"-",G85) -> 21xx-41140004937-210120250811TAC0001 | B85: 2101 ДГД по Жамбылской области | C85: 21xx | D85: ИСНА | E85: Отдел аудита | F85: Калыкулов Ерсин Аскербекович | G85: 210120250811TAC0001 | H85: 45880 | J85: Тематическая проверка | L85: 44562 | M85: 45657 | N85: КГД МФ РК | O85: 211500220354 | P85: 41140004937 | Q85: ТОО "ТАРАЗСТРОЙ-2004" | T85: УНА | U85: 34642039 | V85: 0 | W85: 0 | X85: 31799451 | Y85: 0 | Z85: 0 | AA85: 2842588.3 | AB85: 0 | AC85: 0 | AD85: 0 | AE85: 0 | AF85: 0 | AG85: 0 | AH85: 0 | AI85: 0 | AJ85: 0
A86: =CONCATENATE(C86,"-",P86,"-",G86) -> 60xx-130740008383-600120251016TAC0081 | B86: 6001 ДГД по г.Алматы | C86: 60xx | D86: ИСНА | E86: Отдел аудита №4 | F86: Естаев Нуртай Куанышбекұлы | G86: 600120251016TAC0081 | H86: 45946 | J86: Тематическая проверка | L86: 44562 | M86: 45657 | N86: КГД МФ РК | O86: 600700685416 | P86: 130740008383 | Q86: ТОО "Бизнес-инкубатор MOST" | T86: УНА | U86: 33654850 | V86: 0 | W86: 0 | X86: 28960000 | Y86: 0 | Z86: 0 | AA86: 4694850 | AB86: 0 | AC86: 0 | AD86: 0 | AE86: 0 | AF86: 0 | AG86: 0 | AH86: 0 | AI86: 0 | AJ86: 0
A87: =CONCATENATE(C87,"-",P87,"-",G87) -> 39xx-151040020928-209 | B87: 3901 ДГД по Костанайской области | C87: 39xx | D87: ИНИС | E87: Управление аудита | F87: Шейко Д.Е. | G87: 209 | H87: 45749 | I87: 46112 | J87: Тематическая | K87: Да | L87: 44562 | M87: 45291 | N87: КГД МФ РК | O87: 391700291026 | P87: 151040020928 | Q87: ТОО "ВикСер1" | R87: N46211 | S87: Субъекты среднего предпринимательства | T87: УНА | U87: 32930439 | V87: 0 | W87: 0 | X87: 24586164 | Y87: 0 | Z87: 0 | AA87: 8344274.7 | AB87: 0 | AC87: 0 | AD87: 0 | AE87: 0 | AF87: 0 | AG87: 0 | AH87: 0 | AI87: 0 | AJ87: 0 | AK87: 45747 | AL87: #N/A | AM87: #N/A
A88: =CONCATENATE(C88,"-",P88,"-",G88) -> 15xx-80340015499-150120251225TAC0002 | B88: 1501 ДГД по Атырауской области | C88: 15xx | D88: ИСНА | E88: Отдел аудита №1 | F88: Кулпейсов Шаттык Алпамысович | G88: 150120251225TAC0002 | H88: 46016 | J88: Тематическая проверка | L88: 44562 | M88: 45657 | N88: КГД МФ РК | O88: 151000030467 | P88: 80340015499 | Q88: ТОО "Атыраугидрогеология" | T88: УНА | U88: 32709947 | V88: 0 | W88: 0 | X88: 29220967 | Y88: 0 | Z88: 0 | AA88: 3488979.9 | AB88: 0 | AC88: 0 | AD88: 0 | AE88: 0 | AF88: 0 | AG88: 0 | AH88: 0 | AI88: 0 | AJ88: 0
A89: =CONCATENATE(C89,"-",P89,"-",G89) -> 62xx-960202450119-620120251201TAC0030 | B89: 6201 ДГД по г. Астана | C89: 62xx | D89: ИСНА | E89: Отдел аудита №1 | F89: Джаканов Нуржан Манапович | G89: 620120251201TAC0030 | H89: 45992 | J89: Тематическая проверка | L89: 44562 | M89: 45657 | N89: КГД МФ РК | O89: 620220958280 | P89: 960202450119 | Q89: АБИЛКАДИРОВА АЙГЕРИМ ЖАНАТОВНА | T89: УНА | U89: 32674666 | V89: 0 | W89: 0 | X89: 25785639 | Y89: 0 | Z89: 0 | AA89: 6889027.5 | AB89: 0 | AC89: 0 | AD89: 0 | AE89: 0 | AF89: 0 | AG89: 0 | AH89: 0 | AI89: 0 | AJ89: 0
A90: =CONCATENATE(C90,"-",P90,"-",G90) -> 58xx-11040005321-580120251205TAC0001 | B90: 5801 ДГД по Туркестанской области | C90: 58xx | D90: ИСНА | E90: Отдел аудита | F90: Утебаев Сеил Абдыхалыкулы | G90: 580120251205TAC0001 | H90: 45996 | J90: Тематическая проверка | L90: 44562 | M90: 45657 | N90: КГД МФ РК | O90: 580400000466 | P90: 11040005321 | Q90: ТОО "Нүрі-Л-Жетісай" | T90: УНА | U90: 31138177 | V90: 0 | W90: 0 | X90: 26400179 | Y90: 0 | Z90: 0 | AA90: 4737998 | AB90: 0 | AC90: 0 | AD90: 0 | AE90: 0 | AF90: 0 | AG90: 0 | AH90: 0 | AI90: 0 | AJ90: 0
A91: =CONCATENATE(C91,"-",P91,"-",G91) -> 60xx-40340009487-600120250728TAC0037 | B91: 6001 ДГД по г.Алматы | C91: 60xx | D91: ИСНА | E91: Отдел аудита №5 | F91: Есимханов Ержан Алтаевич | G91: 600120250728TAC0037 | H91: 45866 | J91: Тематическая проверка | L91: 44562 | M91: 45657 | N91: КГД МФ РК | O91: 620200237482 | P91: 40340009487 | Q91: ТОО "Elif Construction" | T91: УНА | U91: 30747986 | V91: 0 | W91: 0 | X91: 26381919 | Y91: 0 | Z91: 0 | AA91: 4366067.7 | AB91: 0 | AC91: 0 | AD91: 0 | AE91: 0 | AF91: 0 | AG91: 0 | AH91: 0 | AI91: 0 | AJ91: 0
A92: =CONCATENATE(C92,"-",P92,"-",G92) -> 60xx-71240002008-600120250717TAC0004 | B92: 6001 ДГД по г.Алматы | C92: 60xx | D92: ИСНА | E92: Отдел аудита №4 | F92: Естаев Нуртай Куанышбекұлы | G92: 600120250717TAC0004 | H92: 45855 | J92: Тематическая проверка | L92: 43831 | M92: 45657 | N92: КГД МФ РК | O92: 600900600194 | P92: 71240002008 | Q92: АО "Кристалл Менеджмент" | T92: УНА | U92: 30591058 | V92: 0 | W92: 0 | X92: 25539926 | Y92: 0 | Z92: 0 | AA92: 5051132.6 | AB92: 0 | AC92: 0 | AD92: 0 | AE92: 0 | AF92: 0 | AG92: 0 | AH92: 0 | AI92: 0 | AJ92: 0
A93: =CONCATENATE(C93,"-",P93,"-",G93) -> 60xx-40140004944-600120250811TAC0003 | B93: 6001 ДГД по г.Алматы | C93: 60xx | D93: ИСНА | E93: Отдел аудита №3 | F93: Нукетаева Сауле Жусуппековна | G93: 600120250811TAC0003 | H93: 45880 | J93: Тематическая проверка | L93: 44562 | M93: 45657 | N93: КГД МФ РК | O93: 090500215512 | P93: 40140004944 | Q93: ТОО "Специализированный рынок "Жібек жолы" | T93: УНА | U93: 29135640 | V93: 0 | W93: 0 | X93: 23256983 | Y93: 0 | Z93: 0 | AA93: 5878656.7 | AB93: 0 | AC93: 0 | AD93: 0 | AE93: 0 | AF93: 0 | AG93: 0 | AH93: 0 | AI93: 0 | AJ93: 0
A94: =CONCATENATE(C94,"-",P94,"-",G94) -> 58xx-220140006939-580120251126TAC0001 | B94: 5801 ДГД по Туркестанской области | C94: 58xx | D94: ИСНА | E94: Отдел аудита | F94: Байдарбеков Бекболат Калиевич | G94: 580120251126TAC0001 | H94: 45987 | J94: Тематическая проверка | L94: 44575 | M94: 45657 | N94: КГД МФ РК | O94: 580500220830 | P94: 220140006939 | Q94: ТОО "QAZAQ BITUM Processing" | T94: УНА | U94: 27414006 | V94: 0 | W94: 0 | X94: 21238365 | Y94: 0 | Z94: 0 | AA94: 6175641.3 | AB94: 0 | AC94: 0 | AD94: 0 | AE94: 0 | AF94: 0 | AG94: 0 | AH94: 0 | AI94: 0 | AJ94: 0
A95: =CONCATENATE(C95,"-",P95,"-",G95) -> 39xx-40840003426-366 | B95: 3901 ДГД по Костанайской области | C95: 39xx | D95: ИНИС | E95: Управление аудита | F95: Каримов С.А. | G95: 366 | H95: 45789 | I95: 46112 | J95: Тематическая | K95: Нет | L95: 44562 | M95: 45657 | N95: КГД МФ РК | O95: 391700056443 | P95: 40840003426 | Q95: ТОО "Қостанай жолдары" | R95: N42111 | S95: Субъекты крупного предпринимательства | T95: УНА | U95: 27005951 | V95: 0 | W95: 0 | X95: 23632690 | Y95: 0 | Z95: 0 | AA95: 3373261.5 | AB95: 0 | AC95: 0 | AD95: 0 | AE95: 0 | AF95: 0 | AG95: 0 | AH95: 0 | AI95: 0 | AJ95: 0 | AK95: 45785 | AL95: #N/A | AM95: #N/A
A96: =CONCATENATE(C96,"-",P96,"-",G96) -> 15xx-151040003452-150120260123TAC0191 | B96: 1501 ДГД по Атырауской области | C96: 15xx | D96: ИСНА | E96: Отдел аудита №1 | F96: Нұрлыбай Мейрамбек Нұрлыбайұлы | G96: 150120260123TAC0191 | H96: 46045 | J96: Комплексная проверка | L96: 44197 | M96: 46017 | N96: Заявление налогоплательщика на ликвидацию | O96: 430600031793 | P96: 151040003452 | Q96: ТОО "Маңғыстау Жарық" | T96: УНА | U96: 26393400 | V96: 0 | W96: 0 | X96: 25080751 | Y96: 0 | Z96: 0 | AA96: 1312649.4 | AB96: 0 | AC96: 0 | AD96: 0 | AE96: 0 | AF96: 0 | AG96: 0 | AH96: 0 | AI96: 0 | AJ96: 0
A97: =CONCATENATE(C97,"-",P97,"-",G97) -> 59xx-40340001878-79 | B97: 5901 ДГД по г. Шымкент | C97: 59xx | D97: ИНИС | E97: отдел аудита № 2 | F97: Айдарулы Ж. | G97: 79 | H97: 45748 | I97: 46111 | J97: Тематическая | K97: Нет | L97: 44562 | M97: 45657 | N97: Другие заявления налогоплательщика | O97: 270100222156 | P97: 40340001878 | Q97: ТОО "Адал Арна" | R97: N42111 | S97: Субъекты среднего предпринимательства | T97: УНА | U97: 25418153 | V97: 0 | W97: 0 | X97: 19287987 | Y97: 0 | Z97: 0 | AA97: 6130165.7 | AB97: 0 | AC97: 0 | AD97: 0 | AE97: 0 | AF97: 0 | AG97: 0 | AH97: 0 | AI97: 0 | AJ97: 0 | AK97: #N/A | AL97: #N/A | AM97: #N/A
